Workbook
Name IQ_CH: 110000
Name IQ_CQ: 5000
Name IQ_CY: 10000
Name IQ_DAILY: 500000
Name IQ_FH: 100000
Name IQ_FQ: 500
Name IQ_FY: 1000
Name IQ_LTM: 2000
Name IQ_MONTH: 15000
Name IQ_NTM: 6000
Name IQ_WEEK: 50000
Name IQ_YTD: 3000

Sheet Returns_Wide
A1: Simple Returns
A2: Formula: Price_t / Price_(t-1) - 1
A4: Date | B4: =Volume!B4 -> TZTA Comdty | C4: =Volume!C4 -> TZTB Comdty | D4: =Volume!D4 -> TZT1 Comdty | E4: =Volume!#REF! -> #REF! | F4: =Volume!#REF! -> #REF! | G4: =Volume!E4 -> FNA Comdty | H4: =Volume!F4 -> FNB Comdty | I4: =Volume!G4 -> MO1 Comdty | J4: =Volume!H4 -> MO2 Comdty | K4: =Volume!#REF! -> #REF! | L4: =Volume!#REF! -> #REF! | M4: =Volume!#REF! -> #REF! | N4: =Volume!I4 -> XA1 Comdty | O4: =Volume!#REF! -> #REF! | P4: =Volume!#REF! -> #REF! | Q4: =Volume!#REF! -> #REF! | R4: =Volume!#REF! -> #REF! | S4: =Volume!#REF! -> #REF! | T4: =Volume!J4 -> MO1 Comdty | U4: =Volume!K4 -> 0
A5: {=_xll.BDH("AAPL US Equity","PX_LAST",$B$3,$B$4,"Per=D")} -> #N/A Mandatory parameter [STARTDATE] cannot be empty
B6: =IFERROR(Volume!B6/Volume!B5-1,"") | C6: =IFERROR(Volume!C6/Volume!C5-1,"") | D6: =IFERROR(Volume!D6/Volume!D5-1,"") | E6: =IFERROR(Volume!#REF!/Volume!#REF!-1,"") | F6: =IFERROR(Volume!#REF!/Volume!#REF!-1,"") | G6: =IFERROR(Volume!E6/Volume!E5-1,"") | H6: =IFERROR(Volume!F6/Volume!F5-1,"") | I6: =IFERROR(Volume!G6/Volume!G5-1,"") | J6: =IFERROR(Volume!H6/Volume!H5-1,"") | K6: =IFERROR(Volume!#REF!/Volume!#REF!-1,"") | L6: =IFERROR(Volume!#REF!/Volume!#REF!-1,"") | M6: =IFERROR(Volume!#REF!/Volume!#REF!-1,"") | N6: =IFERROR(Volume!I6/Volume!I5-1,"") | O6: =IFERROR(Volume!#REF!/Volume!#REF!-1,"") | P6: =IFERROR(Volume!#REF!/Volume!#REF!-1,"") | Q6: =IFERROR(Volume!#REF!/Volume!#REF!-1,"") | R6: =IFERROR(Volume!#REF!/Volume!#REF!-1,"") | S6: =IFERROR(Volume!#REF!/Volume!#REF!-1,"") | T6: =IFERROR(Volume!J6/Volume!J5-1,"") | U6: =IFERROR(Volume!K6/Volume!K5-1,"")
B7: =IFERROR(Volume!B7/Volume!B6-1,"") | C7: =IFERROR(Volume!C7/Volume!C6-1,"") | D7: =IFERROR(Volume!D7/Volume!D6-1,"") -> 0.41962505 | E7: =IFERROR(Volume!#REF!/Volume!#REF!-1,"") | F7: =IFERROR(Volume!#REF!/Volume!#REF!-1,"") | G7: =IFERROR(Volume!E7/Volume!E6-1,"") | H7: =IFERROR(Volume!F7/Volume!F6-1,"") | I7: =IFERROR(Volume!G7/Volume!G6-1,"") -> -0.51935484 | J7: =IFERROR(Volume!H7/Volume!H6-1,"") | K7: =IFERROR(Volume!#REF!/Volume!#REF!-1,"") | L7: =IFERROR(Volume!#REF!/Volume!#REF!-1,"") | M7: =IFERROR(Volume!#REF!/Volume!#REF!-1,"") | N7: =IFERROR(Volume!I7/Volume!I6-1,"") -> -0.37435897 | O7: =IFERROR(Volume!#REF!/Volume!#REF!-1,"") | P7: =IFERROR(Volume!#REF!/Volume!#REF!-1,"") | Q7: =IFERROR(Volume!#REF!/Volume!#REF!-1,"") | R7: =IFERROR(Volume!#REF!/Volume!#REF!-1,"") | S7: =IFERROR(Volume!#REF!/Volume!#REF!-1,"") | T7: =IFERROR(Volume!J7/Volume!J6-1,"") -> 0.02553542 | U7: =IFERROR(Volume!K7/Volume!K6-1,"")
B8: =IFERROR(Volume!B8/Volume!B7-1,"") | C8: =IFERROR(Volume!C8/Volume!C7-1,"") | D8: =IFERROR(Volume!D8/Volume!D7-1,"") -> -0.43832537 | E8: =IFERROR(Volume!#REF!/Volume!#REF!-1,"") | F8: =IFERROR(Volume!#REF!/Volume!#REF!-1,"") | G8: =IFERROR(Volume!E8/Volume!E7-1,"") | H8: =IFERROR(Volume!F8/Volume!F7-1,"") | I8: =IFERROR(Volume!G8/Volume!G7-1,"") -> -0.28187919 | J8: =IFERROR(Volume!H8/Volume!H7-1,"") | K8: =IFERROR(Volume!#REF!/Volume!#REF!-1,"") | L8: =IFERROR(Volume!#REF!/Volume!#REF!-1,"") | M8: =IFERROR(Volume!#REF!/Volume!#REF!-1,"") | N8: =IFERROR(Volume!I8/Volume!I7-1,"") -> -0.06557377 | O8: =IFERROR(Volume!#REF!/Volume!#REF!-1,"") | P8: =IFERROR(Volume!#REF!/Volume!#REF!-1,"") | Q8: =IFERROR(Volume!#REF!/Volume!#REF!-1,"") | R8: =IFERROR(Volume!#REF!/Volume!#REF!-1,"") | S8: =IFERROR(Volume!#REF!/Volume!#REF!-1,"") | T8: =IFERROR(Volume!J8/Volume!J7-1,"") -> -0.030120482 | U8: =IFERROR(Volume!K8/Volume!K7-1,"")
B9: =IFERROR(Volume!B9/Volume!B8-1,"") | C9: =IFERROR(Volume!C9/Volume!C8-1,"") | D9: =IFERROR(Volume!D9/Volume!D8-1,"") -> 0.26543272 | E9: =IFERROR(Volume!#REF!/Volume!#REF!-1,"") | F9: =IFERROR(Volume!#REF!/Volume!#REF!-1,"") | G9: =IFERROR(Volume!E9/Volume!E8-1,"") | H9: =IFERROR(Volume!F9/Volume!F8-1,"") | I9: =IFERROR(Volume!G9/Volume!G8-1,"") -> 0.29906542 | J9: =IFERROR(Volume!H9/Volume!H8-1,"") | K9: =IFERROR(Volume!#REF!/Volume!#REF!-1,"") | L9: =IFERROR(Volume!#REF!/Volume!#REF!-1,"") | M9: =IFERROR(Volume!#REF!/Volume!#REF!-1,"") | N9: =IFERROR(Volume!I9/Volume!I8-1,"") -> 0.40350877 | O9: =IFERROR(Volume!#REF!/Volume!#REF!-1,"") | P9: =IFERROR(Volume!#REF!/Volume!#REF!-1,"") | Q9: =IFERROR(Volume!#REF!/Volume!#REF!-1,"") | R9: =IFERROR(Volume!#REF!/Volume!#REF!-1,"") | S9: =IFERROR(Volume!#REF!/Volume!#REF!-1,"") | T9: =IFERROR(Volume!J9/Volume!J8-1,"") -> 0.013250518 | U9: =IFERROR(Volume!K9/Volume!K8-1,"")
B10: =IFERROR(Volume!B10/Volume!B9-1,"") | C10: =IFERROR(Volume!C10/Volume!C9-1,"") | D10: =IFERROR(Volume!D10/Volume!D9-1,"") -> -0.080724225 | E10: =IFERROR(Volume!#REF!/Volume!#REF!-1,"") | F10: =IFERROR(Volume!#REF!/Volume!#REF!-1,"") | G10: =IFERROR(Volume!E10/Volume!E9-1,"") | H10: =IFERROR(Volume!F10/Volume!F9-1,"") | I10: =IFERROR(Volume!G10/Volume!G9-1,"") -> 9.6618705 | J10: =IFERROR(Volume!H10/Volume!H9-1,"") | K10: =IFERROR(Volume!#REF!/Volume!#REF!-1,"") | L10: =IFERROR(Volume!#REF!/Volume!#REF!-1,"") | M10: =IFERROR(Volume!#REF!/Volume!#REF!-1,"") | N10: =IFERROR(Volume!I10/Volume!I9-1,"") -> -0.33125 | O10: =IFERROR(Volume!#REF!/Volume!#REF!-1,"") | P10: =IFERROR(Volume!#REF!/Volume!#REF!-1,"") | Q10: =IFERROR(Volume!#REF!/Volume!#REF!-1,"") | R10: =IFERROR(Volume!#REF!/Volume!#REF!-1,"") | S10: =IFERROR(Volume!#REF!/Volume!#REF!-1,"") | T10: =IFERROR(Volume!J10/Volume!J9-1,"") -> -0.020433183 | U10: =IFERROR(Volume!K10/Volume!K9-1,"")
B11: =IFERROR(Volume!B11/Volume!B10-1,"") | C11: =IFERROR(Volume!C11/Volume!C10-1,"") | D11: =IFERROR(Volume!D11/Volume!D10-1,"") -> 0.20762019 | E11: =IFERROR(Volume!#REF!/Volume!#REF!-1,"") | F11: =IFERROR(Volume!#REF!/Volume!#REF!-1,"") | G11: =IFERROR(Volume!E11/Volume!E10-1,"") | H11: =IFERROR(Volume!F11/Volume!F10-1,"") | I11: =IFERROR(Volume!G11/Volume!G10-1,"") -> -0.23684211 | J11: =IFERROR(Volume!H11/Volume!H10-1,"") | K11: =IFERROR(Volume!#REF!/Volume!#REF!-1,"") | L11: =IFERROR(Volume!#REF!/Volume!#REF!-1,"") | M11: =IFERROR(Volume!#REF!/Volume!#REF!-1,"") | N11: =IFERROR(Volume!I11/Volume!I10-1,"") -> 0.90654206 | O11: =IFERROR(Volume!#REF!/Volume!#REF!-1,"") | P11: =IFERROR(Volume!#REF!/Volume!#REF!-1,"") | Q11: =IFERROR(Volume!#REF!/Volume!#REF!-1,"") | R11: =IFERROR(Volume!#REF!/Volume!#REF!-1,"") | S11: =IFERROR(Volume!#REF!/Volume!#REF!-1,"") | T11: =IFERROR(Volume!J11/Volume!J10-1,"") -> 0.025448477 | U11: =IFERROR(Volume!K11/Volume!K10-1,"")
B12: =IFERROR(Volume!B12/Volume!B11-1,"") | C12: =IFERROR(Volume!C12/Volume!C11-1,"") | D12: =IFERROR(Volume!D12/Volume!D11-1,"") -> -0.042091019 | E12: =IFERROR(Volume!#REF!/Volume!#REF!-1,"") | F12: =IFERROR(Volume!#REF!/Volume!#REF!-1,"") | G12: =IFERROR(Volume!E12/Volume!E11-1,"") | H12: =IFERROR(Volume!F12/Volume!F11-1,"") | I12: =IFERROR(Volume!G12/Volume!G11-1,"") -> -0.55791335 | J12: =IFERROR(Volume!H12/Volume!H11-1,"") -> -0.99734043 | K12: =IFERROR(Volume!#REF!/Volume!#REF!-1,"") | L12: =IFERROR(Volume!#REF!/Volume!#REF!-1,"") | M12: =IFERROR(Volume!#REF!/Volume!#REF!-1,"") | N12: =IFERROR(Volume!I12/Volume!I11-1,"") -> -0.28431373 | O12: =IFERROR(Volume!#REF!/Volume!#REF!-1,"") | P12: =IFERROR(Volume!#REF!/Volume!#REF!-1,"") | Q12: =IFERROR(Volume!#REF!/Volume!#REF!-1,"") | R12: =IFERROR(Volume!#REF!/Volume!#REF!-1,"") | S12: =IFERROR(Volume!#REF!/Volume!#REF!-1,"") | T12: =IFERROR(Volume!J12/Volume!J11-1,"") -> -0.018714402 | U12: =IFERROR(Volume!K12/Volume!K11-1,"")
B13: =IFERROR(Volume!B13/Volume!B12-1,"") | C13: =IFERROR(Volume!C13/Volume!C12-1,"") | D13: =IFERROR(Volume!D13/Volume!D12-1,"") -> -0.27591078 | E13: =IFERROR(Volume!#REF!/Volume!#REF!-1,"") | F13: =IFERROR(Volume!#REF!/Volume!#REF!-1,"") | G13: =IFERROR(Volume!E13/Volume!E12-1,"") | H13: =IFERROR(Volume!F13/Volume!F12-1,"") | I13: =IFERROR(Volume!G13/Volume!G12-1,"") -> -0.84 | J13: =IFERROR(Volume!H13/Volume!H12-1,"") | K13: =IFERROR(Volume!#REF!/Volume!#REF!-1,"") | L13: =IFERROR(Volume!#REF!/Volume!#REF!-1,"") | M13: =IFERROR(Volume!#REF!/Volume!#REF!-1,"") | N13: =IFERROR(Volume!I13/Volume!I12-1,"") -> -0.39726027 | O13: =IFERROR(Volume!#REF!/Volume!#REF!-1,"") | P13: =IFERROR(Volume!#REF!/Volume!#REF!-1,"") | Q13: =IFERROR(Volume!#REF!/Volume!#REF!-1,"") | R13: =IFERROR(Volume!#REF!/Volume!#REF!-1,"") | S13: =IFERROR(Volume!#REF!/Volume!#REF!-1,"") | T13: =IFERROR(Volume!J13/Volume!J12-1,"") -> -0.0024875622 | U13: =IFERROR(Volume!K13/Volume!K12-1,"")
B14: =IFERROR(Volume!B14/Volume!B13-1,"") | C14: =IFERROR(Volume!C14/Volume!C13-1,"") | D14: =IFERROR(Volume!D14/Volume!D13-1,"") -> 1.4026081 | E14: =IFERROR(Volume!#REF!/Volume!#REF!-1,"") | F14: =IFERROR(Volume!#REF!/Volume!#REF!-1,"") | G14: =IFERROR(Volume!E14/Volume!E13-1,"") | H14: =IFERROR(Volume!F14/Volume!F13-1,"") | I14: =IFERROR(Volume!G14/Volume!G13-1,"") -> 4.125 | J14: =IFERROR(Volume!H14/Volume!H13-1,"") | K14: =IFERROR(Volume!#REF!/Volume!#REF!-1,"") | L14: =IFERROR(Volume!#REF!/Volume!#REF!-1,"") | M14: =IFERROR(Volume!#REF!/Volume!#REF!-1,"") | N14: =IFERROR(Volume!I14/Volume!I13-1,"") -> 0.82954545 | O14: =IFERROR(Volume!#REF!/Volume!#REF!-1,"") | P14: =IFERROR(Volume!#REF!/Volume!#REF!-1,"") | Q14: =IFERROR(Volume!#REF!/Volume!#REF!-1,"") | R14: =IFERROR(Volume!#REF!/Volume!#REF!-1,"") | S14: =IFERROR(Volume!#REF!/Volume!#REF!-1,"") | T14: =IFERROR(Volume!J14/Volume!J13-1,"") -> -0.0120532 | U14: =IFERROR(Volume!K14/Volume!K13-1,"")
B15: =IFERROR(Volume!B15/Volume!B14-1,"") | C15: =IFERROR(Volume!C15/Volume!C14-1,"") | D15: =IFERROR(Volume!D15/Volume!D14-1,"") -> -0.41215437 | E15: =IFERROR(Volume!#REF!/Volume!#REF!-1,"") | F15: =IFERROR(Volume!#REF!/Volume!#REF!-1,"") | G15: =IFERROR(Volume!E15/Volume!E14-1,"") | H15: =IFERROR(Volume!F15/Volume!F14-1,"") | I15: =IFERROR(Volume!G15/Volume!G14-1,"") -> 0.11707317 | J15: =IFERROR(Volume!H15/Volume!H14-1,"") -> 2.8444444 | K15: =IFERROR(Volume!#REF!/Volume!#REF!-1,"") | L15: =IFERROR(Volume!#REF!/Volume!#REF!-1,"") | M15: =IFERROR(Volume!#REF!/Volume!#REF!-1,"") | N15: =IFERROR(Volume!I15/Volume!I14-1,"") -> -0.64596273 | O15: =IFERROR(Volume!#REF!/Volume!#REF!-1,"") | P15: =IFERROR(Volume!#REF!/Volume!#REF!-1,"") | Q15: =IFERROR(Volume!#REF!/Volume!#REF!-1,"") | R15: =IFERROR(Volume!#REF!/Volume!#REF!-1,"") | S15: =IFERROR(Volume!#REF!/Volume!#REF!-1,"") | T15: =IFERROR(Volume!J15/Volume!J14-1,"") -> 0.027766092 | U15: =IFERROR(Volume!K15/Volume!K14-1,"")
B16: =IFERROR(Volume!B16/Volume!B15-1,"") | C16: =IFERROR(Volume!C16/Volume!C15-1,"") | D16: =IFERROR(Volume!D16/Volume!D15-1,"") -> -0.26354053 | E16: =IFERROR(Volume!#REF!/Volume!#REF!-1,"") | F16: =IFERROR(Volume!#REF!/Volume!#REF!-1,"") | G16: =IFERROR(Volume!E16/Volume!E15-1,"") | H16: =IFERROR(Volume!F16/Volume!F15-1,"") | I16: =IFERROR(Volume!G16/Volume!G15-1,"") -> 2.1135371 | J16: =IFERROR(Volume!H16/Volume!H15-1,"") -> -0.89884393 | K16: =IFERROR(Volume!#REF!/Volume!#REF!-1,"") | L16: =IFERROR(Volume!#REF!/Volume!#REF!-1,"") | M16: =IFERROR(Volume!#REF!/Volume!#REF!-1,"") | N16: =IFERROR(Volume!I16/Volume!I15-1,"") -> 0.035087719 | O16: =IFERROR(Volume!#REF!/Volume!#REF!-1,"") | P16: =IFERROR(Volume!#REF!/Volume!#REF!-1,"") | Q16: =IFERROR(Volume!#REF!/Volume!#REF!-1,"") | R16: =IFERROR(Volume!#REF!/Volume!#REF!-1,"") | S16: =IFERROR(Volume!#REF!/Volume!#REF!-1,"") | T16: =IFERROR(Volume!J16/Volume!J15-1,"") -> 0.013917315 | U16: =IFERROR(Volume!K16/Volume!K15-1,"")
B17: =IFERROR(Volume!B17/Volume!B16-1,"") | C17: =IFERROR(Volume!C17/Volume!C16-1,"") | D17: =IFERROR(Volume!D17/Volume!D16-1,"") -> 0.329615 | E17: =IFERROR(Volume!#REF!/Volume!#REF!-1,"") | F17: =IFERROR(Volume!#REF!/Volume!#REF!-1,"") | G17: =IFERROR(Volume!E17/Volume!E16-1,"") | H17: =IFERROR(Volume!F17/Volume!F16-1,"") | I17: =IFERROR(Volume!G17/Volume!G16-1,"") -> -0.51472651 | J17: =IFERROR(Volume!H17/Volume!H16-1,"") -> 1.8571429 | K17: =IFERROR(Volume!#REF!/Volume!#REF!-1,"") | L17: =IFERROR(Volume!#REF!/Volume!#REF!-1,"") | M17: =IFERROR(Volume!#REF!/Volume!#REF!-1,"") | N17: =IFERROR(Volume!I17/Volume!I16-1,"") -> -0.11864407 | O17: =IFERROR(Volume!#REF!/Volume!#REF!-1,"") | P17: =IFERROR(Volume!#REF!/Volume!#REF!-1,"") | Q17: =IFERROR(Volume!#REF!/Volume!#REF!-1,"") | R17: =IFERROR(Volume!#REF!/Volume!#REF!-1,"") | S17: =IFERROR(Volume!#REF!/Volume!#REF!-1,"") | T17: =IFERROR(Volume!J17/Volume!J16-1,"") -> 0.023819136 | U17: =IFERROR(Volume!K17/Volume!K16-1,"")
... B2505: =IFERROR(Volume!B2505/Volume!B2504-1,"") | C2505: =IFERROR(Volume!C2505/Volume!C2504-1,"") | D2505: =IFERROR(Volume!D2505/Volume!D2504-1,"") | E2505: =IFERROR(Volume!#REF!/Volume!#REF!-1,"") | F2505: =IFERROR(Volume!#REF!/Volume!#REF!-1,"") | G2505: =IFERROR(Volume!E2505/Volume!E2504-1,"") | H2505: =IFERROR(Volume!F2505/Volume!F2504-1,"") | I2505: =IFERROR(Volume!G2505/Volume!G2504-1,"") | J2505: =IFERROR(Volume!H2505/Volume!H2504-1,"") | K2505: =IFERROR(Volume!#REF!/Volume!#REF!-1,"") | L2505: =IFERROR(Volume!#REF!/Volume!#REF!-1,"") | M2505: =IFERROR(Volume!#REF!/Volume!#REF!-1,"") | N2505: =IFERROR(Volume!I2505/Volume!I2504-1,"") | O2505: =IFERROR(Volume!#REF!/Volume!#REF!-1,"") | P2505: =IFERROR(Volume!#REF!/Volume!#REF!-1,"") | Q2505: =IFERROR(Volume!#REF!/Volume!#REF!-1,"") | R2505: =IFERROR(Volume!#REF!/Volume!#REF!-1,"") | S2505: =IFERROR(Volume!#REF!/Volume!#REF!-1,"") | T2505: =IFERROR(Volume!J2505/Volume!J2504-1,"") | U2505: =IFERROR(Volume!K2505/Volume!K2504-1,"")

Sheet Log_Returns_Wide
A1: Log Returns
A2: Formula: LN(Price_t / Price_(t-1))
A4: Date | B4: =Volume!B4 -> TZTA Comdty | C4: =Volume!C4 -> TZTB Comdty | D4: =Volume!D4 -> TZT1 Comdty | E4: =Volume!#REF! -> #REF! | F4: =Volume!#REF! -> #REF! | G4: =Volume!E4 -> FNA Comdty | H4: =Volume!F4 -> FNB Comdty | I4: =Volume!G4 -> MO1 Comdty | J4: =Volume!H4 -> MO2 Comdty | K4: =Volume!#REF! -> #REF! | L4: =Volume!#REF! -> #REF! | M4: =Volume!#REF! -> #REF! | N4: =Volume!I4 -> XA1 Comdty | O4: =Volume!#REF! -> #REF! | P4: =Volume!#REF! -> #REF! | Q4: =Volume!#REF! -> #REF! | R4: =Volume!#REF! -> #REF! | S4: =Volume!#REF! -> #REF! | T4: =Volume!J4 -> MO1 Comdty | U4: =Volume!K4 -> 0
A5: =Volume!A5 -> 43831
A6: =Volume!A6 -> 43832 | B6: =IFERROR(LN(Volume!B6/Volume!B5),"") | C6: =IFERROR(LN(Volume!C6/Volume!C5),"") | D6: =IFERROR(LN(Volume!D6/Volume!D5),"") | E6: =IFERROR(LN(Volume!#REF!/Volume!#REF!),"") | F6: =IFERROR(LN(Volume!#REF!/Volume!#REF!),"") | G6: =IFERROR(LN(Volume!E6/Volume!E5),"") | H6: =IFERROR(LN(Volume!F6/Volume!F5),"") | I6: =IFERROR(LN(Volume!G6/Volume!G5),"") | J6: =IFERROR(LN(Volume!H6/Volume!H5),"") | K6: =IFERROR(LN(Volume!#REF!/Volume!#REF!),"") | L6: =IFERROR(LN(Volume!#REF!/Volume!#REF!),"") | M6: =IFERROR(LN(Volume!#REF!/Volume!#REF!),"") | N6: =IFERROR(LN(Volume!I6/Volume!I5),"") | O6: =IFERROR(LN(Volume!#REF!/Volume!#REF!),"") | P6: =IFERROR(LN(Volume!#REF!/Volume!#REF!),"") | Q6: =IFERROR(LN(Volume!#REF!/Volume!#REF!),"") | R6: =IFERROR(LN(Volume!#REF!/Volume!#REF!),"") | S6: =IFERROR(LN(Volume!#REF!/Volume!#REF!),"") | T6: =IFERROR(LN(Volume!J6/Volume!J5),"") | U6: =IFERROR(LN(Volume!K6/Volume!K5),"")
A7: =Volume!A7 -> 43833 | B7: =IFERROR(LN(Volume!B7/Volume!B6),"") | C7: =IFERROR(LN(Volume!C7/Volume!C6),"") | D7: =IFERROR(LN(Volume!D7/Volume!D6),"") -> 0.35039279 | E7: =IFERROR(LN(Volume!#REF!/Volume!#REF!),"") | F7: =IFERROR(LN(Volume!#REF!/Volume!#REF!),"") | G7: =IFERROR(LN(Volume!E7/Volume!E6),"") | H7: =IFERROR(LN(Volume!F7/Volume!F6),"") | I7: =IFERROR(LN(Volume!G7/Volume!G6),"") -> -0.73262599 | J7: =IFERROR(LN(Volume!H7/Volume!H6),"") | K7: =IFERROR(LN(Volume!#REF!/Volume!#REF!),"") | L7: =IFERROR(LN(Volume!#REF!/Volume!#REF!),"") | M7: =IFERROR(LN(Volume!#REF!/Volume!#REF!),"") | N7: =IFERROR(LN(Volume!I7/Volume!I6),"") -> -0.46897851 | O7: =IFERROR(LN(Volume!#REF!/Volume!#REF!),"") | P7: =IFERROR(LN(Volume!#REF!/Volume!#REF!),"") | Q7: =IFERROR(LN(Volume!#REF!/Volume!#REF!),"") | R7: =IFERROR(LN(Volume!#REF!/Volume!#REF!),"") | S7: =IFERROR(LN(Volume!#REF!/Volume!#REF!),"") | T7: =IFERROR(LN(Volume!J7/Volume!J6),"") -> 0.025214837 | U7: =IFERROR(LN(Volume!K7/Volume!K6),"")
A8: =Volume!A8 -> 43836 | B8: =IFERROR(LN(Volume!B8/Volume!B7),"") | C8: =IFERROR(LN(Volume!C8/Volume!C7),"") | D8: =IFERROR(LN(Volume!D8/Volume!D7),"") -> -0.57683255 | E8: =IFERROR(LN(Volume!#REF!/Volume!#REF!),"") | F8: =IFERROR(LN(Volume!#REF!/Volume!#REF!),"") | G8: =IFERROR(LN(Volume!E8/Volume!E7),"") | H8: =IFERROR(LN(Volume!F8/Volume!F7),"") | I8: =IFERROR(LN(Volume!G8/Volume!G7),"") -> -0.33111747 | J8: =IFERROR(LN(Volume!H8/Volume!H7),"") | K8: =IFERROR(LN(Volume!#REF!/Volume!#REF!),"") | L8: =IFERROR(LN(Volume!#REF!/Volume!#REF!),"") | M8: =IFERROR(LN(Volume!#REF!/Volume!#REF!),"") | N8: =IFERROR(LN(Volume!I8/Volume!I7),"") -> -0.067822596 | O8: =IFERROR(LN(Volume!#REF!/Volume!#REF!),"") | P8: =IFERROR(LN(Volume!#REF!/Volume!#REF!),"") | Q8: =IFERROR(LN(Volume!#REF!/Volume!#REF!),"") | R8: =IFERROR(LN(Volume!#REF!/Volume!#REF!),"") | S8: =IFERROR(LN(Volume!#REF!/Volume!#REF!),"") | T8: =IFERROR(LN(Volume!J8/Volume!J7),"") -> -0.030583423 | U8: =IFERROR(LN(Volume!K8/Volume!K7),"")
A9: =Volume!A9 -> 43837 | B9: =IFERROR(LN(Volume!B9/Volume!B8),"") | C9: =IFERROR(LN(Volume!C9/Volume!C8),"") | D9: =IFERROR(LN(Volume!D9/Volume!D8),"") -> 0.23541413 | E9: =IFERROR(LN(Volume!#REF!/Volume!#REF!),"") | F9: =IFERROR(LN(Volume!#REF!/Volume!#REF!),"") | G9: =IFERROR(LN(Volume!E9/Volume!E8),"") | H9: =IFERROR(LN(Volume!F9/Volume!F8),"") | I9: =IFERROR(LN(Volume!G9/Volume!G8),"") -> 0.2616451 | J9: =IFERROR(LN(Volume!H9/Volume!H8),"") | K9: =IFERROR(LN(Volume!#REF!/Volume!#REF!),"") | L9: =IFERROR(LN(Volume!#REF!/Volume!#REF!),"") | M9: =IFERROR(LN(Volume!#REF!/Volume!#REF!),"") | N9: =IFERROR(LN(Volume!I9/Volume!I8),"") -> 0.33897537 | O9: =IFERROR(LN(Volume!#REF!/Volume!#REF!),"") | P9: =IFERROR(LN(Volume!#REF!/Volume!#REF!),"") | Q9: =IFERROR(LN(Volume!#REF!/Volume!#REF!),"") | R9: =IFERROR(LN(Volume!#REF!/Volume!#REF!),"") | S9: =IFERROR(LN(Volume!#REF!/Volume!#REF!),"") | T9: =IFERROR(LN(Volume!J9/Volume!J8),"") -> 0.013163497 | U9: =IFERROR(LN(Volume!K9/Volume!K8),"")
A10: =Volume!A10 -> 43838 | B10: =IFERROR(LN(Volume!B10/Volume!B9),"") | C10: =IFERROR(LN(Volume!C10/Volume!C9),"") | D10: =IFERROR(LN(Volume!D10/Volume!D9),"") -> -0.08416912 | E10: =IFERROR(LN(Volume!#REF!/Volume!#REF!),"") | F10: =IFERROR(LN(Volume!#REF!/Volume!#REF!),"") | G10: =IFERROR(LN(Volume!E10/Volume!E9),"") | H10: =IFERROR(LN(Volume!F10/Volume!F9),"") | I10: =IFERROR(LN(Volume!G10/Volume!G9),"") -> 2.3666739 | J10: =IFERROR(LN(Volume!H10/Volume!H9),"") | K10: =IFERROR(LN(Volume!#REF!/Volume!#REF!),"") | L10: =IFERROR(LN(Volume!#REF!/Volume!#REF!),"") | M10: =IFERROR(LN(Volume!#REF!/Volume!#REF!),"") | N10: =IFERROR(LN(Volume!I10/Volume!I9),"") -> -0.40234498 | O10: =IFERROR(LN(Volume!#REF!/Volume!#REF!),"") | P10: =IFERROR(LN(Volume!#REF!/Volume!#REF!),"") | Q10: =IFERROR(LN(Volume!#REF!/Volume!#REF!),"") | R10: =IFERROR(LN(Volume!#REF!/Volume!#REF!),"") | S10: =IFERROR(LN(Volume!#REF!/Volume!#REF!),"") | T10: =IFERROR(LN(Volume!J10/Volume!J9),"") -> -0.020644829 | U10: =IFERROR(LN(Volume!K10/Volume!K9),"")
A11: =Volume!A11 -> 43839 | B11: =IFERROR(LN(Volume!B11/Volume!B10),"") | C11: =IFERROR(LN(Volume!C11/Volume!C10),"") | D11: =IFERROR(LN(Volume!D11/Volume!D10),"") -> 0.18865164 | E11: =IFERROR(LN(Volume!#REF!/Volume!#REF!),"") | F11: =IFERROR(LN(Volume!#REF!/Volume!#REF!),"") | G11: =IFERROR(LN(Volume!E11/Volume!E10),"") | H11: =IFERROR(LN(Volume!F11/Volume!F10),"") | I11: =IFERROR(LN(Volume!G11/Volume!G10),"") -> -0.27029033 | J11: =IFERROR(LN(Volume!H11/Volume!H10),"") | K11: =IFERROR(LN(Volume!#REF!/Volume!#REF!),"") | L11: =IFERROR(LN(Volume!#REF!/Volume!#REF!),"") | M11: =IFERROR(LN(Volume!#REF!/Volume!#REF!),"") | N11: =IFERROR(LN(Volume!I11/Volume!I10),"") -> 0.64529116 | O11: =IFERROR(LN(Volume!#REF!/Volume!#REF!),"") | P11: =IFERROR(LN(Volume!#REF!/Volume!#REF!),"") | Q11: =IFERROR(LN(Volume!#REF!/Volume!#REF!),"") | R11: =IFERROR(LN(Volume!#REF!/Volume!#REF!),"") | S11: =IFERROR(LN(Volume!#REF!/Volume!#REF!),"") | T11: =IFERROR(LN(Volume!J11/Volume!J10),"") -> 0.025130056 | U11: =IFERROR(LN(Volume!K11/Volume!K10),"")
A12: =Volume!A12 -> 43840 | B12: =IFERROR(LN(Volume!B12/Volume!B11),"") | C12: =IFERROR(LN(Volume!C12/Volume!C11),"") | D12: =IFERROR(LN(Volume!D12/Volume!D11),"") -> -0.043002515 | E12: =IFERROR(LN(Volume!#REF!/Volume!#REF!),"") | F12: =IFERROR(LN(Volume!#REF!/Volume!#REF!),"") | G12: =IFERROR(LN(Volume!E12/Volume!E11),"") | H12: =IFERROR(LN(Volume!F12/Volume!F11),"") | I12: =IFERROR(LN(Volume!G12/Volume!G11),"") -> -0.81624938 | J12: =IFERROR(LN(Volume!H12/Volume!H11),"") -> -5.9295891 | K12: =IFERROR(LN(Volume!#REF!/Volume!#REF!),"") | L12: =IFERROR(LN(Volume!#REF!/Volume!#REF!),"") | M12: =IFERROR(LN(Volume!#REF!/Volume!#REF!),"") | N12: =IFERROR(LN(Volume!I12/Volume!I11),"") -> -0.33451337 | O12: =IFERROR(LN(Volume!#REF!/Volume!#REF!),"") | P12: =IFERROR(LN(Volume!#REF!/Volume!#REF!),"") | Q12: =IFERROR(LN(Volume!#REF!/Volume!#REF!),"") | R12: =IFERROR(LN(Volume!#REF!/Volume!#REF!),"") | S12: =IFERROR(LN(Volume!#REF!/Volume!#REF!),"") | T12: =IFERROR(LN(Volume!J12/Volume!J11),"") -> -0.018891732 | U12: =IFERROR(LN(Volume!K12/Volume!K11),"")
A13: =Volume!A13 -> 43843 | B13: =IFERROR(LN(Volume!B13/Volume!B12),"") | C13: =IFERROR(LN(Volume!C13/Volume!C12),"") | D13: =IFERROR(LN(Volume!D13/Volume!D12),"") -> -0.32284066 | E13: =IFERROR(LN(Volume!#REF!/Volume!#REF!),"") | F13: =IFERROR(LN(Volume!#REF!/Volume!#REF!),"") | G13: =IFERROR(LN(Volume!E13/Volume!E12),"") | H13: =IFERROR(LN(Volume!F13/Volume!F12),"") | I13: =IFERROR(LN(Volume!G13/Volume!G12),"") -> -1.8325815 | J13: =IFERROR(LN(Volume!H13/Volume!H12),"") | K13: =IFERROR(LN(Volume!#REF!/Volume!#REF!),"") | L13: =IFERROR(LN(Volume!#REF!/Volume!#REF!),"") | M13: =IFERROR(LN(Volume!#REF!/Volume!#REF!),"") | N13: =IFERROR(LN(Volume!I13/Volume!I12),"") -> -0.50626981 | O13: =IFERROR(LN(Volume!#REF!/Volume!#REF!),"") | P13: =IFERROR(LN(Volume!#REF!/Volume!#REF!),"") | Q13: =IFERROR(LN(Volume!#REF!/Volume!#REF!),"") | R13: =IFERROR(LN(Volume!#REF!/Volume!#REF!),"") | S13: =IFERROR(LN(Volume!#REF!/Volume!#REF!),"") | T13: =IFERROR(LN(Volume!J13/Volume!J12),"") -> -0.0024906613 | U13: =IFERROR(LN(Volume!K13/Volume!K12),"")
A14: =Volume!A14 -> 43844 | B14: =IFERROR(LN(Volume!B14/Volume!B13),"") | C14: =IFERROR(LN(Volume!C14/Volume!C13),"") | D14: =IFERROR(LN(Volume!D14/Volume!D13),"") -> 0.87655484 | E14: =IFERROR(LN(Volume!#REF!/Volume!#REF!),"") | F14: =IFERROR(LN(Volume!#REF!/Volume!#REF!),"") | G14: =IFERROR(LN(Volume!E14/Volume!E13),"") | H14: =IFERROR(LN(Volume!F14/Volume!F13),"") | I14: =IFERROR(LN(Volume!G14/Volume!G13),"") -> 1.6341305 | J14: =IFERROR(LN(Volume!H14/Volume!H13),"") | K14: =IFERROR(LN(Volume!#REF!/Volume!#REF!),"") | L14: =IFERROR(LN(Volume!#REF!/Volume!#REF!),"") | M14: =IFERROR(LN(Volume!#REF!/Volume!#REF!),"") | N14: =IFERROR(LN(Volume!I14/Volume!I13),"") -> 0.60406755 | O14: =IFERROR(LN(Volume!#REF!/Volume!#REF!),"") | P14: =IFERROR(LN(Volume!#REF!/Volume!#REF!),"") | Q14: =IFERROR(LN(Volume!#REF!/Volume!#REF!),"") | R14: =IFERROR(LN(Volume!#REF!/Volume!#REF!),"") | S14: =IFERROR(LN(Volume!#REF!/Volume!#REF!),"") | T14: =IFERROR(LN(Volume!J14/Volume!J13),"") -> -0.012126429 | U14: =IFERROR(LN(Volume!K14/Volume!K13),"")
A15: =Volume!A15 -> 43845 | B15: =IFERROR(LN(Volume!B15/Volume!B14),"") | C15: =IFERROR(LN(Volume!C15/Volume!C14),"") | D15: =IFERROR(LN(Volume!D15/Volume!D14),"") -> -0.53129089 | E15: =IFERROR(LN(Volume!#REF!/Volume!#REF!),"") | F15: =IFERROR(LN(Volume!#REF!/Volume!#REF!),"") | G15: =IFERROR(LN(Volume!E15/Volume!E14),"") | H15: =IFERROR(LN(Volume!F15/Volume!F14),"") | I15: =IFERROR(LN(Volume!G15/Volume!G14),"") -> 0.11071202 | J15: =IFERROR(LN(Volume!H15/Volume!H14),"") -> 1.3466291 | K15: =IFERROR(LN(Volume!#REF!/Volume!#REF!),"") | L15: =IFERROR(LN(Volume!#REF!/Volume!#REF!),"") | M15: =IFERROR(LN(Volume!#REF!/Volume!#REF!),"") | N15: =IFERROR(LN(Volume!I15/Volume!I14),"") -> -1.0383531 | O15: =IFERROR(LN(Volume!#REF!/Volume!#REF!),"") | P15: =IFERROR(LN(Volume!#REF!/Volume!#REF!),"") | Q15: =IFERROR(LN(Volume!#REF!/Volume!#REF!),"") | R15: =IFERROR(LN(Volume!#REF!/Volume!#REF!),"") | S15: =IFERROR(LN(Volume!#REF!/Volume!#REF!),"") | T15: =IFERROR(LN(Volume!J15/Volume!J14),"") -> 0.027387604 | U15: =IFERROR(LN(Volume!K15/Volume!K14),"")
A16: =Volume!A16 -> 43846 | B16: =IFERROR(LN(Volume!B16/Volume!B15),"") | C16: =IFERROR(LN(Volume!C16/Volume!C15),"") | D16: =IFERROR(LN(Volume!D16/Volume!D15),"") -> -0.30590108 | E16: =IFERROR(LN(Volume!#REF!/Volume!#REF!),"") | F16: =IFERROR(LN(Volume!#REF!/Volume!#REF!),"") | G16: =IFERROR(LN(Volume!E16/Volume!E15),"") | H16: =IFERROR(LN(Volume!F16/Volume!F15),"") | I16: =IFERROR(LN(Volume!G16/Volume!G15),"") -> 1.1357594 | J16: =IFERROR(LN(Volume!H16/Volume!H15),"") -> -2.2910907 | K16: =IFERROR(LN(Volume!#REF!/Volume!#REF!),"") | L16: =IFERROR(LN(Volume!#REF!/Volume!#REF!),"") | M16: =IFERROR(LN(Volume!#REF!/Volume!#REF!),"") | N16: =IFERROR(LN(Volume!I16/Volume!I15),"") -> 0.034486176 | O16: =IFERROR(LN(Volume!#REF!/Volume!#REF!),"") | P16: =IFERROR(LN(Volume!#REF!/Volume!#REF!),"") | Q16: =IFERROR(LN(Volume!#REF!/Volume!#REF!),"") | R16: =IFERROR(LN(Volume!#REF!/Volume!#REF!),"") | S16: =IFERROR(LN(Volume!#REF!/Volume!#REF!),"") | T16: =IFERROR(LN(Volume!J16/Volume!J15),"") -> 0.013821358 | U16: =IFERROR(LN(Volume!K16/Volume!K15),"")
A17: =Volume!A17 -> 43847 | B17: =IFERROR(LN(Volume!B17/Volume!B16),"") | C17: =IFERROR(LN(Volume!C17/Volume!C16),"") | D17: =IFERROR(LN(Volume!D17/Volume!D16),"") -> 0.28488943 | E17: =IFERROR(LN(Volume!#REF!/Volume!#REF!),"") | F17: =IFERROR(LN(Volume!#REF!/Volume!#REF!),"") | G17: =IFERROR(LN(Volume!E17/Volume!E16),"") | H17: =IFERROR(LN(Volume!F17/Volume!F16),"") | I17: =IFERROR(LN(Volume!G17/Volume!G16),"") -> -0.72304265 | J17: =IFERROR(LN(Volume!H17/Volume!H16),"") -> 1.0498221 | K17: =IFERROR(LN(Volume!#REF!/Volume!#REF!),"") | L17: =IFERROR(LN(Volume!#REF!/Volume!#REF!),"") | M17: =IFERROR(LN(Volume!#REF!/Volume!#REF!),"") | N17: =IFERROR(LN(Volume!I17/Volume!I16),"") -> -0.12629373 | O17: =IFERROR(LN(Volume!#REF!/Volume!#REF!),"") | P17: =IFERROR(LN(Volume!#REF!/Volume!#REF!),"") | Q17: =IFERROR(LN(Volume!#REF!/Volume!#REF!),"") | R17: =IFERROR(LN(Volume!#REF!/Volume!#REF!),"") | S17: =IFERROR(LN(Volume!#REF!/Volume!#REF!),"") | T17: =IFERROR(LN(Volume!J17/Volume!J16),"") -> 0.023539886 | U17: =IFERROR(LN(Volume!K17/Volume!K16),"")
... A2505: =Volume!A2505 -> 0 | B2505: =IFERROR(LN(Volume!B2505/Volume!B2504),"") | C2505: =IFERROR(LN(Volume!C2505/Volume!C2504),"") | D2505: =IFERROR(LN(Volume!D2505/Volume!D2504),"") | E2505: =IFERROR(LN(Volume!#REF!/Volume!#REF!),"") | F2505: =IFERROR(LN(Volume!#REF!/Volume!#REF!),"") | G2505: =IFERROR(LN(Volume!E2505/Volume!E2504),"") | H2505: =IFERROR(LN(Volume!F2505/Volume!F2504),"") | I2505: =IFERROR(LN(Volume!G2505/Volume!G2504),"") | J2505: =IFERROR(LN(Volume!H2505/Volume!H2504),"") | K2505: =IFERROR(LN(Volume!#REF!/Volume!#REF!),"") | L2505: =IFERROR(LN(Volume!#REF!/Volume!#REF!),"") | M2505: =IFERROR(LN(Volume!#REF!/Volume!#REF!),"") | N2505: =IFERROR(LN(Volume!I2505/Volume!I2504),"") | O2505: =IFERROR(LN(Volume!#REF!/Volume!#REF!),"") | P2505: =IFERROR(LN(Volume!#REF!/Volume!#REF!),"") | Q2505: =IFERROR(LN(Volume!#REF!/Volume!#REF!),"") | R2505: =IFERROR(LN(Volume!#REF!/Volume!#REF!),"") | S2505: =IFERROR(LN(Volume!#REF!/Volume!#REF!),"") | T2505: =IFERROR(LN(Volume!J2505/Volume!J2504),"") | U2505: =IFERROR(LN(Volume!K2505/Volume!K2504),"")

Sheet Master List
A1: Ticker | B1: Name / Description | C1: Asset Type | D1: Fields Pulled | E1: Fields Pulled | F1: Fields Pulled | G1: Fields Pulled | H1: Notes
A2: TZTA Comdty | B2: TTF NAT GAS F May26 | C2: Commodity | D2: PX_LAST | E2: PX_VOLUME | F2: OPEN_INT | H2: TTF gas family ticker; exact Bloomberg description still needs confirmation
A3: TZTB Comdty | B3: TTF NAT GAS F Jun26 | C3: Commodity | D3: PX_LAST | E3: PX_VOLUME | F3: OPEN_INT | H3: TTF gas family ticker; exact Bloomberg description still needs confirmation
A4: TZT1 Comdty | B4: Generic 1st 'TZT' Future | C4: Commodity | D4: PX_LAST | E4: PX_VOLUME | F4: OPEN_INT | H4: TTF gas family ticker; exact Bloomberg description still needs confirmation
A5: FNA Comdty | B5: UK Natural Gas FutMay26 | C5: Commodity | D5: PX_LAST | E5: PX_VOLUME | F5: OPEN_INT | H5: Exact Bloomberg description not captured yet
A6: FNB Comdty | B6: UK Natural Gas FutJun26 | C6: Commodity | D6: PX_LAST | E6: PX_VOLUME | F6: OPEN_INT | H6: Exact Bloomberg description not captured yet
A7: MO1 Comdty | B7: Generic 1st 'MO' Future | C7: Commodity | D7: PX_LAST | E7: PX_VOLUME | F7: OPEN_INT | G7: HIST_CALL_IMP_VOL
A8: MO2 Comdty | B8: Generic 2nd 'MO' Future | C8: Commodity | D8: PX_LAST | E8: PX_VOLUME | F8: OPEN_INT | H8: Exact Bloomberg description not captured yet
A9: BDIY Index | B9: BDI Baltic Exchange Dry Index | C9: Index | D9: PX_LAST | H9: Freight / shipping activity proxy
A10: TMR1 Comdty | B10: Generic 1st 'TMR' Future | C10: Commodity | D10: PX_LAST | H10: Alternate TTF month 1 / front-month futures proxy
A11: TTFG1MON Index | B11: NL TTF Nat Gas Month 1 | C11: Index | D11: PX_LAST | H11: TTF forward month 1 benchmark
A12: TTFDDAHD Index | B12: TTF Day-Ahead | C12: Index | D12: PX_LAST | H12: TTF day-ahead spot gas series; history looked short
A13: RTEGNUCT Index | B13: France Gen Nuclear Average | C13: Index | D13: PX_LAST | H13: French nuclear generation proxy
A14: RTEGNUCD Index | B14: France Gen Nuclear Daily | C14: Index | D14: PX_LAST | H14: Alternative French nuclear generation series
A15: API21MON Index | B15: Eur Coal Forward M1 | C15: Index | D15: PX_LAST | H15: European coal forward month 1 benchmark
A16: XA1 Comdty | B16: Generic 1st 'XA' Future | C16: Commodity | D16: PX_LAST | E16: PX_VOLUME | F16: OPEN_INT | H16: Main coal tradable proxy
A17: XAA Comdty | B17: ICE RTD MONTH COA May26 | C17: Commodity | D17: PX_LAST | H17: Alternate Rotterdam coal contract
A18: EEXXT3PA Index | B18: EUA Auction | C18: Index | D18: PX_LAST | H18: Main EUA auction series that worked
A19: ELGB1MON Index | B19: DE Baseload Month 1 | C19: Index | D19: PX_LAST | H19: German baseload month-ahead benchmark
A20: ELGP1MON Index | B20: DE Peakload Month 1 | C20: Index | D20: PX_LAST | H20: German peakload month-ahead benchmark
A21: TZTA Comdty | B21: RK910 | C21: 1M_PUT_IMP_VOL_25DELTA_DFLT | D21: TTF 25D put IV | H21: TTF 25D call IV
A22: TZTA Comdty | B22: RK903 | C22: 1M_CALL_IMP_VOL_25DELTA_DFLT | D22: TTF 25D call IV | H22: TTF 50D put IV
A23: TZTA Comdty | B23: RK908 | C23: 1M_PUT_IMP_VOL_50DELTA_DFLT | D23: TTF 50D put IV | H23: TTF 50D call IV
A24: TZTA Comdty | B24: RK901 | C24: 1M_CALL_IMP_VOL_50DELTA_DFLT | D24: TTF 50D call IV | H24: EUA 25D put IV
A25: MOA Comdty | B25: RK910 | C25: 1M_PUT_IMP_VOL_25DELTA_DFLT | D25: EUA 25D put IV | H25: EUA 25D call IV
A26: MOA Comdty | B26: RK903 | C26: 1M_CALL_IMP_VOL_25DELTA_DFLT | D26: EUA 25D call IV | H26: EUA 50D put IV
A27: MOA Comdty | B27: RK908 | C27: 1M_PUT_IMP_VOL_50DELTA_DFLT | D27: EUA 50D put IV | H27: EUA 50D call IV
A28: MOA Comdty | B28: RK901 | C28: 1M_CALL_IMP_VOL_50DELTA_DFLT | D28: EUA 50D call IV

Sheet Master List COT
A1: MO1 (ICE Brent Crude Oil) — ESMA COT Tickers — All 75 Unique Bloomberg Tickers
A2: ESMA Category | B2: Direction | C2: Group | D2: Field | E2: Bloomberg Ticker | F2: BDP Field (Position) | G2: BDP Field (Chg) | H2: Notes
A3: Investment Firms or Credit Institutions | B3: Long | C3: G1 | D3: Position | E3: IU34DXTZ Index | F3: LAST_PRICE | G3: RT_PX_CHG_NET_1D | H3: -> MM (Money Manager) analog | Futures Only
A4: Investment Firms or Credit Institutions | B4: Long | C4: G1 | D4: PctOI | E4: IU34NIMQ Index | F4: LAST_PRICE | G4: RT_PX_CHG_NET_1D | H4: -> MM (Money Manager) analog | Futures Only
A5: Investment Firms or Credit Institutions | B5: Long | C5: G2 | D5: Position | E5: IU34SOVM Index | F5: LAST_PRICE | G5: RT_PX_CHG_NET_1D | H5: -> MM (Money Manager) analog | Options Only
A6: Investment Firms or Credit Institutions | B6: Long | C6: G2 | D6: PctOI | E6: IU34TKAC Index | F6: LAST_PRICE | G6: RT_PX_CHG_NET_1D | H6: -> MM (Money Manager) analog | Options Only
A7: Investment Firms or Credit Institutions | B7: Long | C7: G3 | D7: Position | E7: IU34LTIS Index | F7: LAST_PRICE | G7: RT_PX_CHG_NET_1D | H7: -> MM (Money Manager) analog | Futures + Options (F+O)
A8: Investment Firms or Credit Institutions | B8: Long | C8: G3 | D8: PctOI | E8: IU34JCIV Index | F8: LAST_PRICE | G8: RT_PX_CHG_NET_1D | H8: -> MM (Money Manager) analog | Futures + Options (F+O)
A9: Investment Firms or Credit Institutions | B9: Short | C9: G1 | D9: Position | E9: IU34XWQO Index | F9: LAST_PRICE | G9: RT_PX_CHG_NET_1D | H9: -> MM (Money Manager) analog | Futures Only
A10: Investment Firms or Credit Institutions | B10: Short | C10: G1 | D10: PctOI | E10: IU34JIHS Index | F10: LAST_PRICE | G10: RT_PX_CHG_NET_1D | H10: -> MM (Money Manager) analog | Futures Only
A11: Investment Firms or Credit Institutions | B11: Short | C11: G2 | D11: Position | E11: IU34PACT Index | F11: LAST_PRICE | G11: RT_PX_CHG_NET_1D | H11: -> MM (Money Manager) analog | Options Only
A12: Investment Firms or Credit Institutions | B12: Short | C12: G2 | D12: PctOI | E12: IU34BDCL Index | F12: LAST_PRICE | G12: RT_PX_CHG_NET_1D | H12: -> MM (Money Manager) analog | Options Only
A13: Investment Firms or Credit Institutions | B13: Short | C13: G3 | D13: Position | E13: IU34YJER Index | F13: LAST_PRICE | G13: RT_PX_CHG_NET_1D | H13: -> MM (Money Manager) analog | Futures + Options (F+O)
... A77: Directive Compliance Obligations | B77: Net | C77: G3 | D77: Position | E77: IU34MHIR Index | F77: LAST_PRICE | G77: RT_PX_CHG_NET_1D | H77: -> NR (Non-Reportable) analog | Futures + Options (F+O)

Sheet Volume
A1: Paste Bloomberg historical price export here
A2: Recommended: export daily PX_LAST in wide format with dates in rows and tickers in columns. Paste starting at A4.
J3: HIST_CALL_IMP_VOL
A4: Date | B4: TZTA Comdty | C4: TZTB Comdty | D4: TZT1 Comdty | E4: FNA Comdty | F4: FNB Comdty | G4: MO1 Comdty | H4: MO2 Comdty | I4: XA1 Comdty | J4: MO1 Comdty
A5: 43831 | B5: #N/A N/A | C5: #N/A N/A | D5: #N/A N/A | E5: #N/A N/A | F5: #N/A N/A | G5: #N/A N/A | H5: #N/A N/A | I5: #N/A N/A | J5: #N/A N/A
A6: =A5+1 -> 43832 | B6: #N/A N/A | C6: #N/A N/A | D6: 12535 | E6: #N/A N/A | F6: #N/A N/A | G6: 310 | H6: #N/A N/A | I6: 195 | J6: 24.28
A7: =WORKDAY(A6,1,0) -> 43833 | B7: #N/A N/A | C7: #N/A N/A | D7: 17795 | E7: #N/A N/A | F7: #N/A N/A | G7: 149 | H7: #N/A N/A | I7: 122 | J7: 24.9
A8: =WORKDAY(A7,1,0) -> 43836 | B8: #N/A N/A | C8: #N/A N/A | D8: 9995 | E8: #N/A N/A | F8: #N/A N/A | G8: 107 | H8: #N/A N/A | I8: 114 | J8: 24.15
A9: =WORKDAY(A8,1,0) -> 43837 | B9: #N/A N/A | C9: #N/A N/A | D9: 12648 | E9: #N/A N/A | F9: #N/A N/A | G9: 139 | H9: #N/A N/A | I9: 160 | J9: 24.47
A10: =WORKDAY(A9,1,0) -> 43838 | B10: #N/A N/A | C10: #N/A N/A | D10: 11627 | E10: #N/A N/A | F10: #N/A N/A | G10: 1482 | H10: #N/A N/A | I10: 107 | J10: 23.97
A11: =WORKDAY(A10,1,0) -> 43839 | B11: #N/A N/A | C11: #N/A N/A | D11: 14041 | E11: #N/A N/A | F11: #N/A N/A | G11: 1131 | H11: 2256 | I11: 204 | J11: 24.58
A12: =WORKDAY(A11,1,0) -> 43840 | B12: #N/A N/A | C12: #N/A N/A | D12: 13450 | E12: #N/A N/A | F12: #N/A N/A | G12: 500 | H12: 6 | I12: 146 | J12: 24.12
A13: =WORKDAY(A12,1,0) -> 43843 | B13: #N/A N/A | C13: #N/A N/A | D13: 9739 | E13: #N/A N/A | F13: #N/A N/A | G13: 80 | H13: #N/A N/A | I13: 88 | J13: 24.06
A14: =WORKDAY(A13,1,0) -> 43844 | B14: #N/A N/A | C14: #N/A N/A | D14: 23399 | E14: #N/A N/A | F14: #N/A N/A | G14: 410 | H14: 90 | I14: 161 | J14: 23.77
A15: =WORKDAY(A14,1,0) -> 43845 | B15: #N/A N/A | C15: #N/A N/A | D15: 13755 | E15: #N/A N/A | F15: #N/A N/A | G15: 458 | H15: 346 | I15: 57 | J15: 24.43
A16: =WORKDAY(A15,1,0) -> 43846 | B16: #N/A N/A | C16: #N/A N/A | D16: 10130 | E16: #N/A N/A | F16: #N/A N/A | G16: 1426 | H16: 35 | I16: 59 | J16: 24.77
A17: =WORKDAY(A16,1,0) -> 43847 | B17: #N/A N/A | C17: #N/A N/A | D17: 13469 | E17: #N/A N/A | F17: #N/A N/A | G17: 692 | H17: 100 | I17: 52 | J17: 25.36
A18: =WORKDAY(A17,1,0) -> 43850 | B18: #N/A N/A | C18: #N/A N/A | D18: 11891 | E18: #N/A N/A | F18: #N/A N/A | G18: 611 | H18: 135 | I18: 40 | J18: 25.11
A19: =WORKDAY(A18,1,0) -> 43851 | B19: #N/A N/A | C19: #N/A N/A | D19: 14946 | E19: #N/A N/A | F19: #N/A N/A | G19: 303 | H19: 121 | I19: 131 | J19: 24.85
A20: =WORKDAY(A19,1,0) -> 43852 | B20: #N/A N/A | C20: #N/A N/A | D20: 13725 | E20: #N/A N/A | F20: #N/A N/A | G20: 70 | H20: #N/A N/A | I20: 21 | J20: 24.94
A21: =WORKDAY(A20,1,0) -> 43853 | B21: #N/A N/A | C21: #N/A N/A | D21: 14900 | E21: #N/A N/A | F21: #N/A N/A | G21: 296 | H21: #N/A N/A | I21: 11 | J21: 24.63
A22: =WORKDAY(A21,1,0) -> 43854 | B22: #N/A N/A | C22: #N/A N/A | D22: 12615 | E22: #N/A N/A | F22: #N/A N/A | G22: 261 | H22: 50 | I22: 1 | J22: 24.3
A23: =WORKDAY(A22,1,0) -> 43857 | B23: #N/A N/A | C23: #N/A N/A | D23: 11043 | E23: #N/A N/A | F23: #N/A N/A | G23: 191 | H23: 15 | I23: 5 | J23: 24.52
A24: =WORKDAY(A23,1,0) -> 43858 | B24: #N/A N/A | C24: #N/A N/A | D24: 18213 | E24: #N/A N/A | F24: #N/A N/A | G24: 113 | H24: 45 | I24: 15 | J24: 24.58
A25: =WORKDAY(A24,1,0) -> 43859 | B25: #N/A N/A | C25: #N/A N/A | D25: 16624 | E25: #N/A N/A | F25: #N/A N/A | G25: 175 | H25: 60 | I25: 8 | J25: 23.92
A26: =WORKDAY(A25,1,0) -> 43860 | B26: #N/A N/A | C26: #N/A N/A | D26: 14092 | E26: #N/A N/A | F26: #N/A N/A | G26: 448 | H26: #N/A N/A | I26: #N/A N/A | J26: 23.67
A27: =WORKDAY(A26,1,0) -> 43861 | B27: #N/A N/A | C27: #N/A N/A | D27: 13710 | E27: #N/A N/A | F27: #N/A N/A | G27: 1062 | H27: #N/A N/A | I27: #N/A N/A | J27: 23.82
A28: =WORKDAY(A27,1,0) -> 43864 | B28: #N/A N/A | C28: #N/A N/A | D28: 10452 | E28: #N/A N/A | F28: #N/A N/A | G28: 326 | H28: #N/A N/A | I28: 57 | J28: 23.15
A29: =WORKDAY(A28,1,0) -> 43865 | B29: #N/A N/A | C29: #N/A N/A | D29: 14438 | E29: #N/A N/A | F29: #N/A N/A | G29: 37 | H29: 41 | I29: 91 | J29: 23.3
A30: =WORKDAY(A29,1,0) -> 43866 | B30: #N/A N/A | C30: #N/A N/A | D30: 15255 | E30: #N/A N/A | F30: #N/A N/A | G30: 100 | H30: 42 | I30: 243 | J30: 23.71
A31: =WORKDAY(A30,1,0) -> 43867 | B31: #N/A N/A | C31: #N/A N/A | D31: 14511 | E31: #N/A N/A | F31: #N/A N/A | G31: 1611 | H31: 35 | I31: 101 | J31: 23.5
A32: =WORKDAY(A31,1,0) -> 43868 | B32: #N/A N/A | C32: #N/A N/A | D32: 14545 | E32: #N/A N/A | F32: #N/A N/A | G32: 132 | H32: 15 | I32: 186 | J32: 23.26
A33: =WORKDAY(A32,1,0) -> 43871 | B33: #N/A N/A | C33: #N/A N/A | D33: 11705 | E33: #N/A N/A | F33: #N/A N/A | G33: 77 | H33: 20 | I33: 28 | J33: 23.11
A34: =WORKDAY(A33,1,0) -> 43872 | B34: #N/A N/A | C34: #N/A N/A | D34: 18146 | E34: #N/A N/A | F34: #N/A N/A | G34: 3044 | H34: 20 | I34: #N/A N/A | J34: 23.25
A35: =WORKDAY(A34,1,0) -> 43873 | B35: #N/A N/A | C35: #N/A N/A | D35: 16915 | E35: #N/A N/A | F35: #N/A N/A | G35: 321 | H35: 20 | I35: 33 | J35: 23.83
A36: =WORKDAY(A35,1,0) -> 43874 | B36: #N/A N/A | C36: #N/A N/A | D36: 15825 | E36: #N/A N/A | F36: #N/A N/A | G36: 232 | H36: 5 | I36: 28 | J36: 24.35
A37: =WORKDAY(A36,1,0) -> 43875 | B37: #N/A N/A | C37: #N/A N/A | D37: 18765 | E37: #N/A N/A | F37: #N/A N/A | G37: 259 | H37: 25 | I37: 11 | J37: 24.24
A38: =WORKDAY(A37,1,0) -> 43878 | B38: #N/A N/A | C38: #N/A N/A | D38: 16425 | E38: #N/A N/A | F38: #N/A N/A | G38: 87 | H38: 15 | I38: 26 | J38: 25
A39: =WORKDAY(A38,1,0) -> 43879 | B39: #N/A N/A | C39: #N/A N/A | D39: 20475 | E39: #N/A N/A | F39: #N/A N/A | G39: 121 | H39: 15 | I39: 1 | J39: 25.09
A40: =WORKDAY(A39,1,0) -> 43880 | B40: #N/A N/A | C40: #N/A N/A | D40: 20205 | E40: #N/A N/A | F40: #N/A N/A | G40: 80 | H40: 316 | I40: #N/A N/A | J40: 25.66
A41: =WORKDAY(A40,1,0) -> 43881 | B41: #N/A N/A | C41: #N/A N/A | D41: 27092 | E41: #N/A N/A | F41: #N/A N/A | G41: 68 | H41: 40 | I41: 35 | J41: 25.59
A42: =WORKDAY(A41,1,0) -> 43882 | B42: #N/A N/A | C42: #N/A N/A | D42: 18441 | E42: #N/A N/A | F42: #N/A N/A | G42: 211 | H42: 1545 | I42: #N/A N/A | J42: 25.56
A43: =WORKDAY(A42,1,0) -> 43885 | B43: #N/A N/A | C43: #N/A N/A | D43: 23473 | E43: #N/A N/A | F43: #N/A N/A | G43: 154 | H43: 41 | I43: #N/A N/A | J43: 24.53
A44: =WORKDAY(A43,1,0) -> 43886 | B44: #N/A N/A | C44: #N/A N/A | D44: 30419 | E44: #N/A N/A | F44: #N/A N/A | G44: 126 | H44: 20 | I44: #N/A N/A | J44: 24.14
A45: =WORKDAY(A44,1,0) -> 43887 | B45: #N/A N/A | C45: #N/A N/A | D45: 29245 | E45: #N/A N/A | F45: #N/A N/A | G45: 474 | H45: 2273 | I45: #N/A N/A | J45: 24.22
A46: =WORKDAY(A45,1,0) -> 43888 | B46: #N/A N/A | C46: #N/A N/A | D46: 24339 | E46: #N/A N/A | F46: #N/A N/A | G46: 41 | H46: 285 | I46: #N/A N/A | J46: 23.56
A47: =WORKDAY(A46,1,0) -> 43889 | B47: #N/A N/A | C47: #N/A N/A | D47: 13975 | E47: #N/A N/A | F47: #N/A N/A | G47: 2633 | H47: 23 | I47: #N/A N/A | J47: 23.57
A48: =WORKDAY(A47,1,0) -> 43892 | B48: #N/A N/A | C48: #N/A N/A | D48: 15317 | E48: #N/A N/A | F48: #N/A N/A | G48: 114 | H48: #N/A N/A | I48: 69 | J48: 23.49
A49: =WORKDAY(A48,1,0) -> 43893 | B49: #N/A N/A | C49: #N/A N/A | D49: 18224 | E49: #N/A N/A | F49: #N/A N/A | G49: 2612 | H49: 21 | I49: 30 | J49: 23.33
A50: =WORKDAY(A49,1,0) -> 43894 | B50: #N/A N/A | C50: #N/A N/A | D50: 21188 | E50: #N/A N/A | F50: #N/A N/A | G50: 733 | H50: 516 | I50: 74 | J50: 23.8
A51: =WORKDAY(A50,1,0) -> 43895 | B51: #N/A N/A | C51: #N/A N/A | D51: 14836 | E51: #N/A N/A | F51: #N/A N/A | G51: 67 | H51: 35 | I51: 114 | J51: 23.77
A52: =WORKDAY(A51,1,0) -> 43896 | B52: #N/A N/A | C52: #N/A N/A | D52: 22935 | E52: #N/A N/A | F52: #N/A N/A | G52: 675 | H52: 22 | I52: 63 | J52: 23.39
A53: =WORKDAY(A52,1,0) -> 43899 | B53: #N/A N/A | C53: #N/A N/A | D53: 23910 | E53: #N/A N/A | F53: #N/A N/A | G53: 238 | H53: 30 | I53: 44 | J53: 23.25
A54: =WORKDAY(A53,1,0) -> 43900 | B54: #N/A N/A | C54: #N/A N/A | D54: 25067 | E54: #N/A N/A | F54: #N/A N/A | G54: 2094 | H54: 13 | I54: #N/A N/A | J54: 24.07
A55: =WORKDAY(A54,1,0) -> 43901 | B55: #N/A N/A | C55: #N/A N/A | D55: 33315 | E55: #N/A N/A | F55: #N/A N/A | G55: 450 | H55: 2030 | I55: #N/A N/A | J55: 23.89
A56: =WORKDAY(A55,1,0) -> 43902 | B56: #N/A N/A | C56: #N/A N/A | D56: 31373 | E56: #N/A N/A | F56: #N/A N/A | G56: 316 | H56: 117 | I56: 17 | J56: 22.49
A57: =WORKDAY(A56,1,0) -> 43903 | B57: #N/A N/A | C57: #N/A N/A | D57: 30955 | E57: #N/A N/A | F57: #N/A N/A | G57: 780 | H57: 19 | I57: 20 | J57: 21.89
A58: =WORKDAY(A57,1,0) -> 43906 | B58: #N/A N/A | C58: #N/A N/A | D58: 31197 | E58: #N/A N/A | F58: #N/A N/A | G58: 1918 | H58: 526 | I58: 16 | J58: 19.41
A59: =WORKDAY(A58,1,0) -> 43907 | B59: #N/A N/A | C59: #N/A N/A | D59: 25665 | E59: #N/A N/A | F59: #N/A N/A | G59: 2770 | H59: 343 | I59: 21 | J59: 18.25
A60: =WORKDAY(A59,1,0) -> 43908 | B60: #N/A N/A | C60: #N/A N/A | D60: 24275 | E60: #N/A N/A | F60: #N/A N/A | G60: 5174 | H60: 4022 | I60: #N/A N/A | J60: 15.24
A61: =WORKDAY(A60,1,0) -> 43909 | B61: #N/A N/A | C61: #N/A N/A | D61: 24099 | E61: #N/A N/A | F61: #N/A N/A | G61: 6879 | H61: 275 | I61: 1 | J61: 16.31
A62: =WORKDAY(A61,1,0) -> 43910 | B62: #N/A N/A | C62: #N/A N/A | D62: 28856 | E62: #N/A N/A | F62: #N/A N/A | G62: 1816 | H62: 1017 | I62: 153 | J62: 16.04
A63: =WORKDAY(A62,1,0) -> 43913 | B63: #N/A N/A | C63: #N/A N/A | D63: 27880 | E63: #N/A N/A | F63: #N/A N/A | G63: 3762 | H63: 3873 | I63: 2 | J63: 15.45
A64: =WORKDAY(A63,1,0) -> 43914 | B64: #N/A N/A | C64: #N/A N/A | D64: 25216 | E64: #N/A N/A | F64: #N/A N/A | G64: 753 | H64: 30 | I64: 6 | J64: 16.7
A65: =WORKDAY(A64,1,0) -> 43915 | B65: #N/A N/A | C65: #N/A N/A | D65: 25263 | E65: #N/A N/A | F65: #N/A N/A | G65: 631 | H65: #N/A N/A | I65: 5 | J65: 17.41
A66: =WORKDAY(A65,1,0) -> 43916 | B66: #N/A N/A | C66: #N/A N/A | D66: 16927 | E66: #N/A N/A | F66: #N/A N/A | G66: 1166 | H66: 961 | I66: #N/A N/A | J66: 17.22
A67: =WORKDAY(A66,1,0) -> 43917 | B67: #N/A N/A | C67: #N/A N/A | D67: 29936 | E67: #N/A N/A | F67: #N/A N/A | G67: 530 | H67: 624 | I67: #N/A N/A | J67: 16.26
A68: =WORKDAY(A67,1,0) -> 43920 | B68: #N/A N/A | C68: #N/A N/A | D68: 20883 | E68: #N/A N/A | F68: #N/A N/A | G68: 4354 | H68: 20 | I68: 224 | J68: 16.93
A69: =WORKDAY(A68,1,0) -> 43921 | B69: #N/A N/A | C69: #N/A N/A | D69: 14657 | E69: #N/A N/A | F69: #N/A N/A | G69: 15 | H69: 265 | I69: 141 | J69: 17.59
A70: =WORKDAY(A69,1,0) -> 43922 | B70: #N/A N/A | C70: #N/A N/A | D70: 15095 | E70: #N/A N/A | F70: #N/A N/A | G70: 14 | H70: 15 | I70: 516 | J70: 17
A71: =WORKDAY(A70,1,0) -> 43923 | B71: #N/A N/A | C71: #N/A N/A | D71: 19839 | E71: #N/A N/A | F71: #N/A N/A | G71: 465 | H71: 15 | I71: 50 | J71: 17.99
A72: =WORKDAY(A71,1,0) -> 43924 | B72: #N/A N/A | C72: #N/A N/A | D72: 13801 | E72: #N/A N/A | F72: #N/A N/A | G72: 9 | H72: 1 | I72: 122 | J72: 17.89
A73: =WORKDAY(A72,1,0) -> 43927 | B73: #N/A N/A | C73: #N/A N/A | D73: 15743 | E73: #N/A N/A | F73: #N/A N/A | G73: 512 | H73: 2 | I73: 83 | J73: 20.33
A74: =WORKDAY(A73,1,0) -> 43928 | B74: #N/A N/A | C74: #N/A N/A | D74: 16927 | E74: #N/A N/A | F74: #N/A N/A | G74: 207 | H74: #N/A N/A | I74: 60 | J74: 20.44
A75: =WORKDAY(A74,1,0) -> 43929 | B75: #N/A N/A | C75: #N/A N/A | D75: 15527 | E75: #N/A N/A | F75: #N/A N/A | G75: 1216 | H75: 1 | I75: 20 | J75: 21.06
A76: =WORKDAY(A75,1,0) -> 43930 | B76: #N/A N/A | C76: #N/A N/A | D76: 10965 | E76: #N/A N/A | F76: #N/A N/A | G76: 364 | H76: 8 | I76: 20 | J76: 21.01
A77: =WORKDAY(A76,1,0) -> 43931 | B77: #N/A N/A | C77: #N/A N/A | D77: #N/A N/A | E77: #N/A N/A | F77: #N/A N/A | G77: #N/A N/A | H77: #N/A N/A | I77: #N/A N/A | J77: #N/A N/A
A78: =WORKDAY(A77,1,0) -> 43934 | B78: #N/A N/A | C78: #N/A N/A | D78: #N/A N/A | E78: #N/A N/A | F78: #N/A N/A | G78: #N/A N/A | H78: #N/A N/A | I78: #N/A N/A | J78: #N/A N/A
A79: =WORKDAY(A78,1,0) -> 43935 | B79: #N/A N/A | C79: #N/A N/A | D79: 14190 | E79: #N/A N/A | F79: #N/A N/A | G79: 258 | H79: 8 | I79: 42 | J79: 19.76
A80: =WORKDAY(A79,1,0) -> 43936 | B80: #N/A N/A | C80: #N/A N/A | D80: 18470 | E80: #N/A N/A | F80: #N/A N/A | G80: 1221 | H80: 25 | I80: 25 | J80: 19.2
A81: =WORKDAY(A80,1,0) -> 43937 | B81: #N/A N/A | C81: #N/A N/A | D81: 24430 | E81: #N/A N/A | F81: #N/A N/A | G81: 1355 | H81: 7 | I81: 25 | J81: 20.89
A82: =WORKDAY(A81,1,0) -> 43938 | B82: #N/A N/A | C82: #N/A N/A | D82: 17076 | E82: #N/A N/A | F82: #N/A N/A | G82: 1093 | H82: #N/A N/A | I82: 7 | J82: 21.64
A83: =WORKDAY(A82,1,0) -> 43941 | B83: #N/A N/A | C83: #N/A N/A | D83: 16983 | E83: #N/A N/A | F83: #N/A N/A | G83: 1045 | H83: #N/A N/A | I83: 15 | J83: 21.32
A84: =WORKDAY(A83,1,0) -> 43942 | B84: #N/A N/A | C84: #N/A N/A | D84: 21340 | E84: #N/A N/A | F84: #N/A N/A | G84: 1309 | H84: #N/A N/A | I84: #N/A N/A | J84: 19.79
A85: =WORKDAY(A84,1,0) -> 43943 | B85: #N/A N/A | C85: #N/A N/A | D85: 27865 | E85: #N/A N/A | F85: #N/A N/A | G85: 1275 | H85: 18 | I85: #N/A N/A | J85: 20.59
A86: =WORKDAY(A85,1,0) -> 43944 | B86: #N/A N/A | C86: #N/A N/A | D86: 18527 | E86: #N/A N/A | F86: #N/A N/A | G86: 553 | H86: 6 | I86: 3 | J86: 20.97
A87: =WORKDAY(A86,1,0) -> 43945 | B87: #N/A N/A | C87: #N/A N/A | D87: 19994 | E87: #N/A N/A | F87: #N/A N/A | G87: 307 | H87: 8 | I87: #N/A N/A | J87: 20.68
A88: =WORKDAY(A87,1,0) -> 43948 | B88: #N/A N/A | C88: #N/A N/A | D88: 18568 | E88: #N/A N/A | F88: #N/A N/A | G88: 509 | H88: 11 | I88: 90 | J88: 20.22
A89: =WORKDAY(A88,1,0) -> 43949 | B89: #N/A N/A | C89: #N/A N/A | D89: 22706 | E89: #N/A N/A | F89: #N/A N/A | G89: 1108 | H89: 9 | I89: 20 | J89: 20.15
A90: =WORKDAY(A89,1,0) -> 43950 | B90: #N/A N/A | C90: #N/A N/A | D90: 12335 | E90: #N/A N/A | F90: #N/A N/A | G90: 1009 | H90: 9 | I90: 22 | J90: 20.13
A91: =WORKDAY(A90,1,0) -> 43951 | B91: #N/A N/A | C91: #N/A N/A | D91: 10939 | E91: #N/A N/A | F91: #N/A N/A | G91: 914 | H91: 32 | I91: 24 | J91: 19.51
A92: =WORKDAY(A91,1,0) -> 43952 | B92: #N/A N/A | C92: #N/A N/A | D92: 9068 | E92: #N/A N/A | F92: #N/A N/A | G92: 79 | H92: #N/A N/A | I92: #N/A N/A | J92: 18.91
A93: =WORKDAY(A92,1,0) -> 43955 | B93: #N/A N/A | C93: #N/A N/A | D93: 10705 | E93: #N/A N/A | F93: #N/A N/A | G93: 2283 | H93: 2267 | I93: 3 | J93: 19.29
A94: =WORKDAY(A93,1,0) -> 43956 | B94: #N/A N/A | C94: #N/A N/A | D94: 9867 | E94: #N/A N/A | F94: #N/A N/A | G94: 530 | H94: 17 | I94: 69 | J94: 19.03
A95: =WORKDAY(A94,1,0) -> 43957 | B95: #N/A N/A | C95: #N/A N/A | D95: 12959 | E95: #N/A N/A | F95: #N/A N/A | G95: 3058 | H95: 1119 | I95: 13 | J95: 18.94
A96: =WORKDAY(A95,1,0) -> 43958 | B96: #N/A N/A | C96: #N/A N/A | D96: 13186 | E96: #N/A N/A | F96: #N/A N/A | G96: 9 | H96: 17 | I96: 40 | J96: 19.48
A97: =WORKDAY(A96,1,0) -> 43959 | B97: #N/A N/A | C97: #N/A N/A | D97: 1318 | E97: #N/A N/A | F97: #N/A N/A | G97: 212 | H97: 18 | I97: #N/A N/A | J97: 19.29
A98: =WORKDAY(A97,1,0) -> 43962 | B98: #N/A N/A | C98: #N/A N/A | D98: 14566 | E98: #N/A N/A | F98: #N/A N/A | G98: 129 | H98: 23 | I98: #N/A N/A | J98: 19
A99: =WORKDAY(A98,1,0) -> 43963 | B99: #N/A N/A | C99: #N/A N/A | D99: 14965 | E99: #N/A N/A | F99: #N/A N/A | G99: 37 | H99: 165 | I99: 5 | J99: 18.46
A100: =WORKDAY(A99,1,0) -> 43964 | B100: #N/A N/A | C100: #N/A N/A | D100: 19170 | E100: #N/A N/A | F100: #N/A N/A | G100: 22 | H100: 668 | I100: #N/A N/A | J100: 18.6
...

Sheet Prices
A1: Paste Bloomberg historical price export here
A2: Recommended: export daily PX_LAST in wide format with dates in rows and tickers in columns. Paste starting at A4.
A4: Date | B4: TZTA Comdty | C4: TZTB Comdty | D4: TZT1 Comdty | E4: FNA Comdty | F4: FNB Comdty | G4: MO1 Comdty | H4: MO2 Comdty | I4: BDIY Index | J4: TMR1 Comdty | K4: TTFG1MON Index | L4: TTFDDAHD Index | M4: RTEGNUCT Index | N4: RTEGNUCD Index | O4: API21MON Index | P4: XA1 Comdty | Q4: XAA Comdty | R4: DEBM A Comdty | S4: DEPK A Comdty | T4: EEXXT3PA Index | U4: ELGB1MON Index | V4: ELGP1MON Index | W4: DBRST3PA Index
A5: 43831 | B5: #N/A N/A | C5: #N/A N/A | D5: #N/A N/A | E5: #N/A N/A | F5: #N/A N/A | G5: #N/A N/A | H5: #N/A N/A | I5: #N/A N/A | J5: #N/A N/A | K5: #N/A N/A | L5: #N/A N/A | M5: 49403 | N5: 1185670 | O5: #N/A N/A | P5: #N/A N/A | Q5: #N/A N/A | R5: #N/A N/A | S5: #N/A N/A | T5: #N/A N/A | U5: #N/A N/A | V5: #N/A N/A | W5: #N/A N/A
A6: =A5+1 -> 43832 | B6: 16.202 | C6: 15.932 | D6: 12.073 | E6: 40.91 | F6: 40.7 | G6: 24.28 | H6: 24.32 | I6: 976 | J6: 3.963 | K6: 12.05 | L6: #N/A N/A | M6: 50085 | N6: 1202051 | O6: #N/A N/A | P6: 52.1 | Q6: #N/A N/A | R6: #N/A N/A | S6: #N/A N/A | T6: #N/A N/A | U6: 39.85 | V6: #N/A N/A | W6: #N/A N/A
A7: =WORKDAY(A6,1,0) -> 43833 | B7: 16.414 | C7: 16.144 | D7: 12.985 | E7: 42.49 | F7: 42.28 | G7: 24.9 | H7: 24.93 | I7: 907 | J7: 4.223 | K7: 12.975 | L7: #N/A N/A | M7: 48881 | N7: 1173136 | O7: #N/A N/A | P7: 52.75 | Q7: #N/A N/A | R7: #N/A N/A | S7: #N/A N/A | T7: #N/A N/A | U7: 40.2 | V7: #N/A N/A | W7: #N/A N/A
A8: =WORKDAY(A7,1,0) -> 43836 | B8: 16.216 | C8: 15.946 | D8: 12.28 | E8: 42.01 | F8: 41.8 | G8: 24.15 | H8: 24.18 | I8: 844 | J8: 4.031 | K8: 12.25 | L8: #N/A N/A | M8: 51770 | N8: 1242490 | O8: #N/A N/A | P8: 52.65 | Q8: #N/A N/A | R8: #N/A N/A | S8: #N/A N/A | T8: #N/A N/A | U8: 39.3 | V8: #N/A N/A | W8: #N/A N/A
A9: =WORKDAY(A8,1,0) -> 43837 | B9: 16.044 | C9: 15.774 | D9: 11.929 | E9: 41.26 | F9: 41.05 | G9: 24.47 | H9: 24.5 | I9: 791 | J9: 3.923 | K9: #N/A N/A | L9: #N/A N/A | M9: 51891 | N9: 1245387 | O9: #N/A N/A | P9: 52.55 | Q9: #N/A N/A | R9: #N/A N/A | S9: #N/A N/A | T9: 24.06 | U9: 38.75 | V9: #N/A N/A | W9: 24.06
A10: =WORKDAY(A9,1,0) -> 43838 | B10: 16.179 | C10: 15.909 | D10: 11.964 | E10: 41.18 | F10: 40.97 | G10: 23.97 | H10: 24.02 | I10: 773 | J10: 3.926 | K10: #N/A N/A | L10: #N/A N/A | M10: 51676 | N10: 1240222 | O10: #N/A N/A | P10: 52.5 | Q10: #N/A N/A | R10: #N/A N/A | S10: #N/A N/A | T10: #N/A N/A | U10: 39 | V10: #N/A N/A | W10: #N/A N/A
A11: =WORKDAY(A10,1,0) -> 43839 | B11: 16.208 | C11: 15.938 | D11: 12.179 | E11: 41.39 | F11: 41.18 | G11: 24.58 | H11: 24.62 | I11: 772 | J11: 3.973 | K11: 12 | L11: #N/A N/A | M11: 45942 | N11: 1102619 | O11: #N/A N/A | P11: 52.7 | Q11: #N/A N/A | R11: #N/A N/A | S11: #N/A N/A | T11: 24.01 | U11: 39.15 | V11: #N/A N/A | W11: 24.01
A12: =WORKDAY(A11,1,0) -> 43840 | B12: 16.21 | C12: 15.94 | D12: 11.94 | E12: 40.98 | F12: 40.77 | G12: 24.12 | H12: 24.16 | I12: 774 | J12: 3.922 | K12: 12 | L12: #N/A N/A | M12: 49475 | N12: 1187409 | O12: #N/A N/A | P12: 52.9 | Q12: #N/A N/A | R12: #N/A N/A | S12: #N/A N/A | T12: 24.48 | U12: 38.65 | V12: #N/A N/A | W12: 24.48
A13: =WORKDAY(A12,1,0) -> 43843 | B13: 16.236 | C13: 15.966 | D13: 12.054 | E13: 41.3 | F13: 41.09 | G13: 24.06 | H13: 24.09 | I13: 765 | J13: 3.951 | K13: #N/A N/A | L13: #N/A N/A | M13: 53695 | N13: 1288687 | O13: 55.15 | P13: 53.5 | Q13: 77.4 | R13: #N/A N/A | S13: #N/A N/A | T13: 24.03 | U13: 38.3 | V13: #N/A N/A | W13: 24.03
A14: =WORKDAY(A13,1,0) -> 43844 | B14: 15.914 | C14: 15.644 | D14: 11.303 | E14: 40.73 | F14: 40.52 | G14: 23.77 | H14: 23.8 | I14: 763 | J14: 3.803 | K14: 11.3 | L14: #N/A N/A | M14: 49302 | N14: 1183242 | O14: 54.6 | P14: 52.2 | Q14: 75.35 | R14: #N/A N/A | S14: #N/A N/A | T14: 23.74 | U14: 36.65 | V14: #N/A N/A | W14: 23.74
A15: =WORKDAY(A14,1,0) -> 43845 | B15: 15.982 | C15: 15.712 | D15: 11.179 | E15: 40.44 | F15: 40.23 | G15: 24.43 | H15: 24.46 | I15: 768 | J15: 3.787 | K15: 11.275 | L15: #N/A N/A | M15: 48965 | N15: 1175155 | O15: #N/A N/A | P15: 51.8 | Q15: 75.4 | R15: #N/A N/A | S15: #N/A N/A | T15: 24.2 | U15: 36.2 | V15: #N/A N/A | W15: 24.2
A16: =WORKDAY(A15,1,0) -> 43846 | B16: 15.981 | C16: 15.711 | D16: 11.117 | E16: 40.01 | F16: 39.8 | G16: 24.77 | H16: 24.8 | I16: 768 | J16: 3.775 | K16: #N/A N/A | L16: #N/A N/A | M16: 49534 | N16: 1188812 | O16: #N/A N/A | P16: 51 | Q16: 74.1 | R16: #N/A N/A | S16: #N/A N/A | T16: 24.85 | U16: 36.05 | V16: #N/A N/A | W16: 24.85
A17: =WORKDAY(A16,1,0) -> 43847 | B17: 15.884 | C17: 15.614 | D17: 10.929 | E17: 39.42 | F17: 39.21 | G17: 25.36 | H17: 25.39 | I17: 754 | J17: 3.74 | K17: #N/A N/A | L17: #N/A N/A | M17: 50039 | N17: 1200946 | O17: #N/A N/A | P17: 50.5 | Q17: 72.2 | R17: #N/A N/A | S17: #N/A N/A | T17: 25.01 | U17: 35.95 | V17: #N/A N/A | W17: 25.01
A18: =WORKDAY(A17,1,0) -> 43850 | B18: 15.972 | C18: 15.857 | D18: 10.566 | E18: 39.36 | F18: 39.15 | G18: 25.11 | H18: 25.14 | I18: 729 | J18: 3.69 | K18: #N/A N/A | L18: #N/A N/A | M18: 49921 | N18: 1198094 | O18: #N/A N/A | P18: 49.75 | Q18: 72.25 | R18: #N/A N/A | S18: #N/A N/A | T18: 25.6 | U18: 34.8 | V18: #N/A N/A | W18: 25.6
A19: =WORKDAY(A18,1,0) -> 43851 | B19: 15.84 | C19: 15.725 | D19: 10.777 | E19: 39.21 | F19: 39 | G19: 24.85 | H19: 24.88 | I19: 689 | J19: 3.717 | K19: #N/A N/A | L19: #N/A N/A | M19: 51360 | N19: 1232646 | O19: #N/A N/A | P19: 50.6 | Q19: 72.8 | R19: #N/A N/A | S19: #N/A N/A | T19: 25.1 | U19: 34.75 | V19: #N/A N/A | W19: 25.1
A20: =WORKDAY(A19,1,0) -> 43852 | B20: 15.77 | C20: 15.655 | D20: 10.455 | E20: 38.35 | F20: 38.14 | G20: 24.94 | H20: 24.97 | I20: 623 | J20: 3.682 | K20: 10.4 | L20: #N/A N/A | M20: 52174 | N20: 1252174 | O20: #N/A N/A | P20: 50.25 | Q20: 72.25 | R20: #N/A N/A | S20: #N/A N/A | T20: #N/A N/A | U20: 35 | V20: #N/A N/A | W20: #N/A N/A
A21: =WORKDAY(A20,1,0) -> 43853 | B21: 15.731 | C21: 15.616 | D21: 10.428 | E21: 38.24 | F21: 38.03 | G21: 24.63 | H21: 24.66 | I21: 576 | J21: 3.677 | K21: #N/A N/A | L21: #N/A N/A | M21: 51311 | N21: 1231466 | O21: #N/A N/A | P21: 50.4 | Q21: 72.95 | R21: #N/A N/A | S21: #N/A N/A | T21: 24.65 | U21: 35.7 | V21: #N/A N/A | W21: 24.65
A22: =WORKDAY(A21,1,0) -> 43854 | B22: 15.365 | C22: 15.25 | D22: 10.455 | E22: 38.09 | F22: 37.88 | G22: 24.3 | H22: 24.33 | I22: 557 | J22: 3.677 | K22: #N/A N/A | L22: #N/A N/A | M22: 50772 | N22: 1218530 | O22: #N/A N/A | P22: 50.25 | Q22: 73.15 | R22: #N/A N/A | S22: #N/A N/A | T22: 24.48 | U22: 35.5 | V22: #N/A N/A | W22: 24.48
A23: =WORKDAY(A22,1,0) -> 43857 | B23: 15.258 | C23: 15.143 | D23: 10.526 | E23: 37.96 | F23: 37.75 | G23: 24.52 | H23: 24.55 | I23: 546 | J23: 3.681 | K23: 10.54 | L23: #N/A N/A | M23: 48536 | N23: 1164870 | O23: #N/A N/A | P23: 50.35 | Q23: 73.2 | R23: #N/A N/A | S23: #N/A N/A | T23: 24.04 | U23: 35.6 | V23: #N/A N/A | W23: 24.04
A24: =WORKDAY(A23,1,0) -> 43858 | B24: 15.64 | C24: 15.525 | D24: 10.792 | E24: 38.39 | F24: 38.18 | G24: 24.58 | H24: 24.61 | I24: 539 | J24: 3.692 | K24: #N/A N/A | L24: #N/A N/A | M24: 49863 | N24: 1196716 | O24: #N/A N/A | P24: 50.35 | Q24: 74.35 | R24: #N/A N/A | S24: #N/A N/A | T24: 24.55 | U24: 35.8 | V24: #N/A N/A | W24: 24.55
A25: =WORKDAY(A24,1,0) -> 43859 | B25: 15.298 | C25: 15.183 | D25: 10.15 | E25: 37.49 | F25: 37.28 | G25: 23.92 | H25: 23.95 | I25: 525 | J25: 3.673 | K25: #N/A N/A | L25: #N/A N/A | M25: 47447 | N25: 1138721 | O25: 49.4 | P25: 50.15 | Q25: 73.85 | R25: #N/A N/A | S25: #N/A N/A | T25: 24.04 | U25: 33.45 | V25: #N/A N/A | W25: 24.04
A26: =WORKDAY(A25,1,0) -> 43860 | B26: 15.04 | C26: 14.925 | D26: 9.781 | E26: 36.31 | F26: 36.1 | G26: 23.67 | H26: 23.7 | I26: 498 | J26: 3.668 | K26: #N/A N/A | L26: #N/A N/A | M26: 49825 | N26: 1195804 | O26: #N/A N/A | P26: 50.45 | Q26: 72 | R26: #N/A N/A | S26: #N/A N/A | T26: 23.74 | U26: 32.1 | V26: #N/A N/A | W26: 23.74
A27: =WORKDAY(A26,1,0) -> 43861 | B27: 14.754 | C27: 14.639 | D27: 9.755 | E27: 36.24 | F27: 36.03 | G27: 23.82 | H27: 23.84 | I27: 487 | J27: 3.168 | K27: 9.775 | L27: #N/A N/A | M27: 48410 | N27: 1161844 | O27: #N/A N/A | P27: 50.35 | Q27: 72.35 | R27: #N/A N/A | S27: #N/A N/A | T27: 23.48 | U27: 31.2 | V27: #N/A N/A | W27: 23.48
A28: =WORKDAY(A27,1,0) -> 43864 | B28: 14.83 | C28: 14.715 | D28: 9.211 | E28: 35.47 | F28: 35.26 | G28: 23.15 | H28: 23.17 | I28: 466 | J28: 2.994 | K28: #N/A N/A | L28: #N/A N/A | M28: 49680 | N28: 1192330 | O28: #N/A N/A | P28: 47.7 | Q28: 72.3 | R28: #N/A N/A | S28: #N/A N/A | T28: 23.2 | U28: 32 | V28: #N/A N/A | W28: 23.2
A29: =WORKDAY(A28,1,0) -> 43865 | B29: 15.171 | C29: 15.056 | D29: 9.366 | E29: 36.28 | F29: 36.07 | G29: 23.3 | H29: 23.32 | I29: 453 | J29: 3.035 | K29: #N/A N/A | L29: #N/A N/A | M29: 51181 | N29: 1228347 | O29: #N/A N/A | P29: 48.9 | Q29: 73.15 | R29: #N/A N/A | S29: #N/A N/A | T29: 23.33 | U29: 32.3 | V29: #N/A N/A | W29: 23.33
A30: =WORKDAY(A29,1,0) -> 43866 | B30: 15.696 | C30: 15.581 | D30: 9.313 | E30: 37.49 | F30: 37.28 | G30: 23.71 | H30: 23.73 | I30: 430 | J30: 3.012 | K30: #N/A N/A | L30: #N/A N/A | M30: 52817 | N30: 1267617 | O30: 51 | P30: 49.45 | Q30: 73.6 | R30: #N/A N/A | S30: #N/A N/A | T30: #N/A N/A | U30: 32.5 | V30: #N/A N/A | W30: #N/A N/A
A31: =WORKDAY(A30,1,0) -> 43867 | B31: 15.464 | C31: 15.349 | D31: 9.149 | E31: 37.18 | F31: 36.97 | G31: 23.5 | H31: 23.52 | I31: 431 | J31: 2.964 | K31: 9.2 | L31: #N/A N/A | M31: 50895 | N31: 1221490 | O31: 49.8 | P31: 48.9 | Q31: 72.7 | R31: #N/A N/A | S31: #N/A N/A | T31: 23.4 | U31: 32.15 | V31: #N/A N/A | W31: 23.4
A32: =WORKDAY(A31,1,0) -> 43868 | B32: 15.6 | C32: 15.485 | D32: 9.068 | E32: 37.7 | F32: 37.49 | G32: 23.26 | H32: 23.28 | I32: 415 | J32: 2.942 | K32: 9.05 | L32: #N/A N/A | M32: 51961 | N32: 1247073 | O32: #N/A N/A | P32: 48.2 | Q32: 71.75 | R32: #N/A N/A | S32: #N/A N/A | T32: 23.17 | U32: 31.2 | V32: #N/A N/A | W32: 23.17
A33: =WORKDAY(A32,1,0) -> 43871 | B33: 15.52 | C33: 15.405 | D33: 8.643 | E33: 36.89 | F33: 36.68 | G33: 23.11 | H33: 23.13 | I33: 411 | J33: 2.839 | K33: #N/A N/A | L33: #N/A N/A | M33: 46869 | N33: 1124854 | O33: #N/A N/A | P33: 47.5 | Q33: 70.75 | R33: #N/A N/A | S33: #N/A N/A | T33: 22.91 | U33: 29.8 | V33: #N/A N/A | W33: 22.91
A34: =WORKDAY(A33,1,0) -> 43872 | B34: 15.964 | C34: 15.849 | D34: 8.557 | E34: 37.09 | F34: 36.88 | G34: 23.25 | H34: 23.27 | I34: 418 | J34: 2.82 | K34: #N/A N/A | L34: 8.85 | M34: 48190 | N34: 1156567 | O34: 49 | P34: 48 | Q34: 71.8 | R34: #N/A N/A | S34: #N/A N/A | T34: 23.15 | U34: 30.2 | V34: #N/A N/A | W34: 23.15
A35: =WORKDAY(A34,1,0) -> 43873 | B35: 16.273 | C35: 16.158 | D35: 8.722 | E35: 37.5 | F35: 37.29 | G35: 23.83 | H35: 23.85 | I35: 421 | J35: 2.848 | K35: #N/A N/A | L35: 9.05 | M35: 49807 | N35: 1195362 | O35: #N/A N/A | P35: 48.75 | Q35: 72.55 | R35: #N/A N/A | S35: #N/A N/A | T35: 23.35 | U35: 30.1 | V35: #N/A N/A | W35: 23.35
A36: =WORKDAY(A35,1,0) -> 43874 | B36: 16.435 | C36: 16.32 | D36: 8.889 | E36: 38.37 | F36: 38.16 | G36: 24.35 | H36: 24.37 | I36: 421 | J36: 2.871 | K36: 8.75 | L36: 8.9 | M36: 48674 | N36: 1168181 | O36: 51.25 | P36: 49.9 | Q36: 73.25 | R36: #N/A N/A | S36: #N/A N/A | T36: 23.52 | U36: 30.45 | V36: #N/A N/A | W36: 23.52
A37: =WORKDAY(A36,1,0) -> 43875 | B37: 16.626 | C37: 16.511 | D37: 8.879 | E37: 38.88 | F37: 38.67 | G37: 24.24 | H37: 24.26 | I37: 425 | J37: 2.869 | K37: #N/A N/A | L37: #N/A N/A | M37: 49831 | N37: 1195951 | O37: #N/A N/A | P37: 50.3 | Q37: 73.45 | R37: #N/A N/A | S37: #N/A N/A | T37: 24.27 | U37: 30.2 | V37: #N/A N/A | W37: 24.27
A38: =WORKDAY(A37,1,0) -> 43878 | B38: 16.576 | C38: 16.461 | D38: 9.312 | E38: 39.53 | F38: 39.32 | G38: 25 | H38: 25.02 | I38: 434 | J38: 2.929 | K38: #N/A N/A | L38: #N/A N/A | M38: 47913 | N38: 1149916 | O38: #N/A N/A | P38: 50.55 | Q38: 74.55 | R38: #N/A N/A | S38: #N/A N/A | T38: 24.11 | U38: 29.6 | V38: #N/A N/A | W38: 24.11
A39: =WORKDAY(A38,1,0) -> 43879 | B39: 16.411 | C39: 16.296 | D39: 9.38 | E39: 39.1 | F39: 38.89 | G39: 25.09 | H39: 25.11 | I39: 450 | J39: 2.937 | K39: #N/A N/A | L39: #N/A N/A | M39: 49930 | N39: 1198309 | O39: #N/A N/A | P39: 49.7 | Q39: 72.75 | R39: #N/A N/A | S39: #N/A N/A | T39: 24.8 | U39: 29.8 | V39: #N/A N/A | W39: 24.8
A40: =WORKDAY(A39,1,0) -> 43880 | B40: 16.139 | C40: 16.024 | D40: 9.572 | E40: 39.28 | F40: 39.07 | G40: 25.66 | H40: 25.68 | I40: 465 | J40: 2.955 | K40: 9.55 | L40: 9.3 | M40: 49174 | N40: 1180175 | O40: #N/A N/A | P40: 49.3 | Q40: 72.45 | R40: #N/A N/A | S40: #N/A N/A | T40: #N/A N/A | U40: 30.25 | V40: #N/A N/A | W40: #N/A N/A
A41: =WORKDAY(A40,1,0) -> 43881 | B41: 15.951 | C41: 15.836 | D41: 9.567 | E41: 38.81 | F41: 38.6 | G41: 25.59 | H41: 25.61 | I41: 480 | J41: 2.956 | K41: #N/A N/A | L41: 9.5 | M41: 45308 | N41: 1087383 | O41: #N/A N/A | P41: 48.4 | Q41: 72.05 | R41: #N/A N/A | S41: #N/A N/A | T41: 25.5 | U41: 30.05 | V41: #N/A N/A | W41: 25.5
A42: =WORKDAY(A41,1,0) -> 43882 | B42: 15.696 | C42: 15.581 | D42: 9.41 | E42: 38.79 | F42: 38.58 | G42: 25.56 | H42: 25.58 | I42: 497 | J42: 2.947 | K42: 9.3 | L42: #N/A N/A | M42: 48144 | N42: 1155467 | O42: 47.75 | P42: 48.3 | Q42: 71.85 | R42: #N/A N/A | S42: #N/A N/A | T42: 25.15 | U42: 29.95 | V42: #N/A N/A | W42: 25.15
A43: =WORKDAY(A42,1,0) -> 43885 | B43: 15.531 | C43: 15.416 | D43: 9.044 | E43: 37.78 | F43: 37.57 | G43: 24.53 | H43: 24.55 | I43: 506 | J43: 2.924 | K43: #N/A N/A | L43: #N/A N/A | M43: 47048 | N43: 1129141 | O43: #N/A N/A | P43: 48 | Q43: 70.5 | R43: #N/A N/A | S43: #N/A N/A | T43: 24.64 | U43: 29.6 | V43: #N/A N/A | W43: 24.64
A44: =WORKDAY(A43,1,0) -> 43886 | B44: 15.435 | C44: 15.32 | D44: 9.007 | E44: 37.47 | F44: 37.26 | G44: 24.14 | H44: 24.16 | I44: 508 | J44: 2.922 | K44: 8.95 | L44: #N/A N/A | M44: 46122 | N44: 1106935 | O44: #N/A N/A | P44: 48.15 | Q44: 70.45 | R44: #N/A N/A | S44: #N/A N/A | T44: 24.32 | U44: 29.75 | V44: #N/A N/A | W44: 24.32
A45: =WORKDAY(A44,1,0) -> 43887 | B45: 15.471 | C45: 15.356 | D45: 9.071 | E45: 37.99 | F45: 37.78 | G45: 24.22 | H45: 24.24 | I45: 517 | J45: 2.924 | K45: #N/A N/A | L45: #N/A N/A | M45: 47119 | N45: 1130857 | O45: 46.9 | P45: 48 | Q45: 70.6 | R45: #N/A N/A | S45: #N/A N/A | T45: 23.85 | U45: 29.75 | V45: #N/A N/A | W45: 23.85
A46: =WORKDAY(A45,1,0) -> 43888 | B46: 15.471 | C46: 15.356 | D46: 8.871 | E46: 37.75 | F46: 37.54 | G46: 23.56 | H46: 23.57 | I46: 529 | J46: 2.923 | K46: 8.8 | L46: 9.3 | M46: 45414 | N46: 1089934 | O46: 47.25 | P46: 47.9 | Q46: 70 | R46: #N/A N/A | S46: #N/A N/A | T46: 23.8 | U46: 29.4 | V46: #N/A N/A | W46: 23.8
A47: =WORKDAY(A46,1,0) -> 43889 | B47: 15.491 | C47: 15.376 | D47: 8.874 | E47: 37.97 | F47: 37.76 | G47: 23.57 | H47: 23.58 | I47: 535 | J47: 2.857 | K47: #N/A N/A | L47: 9.05 | M47: 46989 | N47: 1127726 | O47: #N/A N/A | P47: 47.8 | Q47: 70.2 | R47: #N/A N/A | S47: #N/A N/A | T47: 23.46 | U47: 30.1 | V47: #N/A N/A | W47: 23.46
A48: =WORKDAY(A47,1,0) -> 43892 | B48: 15.43 | C48: 15.315 | D48: 8.887 | E48: 38.39 | F48: 38.18 | G48: 23.49 | H48: 23.5 | I48: 539 | J48: 2.897 | K48: 9.05 | L48: 8.95 | M48: 47210 | N48: 1133033 | O48: #N/A N/A | P48: 46.85 | Q48: 70.3 | R48: #N/A N/A | S48: #N/A N/A | T48: 23.96 | U48: 28.15 | V48: #N/A N/A | W48: 23.96
A49: =WORKDAY(A48,1,0) -> 43893 | B49: 15.665 | C49: 15.55 | D49: 9.169 | E49: 39.55 | F49: 39.34 | G49: 23.33 | H49: 23.34 | I49: 549 | J49: 2.992 | K49: 9.025 | L49: #N/A N/A | M49: 47130 | N49: 1131120 | O49: #N/A N/A | P49: 46.95 | Q49: 70.75 | R49: #N/A N/A | S49: #N/A N/A | T49: 23.26 | U49: 28.3 | V49: #N/A N/A | W49: 23.26
A50: =WORKDAY(A49,1,0) -> 43894 | B50: 15.54 | C50: 15.425 | D50: 8.912 | E50: 39.77 | F50: 39.56 | G50: 23.8 | H50: 23.81 | I50: 562 | J50: 2.911 | K50: #N/A N/A | L50: 9.35 | M50: 47166 | N50: 1131988 | O50: #N/A N/A | P50: 47.3 | Q50: 70.55 | R50: #N/A N/A | S50: #N/A N/A | T50: #N/A N/A | U50: 28.5 | V50: #N/A N/A | W50: #N/A N/A
A51: =WORKDAY(A50,1,0) -> 43895 | B51: 15.656 | C51: 15.541 | D51: 8.849 | E51: 39.47 | F51: 39.26 | G51: 23.77 | H51: 23.78 | I51: 599 | J51: 2.905 | K51: 8.855 | L51: 9.5 | M51: 45297 | N51: 1087127 | O51: #N/A N/A | P51: 47.8 | Q51: 70.75 | R51: #N/A N/A | S51: #N/A N/A | T51: 23.9 | U51: 28.7 | V51: #N/A N/A | W51: 23.9
A52: =WORKDAY(A51,1,0) -> 43896 | B52: 15.185 | C52: 15.07 | D52: 8.647 | E52: 38.6 | F52: 38.39 | G52: 23.39 | H52: 23.4 | I52: 617 | J52: 2.877 | K52: 8.7 | L52: #N/A N/A | M52: 46020 | N52: 1104488 | O52: #N/A N/A | P52: 47.4 | Q52: 69.7 | R52: #N/A N/A | S52: #N/A N/A | T52: 23.36 | U52: 28.6 | V52: #N/A N/A | W52: 23.36
A53: =WORKDAY(A52,1,0) -> 43899 | B53: 14.686 | C53: 14.571 | D53: 8.627 | E53: 37.18 | F53: 36.97 | G53: 23.25 | H53: 23.27 | I53: 616 | J53: 2.892 | K53: 8.595 | L53: 8.7 | M53: 44939 | N53: 1078529 | O53: 47.3 | P53: 46.4 | Q53: 68.2 | R53: #N/A N/A | S53: #N/A N/A | T53: 22.65 | U53: 28.6 | V53: #N/A N/A | W53: 22.65
A54: =WORKDAY(A53,1,0) -> 43900 | B54: 15.089 | C54: 14.974 | D54: 8.993 | E54: 38.21 | F54: 38 | G54: 24.07 | H54: 24.09 | I54: 627 | J54: 2.962 | K54: #N/A N/A | L54: #N/A N/A | M54: 44203 | N54: 1060870 | O54: 47.5 | P54: 46.4 | Q54: 68.95 | R54: #N/A N/A | S54: #N/A N/A | T54: 23.76 | U54: 30.45 | V54: #N/A N/A | W54: 23.76
A55: =WORKDAY(A54,1,0) -> 43901 | B55: 14.61 | C55: 14.495 | D55: 9.369 | E55: 37.65 | F55: 37.44 | G55: 23.89 | H55: 23.91 | I55: 631 | J55: 3.03 | K55: #N/A N/A | L55: 9.05 | M55: 43182 | N55: 1036368 | O55: #N/A N/A | P55: 46.5 | Q55: 68.95 | R55: #N/A N/A | S55: #N/A N/A | T55: 23.63 | U55: 30.6 | V55: #N/A N/A | W55: 23.63
A56: =WORKDAY(A55,1,0) -> 43902 | B56: 14.448 | C56: 14.333 | D56: 9.324 | E56: 37.14 | F56: 36.93 | G56: 22.49 | H56: 22.51 | I56: 633 | J56: 2.99 | K56: #N/A N/A | L56: 9 | M56: 40972 | N56: 983318 | O56: #N/A N/A | P56: 45.8 | Q56: 68.25 | R56: #N/A N/A | S56: #N/A N/A | T56: 22.85 | U56: 29.85 | V56: #N/A N/A | W56: 22.85
A57: =WORKDAY(A56,1,0) -> 43903 | B57: 14.526 | C57: 14.411 | D57: 9.285 | E57: 37.91 | F57: 37.7 | G57: 21.89 | H57: 21.92 | I57: 631 | J57: 2.981 | K57: #N/A N/A | L57: #N/A N/A | M57: 41813 | N57: 1003507 | O57: #N/A N/A | P57: 46.55 | Q57: 68.55 | R57: #N/A N/A | S57: #N/A N/A | T57: 22.78 | U57: 29.5 | V57: #N/A N/A | W57: 22.78
A58: =WORKDAY(A57,1,0) -> 43906 | B58: 14.245 | C58: 14.13 | D58: 8.741 | E58: 37.42 | F58: 37.21 | G58: 19.41 | H58: 19.44 | I58: 623 | J58: 2.902 | K58: 8.635 | L58: 8.95 | M58: 42482 | N58: 1019575 | O58: #N/A N/A | P58: 46.5 | Q58: 68.4 | R58: #N/A N/A | S58: #N/A N/A | T58: 20.64 | U58: 25.53 | V58: #N/A N/A | W58: 20.64
A59: =WORKDAY(A58,1,0) -> 43907 | B59: 14.036 | C59: 13.921 | D59: 8.47 | E59: 36.88 | F59: 36.67 | G59: 18.25 | H59: 18.28 | I59: 612 | J59: 2.843 | K59: #N/A N/A | L59: #N/A N/A | M59: 42596 | N59: 1022297 | O59: #N/A N/A | P59: 47.1 | Q59: 68.35 | R59: #N/A N/A | S59: #N/A N/A | T59: #N/A N/A | U59: 23.3 | V59: #N/A N/A | W59: #N/A N/A
A60: =WORKDAY(A59,1,0) -> 43908 | B60: 13.509 | C60: 13.394 | D60: 8.265 | E60: 36.86 | F60: 36.65 | G60: 15.24 | H60: 15.24 | I60: 629 | J60: 2.802 | K60: 8.2 | L60: #N/A N/A | M60: 41153 | N60: 987660 | O60: #N/A N/A | P60: 47.8 | Q60: 67.85 | R60: #N/A N/A | S60: #N/A N/A | T60: #N/A N/A | U60: 21.15 | V60: #N/A N/A | W60: #N/A N/A
A61: =WORKDAY(A60,1,0) -> 43909 | B61: 13.46 | C61: 13.345 | D61: 8.544 | E61: 36.96 | F61: 36.75 | G61: 16.31 | H61: 16.32 | I61: 630 | J61: 2.822 | K61: 8.54 | L61: 8.4 | M61: 40856 | N61: 980538 | O61: #N/A N/A | P61: 46.9 | Q61: 66.5 | R61: #N/A N/A | S61: #N/A N/A | T61: 16.03 | U61: 21.35 | V61: #N/A N/A | W61: 16.03
A62: =WORKDAY(A61,1,0) -> 43910 | B62: 13.671 | C62: 13.556 | D62: 8.293 | E62: 37.27 | F62: 37.06 | G62: 16.04 | H62: 16.04 | I62: 625 | J62: 2.796 | K62: 8.2 | L62: #N/A N/A | M62: 40236 | N62: 965671 | O62: #N/A N/A | P62: 47.5 | Q62: 66.95 | R62: #N/A N/A | S62: #N/A N/A | T62: 16.35 | U62: 20 | V62: #N/A N/A | W62: 16.35
A63: =WORKDAY(A62,1,0) -> 43913 | B63: 13.605 | C63: 13.49 | D63: 7.849 | E63: 37.35 | F63: 37.14 | G63: 15.45 | H63: 15.47 | I63: 617 | J63: 2.763 | K63: #N/A N/A | L63: 7.99 | M63: 38446 | N63: 922709 | O63: #N/A N/A | P63: 47.4 | Q63: 67 | R63: #N/A N/A | S63: #N/A N/A | T63: 14.6 | U63: 18.55 | V63: #N/A N/A | W63: 14.6
A64: =WORKDAY(A63,1,0) -> 43914 | B64: 14.268 | C64: 14.153 | D64: 7.908 | E64: 37.81 | F64: 37.6 | G64: 16.7 | H64: 16.71 | I64: 603 | J64: 2.769 | K64: #N/A N/A | L64: #N/A N/A | M64: 40633 | N64: 975188 | O64: #N/A N/A | P64: 47.65 | Q64: 67.95 | R64: #N/A N/A | S64: #N/A N/A | T64: 16.25 | U64: 18.75 | V64: #N/A N/A | W64: 16.25
A65: =WORKDAY(A64,1,0) -> 43915 | B65: 14.424 | C65: 14.309 | D65: 7.744 | E65: 38.45 | F65: 38.24 | G65: 17.41 | H65: 17.44 | I65: 582 | J65: 2.761 | K65: #N/A N/A | L65: 7.8 | M65: 41105 | N65: 986530 | O65: #N/A N/A | P65: 48.25 | Q65: 68.75 | R65: #N/A N/A | S65: #N/A N/A | T65: 16.95 | U65: 18.45 | V65: #N/A N/A | W65: 16.95
A66: =WORKDAY(A65,1,0) -> 43916 | B66: 14.551 | C66: 14.436 | D66: 7.575 | E66: 38.06 | F66: 37.85 | G66: 17.22 | H66: 17.26 | I66: 569 | J66: 2.759 | K66: #N/A N/A | L66: #N/A N/A | M66: 40211 | N66: 965057 | O66: #N/A N/A | P66: 47.95 | Q66: 68.55 | R66: #N/A N/A | S66: #N/A N/A | T66: 16.3 | U66: 17.4 | V66: #N/A N/A | W66: 16.3
A67: =WORKDAY(A66,1,0) -> 43917 | B67: 14.401 | C67: 14.286 | D67: 7.218 | E67: 37.22 | F67: 37.01 | G67: 16.26 | H67: 16.3 | I67: 556 | J67: 2.75 | K67: 7.25 | L67: 7.55 | M67: 39610 | N67: 950649 | O67: #N/A N/A | P67: 48.1 | Q67: 67.85 | R67: #N/A N/A | S67: #N/A N/A | T67: 16.55 | U67: 17 | V67: #N/A N/A | W67: 16.55
A68: =WORKDAY(A67,1,0) -> 43920 | B68: 14.393 | C68: 14.278 | D68: 6.897 | E68: 36.89 | F68: 36.68 | G68: 16.93 | H68: 16.97 | I68: 548 | J68: 2.745 | K68: #N/A N/A | L68: #N/A N/A | M68: 39137 | N68: 939283 | O68: #N/A N/A | P68: 50.75 | Q68: 66.65 | R68: #N/A N/A | S68: #N/A N/A | T68: 16.32 | U68: 17.35 | V68: #N/A N/A | W68: 16.32
A69: =WORKDAY(A68,1,0) -> 43921 | B69: 14.633 | C69: 14.518 | D69: 6.902 | E69: 37 | F69: 36.79 | G69: 17.59 | H69: 17.64 | I69: 626 | J69: 2.219 | K69: 6.9 | L69: #N/A N/A | M69: 39642 | N69: 951413 | O69: #N/A N/A | P69: 49.3 | Q69: 66.7 | R69: #N/A N/A | S69: #N/A N/A | T69: 17.4 | U69: 17.1 | V69: #N/A N/A | W69: 17.4
A70: =WORKDAY(A69,1,0) -> 43922 | B70: 14.503 | C70: 14.388 | D70: 6.824 | E70: 37.46 | F70: 37.25 | G70: 17 | H70: 17.04 | I70: 624 | J70: 2.186 | K70: #N/A N/A | L70: #N/A N/A | M70: 41225 | N70: 989405 | O70: #N/A N/A | P70: 48.1 | Q70: 66.6 | R70: #N/A N/A | S70: #N/A N/A | T70: #N/A N/A | U70: 19.1 | V70: #N/A N/A | W70: #N/A N/A
A71: =WORKDAY(A70,1,0) -> 43923 | B71: 14.605 | C71: 14.49 | D71: 6.935 | E71: 37.55 | F71: 37.34 | G71: 17.99 | H71: 18.02 | I71: 624 | J71: 2.207 | K71: #N/A N/A | L71: 7.15 | M71: 42723 | N71: 1025350 | O71: #N/A N/A | P71: 47.45 | Q71: 66.6 | R71: #N/A N/A | S71: #N/A N/A | T71: 17.52 | U71: 19.25 | V71: #N/A N/A | W71: 17.52
A72: =WORKDAY(A71,1,0) -> 43924 | B72: 14.653 | C72: 14.538 | D72: 6.922 | E72: 37.27 | F72: 37.06 | G72: 17.89 | H72: 17.93 | I72: 616 | J72: 2.193 | K72: 6.87 | L72: #N/A N/A | M72: 42086 | N72: 1010075 | O72: #N/A N/A | P72: 46.1 | Q72: 66.65 | R72: #N/A N/A | S72: #N/A N/A | T72: 17.9 | U72: 19.25 | V72: #N/A N/A | W72: 17.9
A73: =WORKDAY(A72,1,0) -> 43927 | B73: 14.803 | C73: 14.688 | D73: 7.287 | E73: 38.02 | F73: 37.81 | G73: 20.33 | H73: 20.37 | I73: 604 | J73: 2.282 | K73: 7.25 | L73: #N/A N/A | M73: 38239 | N73: 917739 | O73: #N/A N/A | P73: 46.3 | Q73: 67.65 | R73: #N/A N/A | S73: #N/A N/A | T73: 18.36 | U73: 21.25 | V73: #N/A N/A | W73: 18.36
A74: =WORKDAY(A73,1,0) -> 43928 | B74: 15.078 | C74: 14.963 | D74: 7.283 | E74: 38.62 | F74: 38.41 | G74: 20.44 | H74: 20.48 | I74: 596 | J74: 2.297 | K74: #N/A N/A | L74: #N/A N/A | M74: 42960 | N74: 1031049 | O74: #N/A N/A | P74: 47.05 | Q74: 68.8 | R74: #N/A N/A | S74: #N/A N/A | T74: 21.11 | U74: 22.4 | V74: #N/A N/A | W74: 21.11
A75: =WORKDAY(A74,1,0) -> 43929 | B75: 15.109 | C75: 14.994 | D75: 7.259 | E75: 38.44 | F75: 38.23 | G75: 21.06 | H75: 21.1 | I75: 607 | J75: 2.289 | K75: #N/A N/A | L75: #N/A N/A | M75: 42775 | N75: 1026602 | O75: #N/A N/A | P75: 46.6 | Q75: 68.5 | R75: #N/A N/A | S75: #N/A N/A | T75: 20.07 | U75: 22.35 | V75: #N/A N/A | W75: 20.07
A76: =WORKDAY(A75,1,0) -> 43930 | B76: 15.288 | C76: 15.173 | D76: 7.279 | E76: 38.42 | F76: 38.21 | G76: 21.01 | H76: 21.04 | I76: 635 | J76: 2.304 | K76: 7.25 | L76: #N/A N/A | M76: 40506 | N76: 972146 | O76: #N/A N/A | P76: 46.8 | Q76: 68.5 | R76: #N/A N/A | S76: #N/A N/A | T76: 21.4 | U76: 23.1 | V76: #N/A N/A | W76: 21.4
A77: =WORKDAY(A76,1,0) -> 43931 | B77: #N/A N/A | C77: #N/A N/A | D77: #N/A N/A | E77: #N/A N/A | F77: #N/A N/A | G77: #N/A N/A | H77: #N/A N/A | I77: #N/A N/A | J77: #N/A N/A | K77: #N/A N/A | L77: #N/A N/A | M77: 39069 | N77: 937655 | O77: #N/A N/A | P77: #N/A N/A | Q77: #N/A N/A | R77: #N/A N/A | S77: #N/A N/A | T77: #N/A N/A | U77: #N/A N/A | V77: #N/A N/A | W77: #N/A N/A
A78: =WORKDAY(A77,1,0) -> 43934 | B78: 15.288 | C78: 15.173 | D78: 7.279 | E78: #N/A N/A | F78: #N/A N/A | G78: #N/A N/A | H78: #N/A N/A | I78: #N/A N/A | J78: #N/A N/A | K78: #N/A N/A | L78: #N/A N/A | M78: 27290 | N78: 654968 | O78: #N/A N/A | P78: 46.7 | Q78: 68.5 | R78: #N/A N/A | S78: #N/A N/A | T78: #N/A N/A | U78: #N/A N/A | V78: #N/A N/A | W78: #N/A N/A
A79: =WORKDAY(A78,1,0) -> 43935 | B79: 15.141 | C79: 15.026 | D79: 6.874 | E79: 37.59 | F79: 37.38 | G79: 19.76 | H79: 19.78 | I79: 679 | J79: 2.23 | K79: 6.84 | L79: #N/A N/A | M79: 37319 | N79: 895667 | O79: #N/A N/A | P79: 45.75 | Q79: 67.05 | R79: #N/A N/A | S79: #N/A N/A | T79: 20.17 | U79: 21.3 | V79: #N/A N/A | W79: 20.17
A80: =WORKDAY(A79,1,0) -> 43936 | B80: 14.687 | C80: 14.572 | D80: 6.649 | E80: 37.36 | F80: 37.15 | G80: 19.2 | H80: 19.22 | I80: 706 | J80: 2.183 | K80: 6.775 | L80: #N/A N/A | M80: 40218 | N80: 965238 | O80: #N/A N/A | P80: 45.3 | Q80: 67.1 | R80: #N/A N/A | S80: #N/A N/A | T80: #N/A N/A | U80: 20.55 | V80: #N/A N/A | W80: #N/A N/A
A81: =WORKDAY(A80,1,0) -> 43937 | B81: 14.795 | C81: 14.68 | D81: 6.907 | E81: 37.6 | F81: 37.39 | G81: 20.89 | H81: 20.91 | I81: 726 | J81: 2.218 | K81: #N/A N/A | L81: #N/A N/A | M81: 39579 | N81: 949887 | O81: #N/A N/A | P81: 45.5 | Q81: 67.4 | R81: #N/A N/A | S81: #N/A N/A | T81: 20.1 | U81: 21.8 | V81: #N/A N/A | W81: 20.1
A82: =WORKDAY(A81,1,0) -> 43938 | B82: 15.085 | C82: 14.971 | D82: 6.994 | E82: 37.84 | F82: 37.63 | G82: 21.64 | H82: 21.67 | I82: 751 | J82: 2.235 | K82: 6.93 | L82: #N/A N/A | M82: 39601 | N82: 950431 | O82: #N/A N/A | P82: 45.4 | Q82: 68.05 | R82: #N/A N/A | S82: #N/A N/A | T82: 21.87 | U82: 23 | V82: #N/A N/A | W82: 21.87
A83: =WORKDAY(A82,1,0) -> 43941 | B83: 14.973 | C83: 14.858 | D83: 6.618 | E83: 37.81 | F83: 37.6 | G83: 21.32 | H83: 21.35 | I83: 757 | J83: 2.186 | K83: #N/A N/A | L83: #N/A N/A | M83: 32598 | N83: 782341 | O83: #N/A N/A | P83: 45.55 | Q83: 67.75 | R83: #N/A N/A | S83: #N/A N/A | T83: 21.24 | U83: 22.9 | V83: #N/A N/A | W83: 21.24
A84: =WORKDAY(A83,1,0) -> 43942 | B84: 14.485 | C84: 14.37 | D84: 6.315 | E84: 37.03 | F84: 36.82 | G84: 19.79 | H84: 19.82 | I84: 728 | J84: 2.151 | K84: #N/A N/A | L84: 6.2 | M84: 33790 | N84: 810968 | O84: #N/A N/A | P84: 45.45 | Q84: 67.4 | R84: #N/A N/A | S84: #N/A N/A | T84: 20.4 | U84: 21.35 | V84: #N/A N/A | W84: 20.4
A85: =WORKDAY(A84,1,0) -> 43943 | B85: 14.255 | C85: 14.14 | D85: 6.226 | E85: 36.79 | F85: 36.58 | G85: 20.59 | H85: 20.63 | I85: 694 | J85: 2.141 | K85: 6.16 | L85: 6.17 | M85: 35941 | N85: 862592 | O85: 42.5 | P85: 45.15 | Q85: 67.15 | R85: #N/A N/A | S85: #N/A N/A | T85: 19.75 | U85: 21 | V85: #N/A N/A | W85: 19.75
A86: =WORKDAY(A85,1,0) -> 43944 | B86: 14.398 | C86: 14.283 | D86: 6.057 | E86: 36.86 | F86: 36.65 | G86: 20.97 | H86: 21.01 | I86: 672 | J86: 2.127 | K86: 6 | L86: 6.05 | M86: 38945 | N86: 934678 | O86: 42 | P86: 44.9 | Q86: 67.35 | R86: #N/A N/A | S86: #N/A N/A | T86: 20.24 | U86: 22 | V86: #N/A N/A | W86: 20.24
A87: =WORKDAY(A86,1,0) -> 43945 | B87: 14.52 | C87: 14.405 | D87: 5.77 | E87: 36.76 | F87: 36.55 | G87: 20.68 | H87: 20.72 | I87: 665 | J87: 2.108 | K87: #N/A N/A | L87: #N/A N/A | M87: 37467 | N87: 899220 | O87: #N/A N/A | P87: 45.05 | Q87: 67.1 | R87: #N/A N/A | S87: #N/A N/A | T87: 20.49 | U87: 21 | V87: #N/A N/A | W87: 20.49
A88: =WORKDAY(A87,1,0) -> 43948 | B88: 14.305 | C88: 14.19 | D88: 5.941 | E88: 36.35 | F88: 36.14 | G88: 20.22 | H88: 20.25 | I88: 661 | J88: 2.117 | K88: #N/A N/A | L88: #N/A N/A | M88: 35848 | N88: 860347 | O88: #N/A N/A | P88: 39.1 | Q88: 66.95 | R88: #N/A N/A | S88: #N/A N/A | T88: 20.4 | U88: 20.75 | V88: #N/A N/A | W88: 20.4
A89: =WORKDAY(A88,1,0) -> 43949 | B89: 14.395 | C89: 14.28 | D89: 6.147 | E89: 36.32 | F89: 36.11 | G89: 20.15 | H89: 20.18 | I89: 655 | J89: 2.124 | K89: 6.075 | L89: #N/A N/A | M89: 36288 | N89: 870923 | O89: #N/A N/A | P89: 38.45 | Q89: 66.75 | R89: #N/A N/A | S89: #N/A N/A | T89: 19.99 | U89: 19.75 | V89: #N/A N/A | W89: 19.99
A90: =WORKDAY(A89,1,0) -> 43950 | B90: 14.25 | C90: 14.135 | D90: 6.014 | E90: 35.71 | F90: 35.5 | G90: 20.13 | H90: 20.16 | I90: 643 | J90: 2.122 | K90: 5.915 | L90: 5.9 | M90: 35698 | N90: 856761 | O90: #N/A N/A | P90: 39 | Q90: 66.85 | R90: #N/A N/A | S90: #N/A N/A | T90: #N/A N/A | U90: 19.5 | V90: #N/A N/A | W90: #N/A N/A
A91: =WORKDAY(A90,1,0) -> 43951 | B91: 14.075 | C91: 13.96 | D91: 6.221 | E91: 35.35 | F91: 35.14 | G91: 19.51 | H91: 19.55 | I91: 635 | J91: 1.997 | K91: #N/A N/A | L91: 5.8 | M91: 34372 | N91: 824936 | O91: #N/A N/A | P91: 39.85 | Q91: 67.2 | R91: #N/A N/A | S91: #N/A N/A | T91: 19.97 | U91: 20.15 | V91: #N/A N/A | W91: 19.97
A92: =WORKDAY(A91,1,0) -> 43952 | B92: 13.79 | C92: 13.675 | D92: 5.843 | E92: 35.12 | F92: 34.91 | G92: 18.91 | H92: 18.95 | I92: 617 | J92: 1.89 | K92: #N/A N/A | L92: #N/A N/A | M92: 28994 | N92: 695847 | O92: #N/A N/A | P92: 39.5 | Q92: 65.95 | R92: #N/A N/A | S92: #N/A N/A | T92: #N/A N/A | U92: #N/A N/A | V92: #N/A N/A | W92: #N/A N/A
A93: =WORKDAY(A92,1,0) -> 43955 | B93: 13.761 | C93: 13.646 | D93: 5.74 | E93: 35.22 | F93: 35.01 | G93: 19.29 | H93: 19.33 | I93: 598 | J93: 1.846 | K93: 5.77 | L93: #N/A N/A | M93: 36433 | N93: 874396 | O93: #N/A N/A | P93: 39 | Q93: 65.9 | R93: #N/A N/A | S93: #N/A N/A | T93: #N/A N/A | U93: 23.85 | V93: #N/A N/A | W93: #N/A N/A
A94: =WORKDAY(A93,1,0) -> 43956 | B94: 14.031 | C94: 13.916 | D94: 5.674 | E94: 34.84 | F94: 34.63 | G94: 19.03 | H94: 19.07 | I94: 575 | J94: 1.817 | K94: #N/A N/A | L94: #N/A N/A | M94: 36083 | N94: 865986 | O94: #N/A N/A | P94: 39.6 | Q94: 66.65 | R94: #N/A N/A | S94: #N/A N/A | T94: 19.01 | U94: 24 | V94: #N/A N/A | W94: 19.01
A95: =WORKDAY(A94,1,0) -> 43957 | B95: 13.895 | C95: 13.78 | D95: 5.763 | E95: 35.19 | F95: 34.98 | G95: 18.94 | H95: 18.98 | I95: 534 | J95: 1.834 | K95: 5.8 | L95: 5.45 | M95: 35105 | N95: 842519 | O95: 43.3 | P95: 40 | Q95: 66.8 | R95: #N/A N/A | S95: #N/A N/A | T95: 18.85 | U95: 23.75 | V95: #N/A N/A | W95: 18.85
A96: =WORKDAY(A95,1,0) -> 43958 | B96: 14.025 | C96: 13.91 | D96: 5.847 | E96: 35.32 | F96: 35.11 | G96: 19.48 | H96: 19.52 | I96: 514 | J96: 1.852 | K96: #N/A N/A | L96: 5.5 | M96: 34130 | N96: 819112 | O96: 44.25 | P96: 40.2 | Q96: 67 | R96: #N/A N/A | S96: #N/A N/A | T96: 19 | U96: 24.1 | V96: #N/A N/A | W96: 19
A97: =WORKDAY(A96,1,0) -> 43959 | B97: 14.121 | C97: 14.006 | D97: 5.831 | E97: 35.32 | F97: 35.11 | G97: 19.29 | H97: 19.33 | I97: #N/A N/A | J97: 1.86 | K97: #N/A N/A | L97: 5.5 | M97: 35951 | N97: 862818 | O97: #N/A N/A | P97: 40 | Q97: 67 | R97: #N/A N/A | S97: #N/A N/A | T97: 19.38 | U97: 24 | V97: #N/A N/A | W97: 19.38
A98: =WORKDAY(A97,1,0) -> 43962 | B98: 14.223 | C98: 14.108 | D98: 5.707 | E98: 35.57 | F98: 35.36 | G98: 19 | H98: 19.04 | I98: 474 | J98: 1.828 | K98: #N/A N/A | L98: #N/A N/A | M98: 32348 | N98: 776362 | O98: #N/A N/A | P98: 39.9 | Q98: 67.2 | R98: #N/A N/A | S98: #N/A N/A | T98: 18.81 | U98: 24.1 | V98: #N/A N/A | W98: 18.81
A99: =WORKDAY(A98,1,0) -> 43963 | B99: 14.039 | C99: 13.924 | D99: 5.313 | E99: 35.56 | F99: 35.35 | G99: 18.46 | H99: 18.49 | I99: 433 | J99: 1.756 | K99: 5.29 | L99: 5.45 | M99: 35932 | N99: 862361 | O99: #N/A N/A | P99: 39.7 | Q99: 66.45 | R99: #N/A N/A | S99: #N/A N/A | T99: 18.72 | U99: 23.85 | V99: #N/A N/A | W99: 18.72
A100: =WORKDAY(A99,1,0) -> 43964 | B100: 13.963 | C100: 13.848 | D100: 5.119 | E100: 35.5 | F100: 35.29 | G100: 18.6 | H100: 18.64 | I100: 398 | J100: 1.717 | K100: 5.175 | L100: #N/A N/A | M100: 36000 | N100: 863996 | O100: #N/A N/A | P100: 39.35 | Q100: 66.4 | R100: #N/A N/A | S100: #N/A N/A | T100: #N/A N/A | U100: 23.65 | V100: #N/A N/A | W100: #N/A N/A
A101: =WORKDAY(A100,1,0) -> 43965 | B101: 14.05 | C101: 13.935 | D101: 5.265 | E101: 35.8 | F101: 35.59 | G101: 18.77 | H101: 18.81 | I101: 393 | J101: 1.74 | K101: #N/A N/A | L101: #N/A N/A | M101: 36201 | N101: 868827 | O101: #N/A N/A | P101: 39.1 | Q101: 66.65 | R101: #N/A N/A | S101: #N/A N/A | T101: 18.37 | U101: 24.05 | V101: #N/A N/A | W101: 18.37
...

Sheet Open_Int
A1: Paste Bloomberg historical price export here
A2: Recommended: export daily PX_LAST in wide format with dates in rows and tickers in columns. Paste starting at A4.
A4: Date | B4: TZTA Comdty | C4: TZTB Comdty | D4: TZT1 Comdty | E4: FNA Comdty | F4: FNB Comdty | G4: MO1 Comdty | H4: MO2 Comdty | I4: XA1 Comdty
A5: 43831 | B5: #N/A N/A | C5: #N/A N/A | D5: #N/A N/A | E5: #N/A N/A | F5: #N/A N/A | G5: #N/A N/A | H5: #N/A N/A | I5: #N/A N/A
A6: =A5+1 -> 43832 | B6: #N/A N/A | C6: #N/A N/A | D6: 80628 | E6: #N/A N/A | F6: #N/A N/A | G6: 141224 | H6: 8050 | I6: 3316
A7: =WORKDAY(A6,1,0) -> 43833 | B7: #N/A N/A | C7: #N/A N/A | D7: 80890 | E7: #N/A N/A | F7: #N/A N/A | G7: 141277 | H7: 8050 | I7: 3298
A8: =WORKDAY(A7,1,0) -> 43836 | B8: #N/A N/A | C8: #N/A N/A | D8: 80276 | E8: #N/A N/A | F8: #N/A N/A | G8: 141291 | H8: 8050 | I8: 3257
A9: =WORKDAY(A8,1,0) -> 43837 | B9: #N/A N/A | C9: #N/A N/A | D9: 81858 | E9: #N/A N/A | F9: #N/A N/A | G9: 141345 | H9: 8050 | I9: 3214
A10: =WORKDAY(A9,1,0) -> 43838 | B10: #N/A N/A | C10: #N/A N/A | D10: 81612 | E10: #N/A N/A | F10: #N/A N/A | G10: 142519 | H10: 8050 | I10: 3195
A11: =WORKDAY(A10,1,0) -> 43839 | B11: #N/A N/A | C11: #N/A N/A | D11: 82239 | E11: #N/A N/A | F11: #N/A N/A | G11: 141616 | H11: 8056 | I11: 3121
A12: =WORKDAY(A11,1,0) -> 43840 | B12: #N/A N/A | C12: #N/A N/A | D12: 79135 | E12: #N/A N/A | F12: #N/A N/A | G12: 141122 | H12: 8062 | I12: 3100
A13: =WORKDAY(A12,1,0) -> 43843 | B13: #N/A N/A | C13: #N/A N/A | D13: 78921 | E13: #N/A N/A | F13: #N/A N/A | G13: 141104 | H13: 8062 | I13: 3089
A14: =WORKDAY(A13,1,0) -> 43844 | B14: #N/A N/A | C14: #N/A N/A | D14: 75837 | E14: #N/A N/A | F14: #N/A N/A | G14: 140963 | H14: 8152 | I14: 3060
A15: =WORKDAY(A14,1,0) -> 43845 | B15: #N/A N/A | C15: #N/A N/A | D15: 75610 | E15: #N/A N/A | F15: #N/A N/A | G15: 140627 | H15: 8498 | I15: 3038
A16: =WORKDAY(A15,1,0) -> 43846 | B16: #N/A N/A | C16: #N/A N/A | D16: 74362 | E16: #N/A N/A | F16: #N/A N/A | G16: 140925 | H16: 8533 | I16: 2992
A17: =WORKDAY(A16,1,0) -> 43847 | B17: #N/A N/A | C17: #N/A N/A | D17: 72193 | E17: #N/A N/A | F17: #N/A N/A | G17: 140873 | H17: 8533 | I17: 2955
A18: =WORKDAY(A17,1,0) -> 43850 | B18: #N/A N/A | C18: #N/A N/A | D18: 70515 | E18: #N/A N/A | F18: #N/A N/A | G18: 140826 | H18: 8568 | I18: 2936
... A76: =WORKDAY(A75,1,0) -> 43930 | B76: #N/A N/A | C76: #N/A N/A | D76: 103589 | E76: #N/A N/A | F76: #N/A N/A | G76: 18932 | H76: 4522 | I76: 2429
A77: =WORKDAY(A76,1,0) -> 43931 | B77: #N/A N/A | C77: #N/A N/A | D77: #N/A N/A | E77: #N/A N/A | F77: #N/A N/A | G77: #N/A N/A | H77: #N/A N/A | I77: #N/A N/A
A78: =WORKDAY(A77,1,0) -> 43934 | B78: #N/A N/A | C78: #N/A N/A | D78: 103584 | E78: #N/A N/A | F78: #N/A N/A | G78: 18932 | H78: 4522 | I78: 2429
A79: =WORKDAY(A78,1,0) -> 43935 | B79: #N/A N/A | C79: #N/A N/A | D79: 101636 | E79: #N/A N/A | F79: #N/A N/A | G79: 19186 | H79: 4530 | I79: 2429
A80: =WORKDAY(A79,1,0) -> 43936 | B80: #N/A N/A | C80: #N/A N/A | D80: 100841 | E80: #N/A N/A | F80: #N/A N/A | G80: 20385 | H80: 4555 | I80: 2439
A81: =WORKDAY(A80,1,0) -> 43937 | B81: #N/A N/A | C81: #N/A N/A | D81: 107003 | E81: #N/A N/A | F81: #N/A N/A | G81: 21735 | H81: 4562 | I81: 2439
A82: =WORKDAY(A81,1,0) -> 43938 | B82: #N/A N/A | C82: #N/A N/A | D82: 100961 | E82: #N/A N/A | F82: #N/A N/A | G82: 22684 | H82: 4562 | I82: 2432
A83: =WORKDAY(A82,1,0) -> 43941 | B83: #N/A N/A | C83: #N/A N/A | D83: 95555 | E83: #N/A N/A | F83: #N/A N/A | G83: 23684 | H83: 4562 | I83: 2432
A84: =WORKDAY(A83,1,0) -> 43942 | B84: #N/A N/A | C84: #N/A N/A | D84: 90392 | E84: #N/A N/A | F84: #N/A N/A | G84: 24859 | H84: 4562 | I84: 2432
A85: =WORKDAY(A84,1,0) -> 43943 | B85: #N/A N/A | C85: #N/A N/A | D85: 83795 | E85: #N/A N/A | F85: #N/A N/A | G85: 26122 | H85: 4580 | I85: 2432
A86: =WORKDAY(A85,1,0) -> 43944 | B86: #N/A N/A | C86: #N/A N/A | D86: 84575 | E86: #N/A N/A | F86: #N/A N/A | G86: 26672 | H86: 4586 | I86: 2429
A87: =WORKDAY(A86,1,0) -> 43945 | B87: #N/A N/A | C87: #N/A N/A | D87: 72255 | E87: #N/A N/A | F87: #N/A N/A | G87: 26972 | H87: 4594 | I87: 2454
A88: =WORKDAY(A87,1,0) -> 43948 | B88: #N/A N/A | C88: #N/A N/A | D88: 65594 | E88: #N/A N/A | F88: #N/A N/A | G88: 27422 | H88: 4605 | I88: 2757
A89: =WORKDAY(A88,1,0) -> 43949 | B89: #N/A N/A | C89: #N/A N/A | D89: 59339 | E89: #N/A N/A | F89: #N/A N/A | G89: 28522 | H89: 4614 | I89: 2772
... A237: =WORKDAY(A236,1,0) -> 44155 | B237: #N/A N/A | C237: #N/A N/A | D237: 81113 | E237: #N/A N/A | F237: #N/A N/A | G237: 396767 | H237: 104567 | I237: 2635
A238: =WORKDAY(A237,1,0) -> 44158 | B238: 65 | C238: 65 | D238: 74216 | E238: #N/A N/A | F238: #N/A N/A | G238: 386296 | H238: 106836 | I238: 2638
A239: =WORKDAY(A238,1,0) -> 44159 | B239: 65 | C239: 65 | D239: 73177 | E239: #N/A N/A | F239: #N/A N/A | G239: 385124 | H239: 107236 | I239: 2638
A240: =WORKDAY(A239,1,0) -> 44160 | B240: 75 | C240: 75 | D240: 68887 | E240: #N/A N/A | F240: #N/A N/A | G240: 378349 | H240: 108291 | I240: 2638
A241: =WORKDAY(A240,1,0) -> 44161 | B241: 75 | C241: 75 | D241: 59786 | E241: #N/A N/A | F241: #N/A N/A | G241: 375287 | H241: 109231 | I241: 2638
A242: =WORKDAY(A241,1,0) -> 44162 | B242: 75 | C242: 75 | D242: 49912 | E242: #N/A N/A | F242: #N/A N/A | G242: 368601 | H242: 111267 | I242: 2638
A243: =WORKDAY(A242,1,0) -> 44165 | B243: 75 | C243: 75 | D243: 106656 | E243: #N/A N/A | F243: #N/A N/A | G243: 355405 | H243: 110387 | I243: 3350
A244: =WORKDAY(A243,1,0) -> 44166 | B244: 75 | C244: 75 | D244: 110604 | E244: #N/A N/A | F244: #N/A N/A | G244: 339995 | H244: 109338 | I244: 3368
A245: =WORKDAY(A244,1,0) -> 44167 | B245: 75 | C245: 75 | D245: 108309 | E245: #N/A N/A | F245: #N/A N/A | G245: 334056 | H245: 108551 | I245: 3367
A246: =WORKDAY(A245,1,0) -> 44168 | B246: 75 | C246: 75 | D246: 109159 | E246: #N/A N/A | F246: #N/A N/A | G246: 321326 | H246: 111472 | I246: 3404
A247: =WORKDAY(A246,1,0) -> 44169 | B247: 75 | C247: 75 | D247: 108665 | E247: #N/A N/A | F247: #N/A N/A | G247: 313531 | H247: 114546 | I247: 3416
A248: =WORKDAY(A247,1,0) -> 44172 | B248: 75 | C248: 75 | D248: 106503 | E248: #N/A N/A | F248: #N/A N/A | G248: 307987 | H248: 114933 | I248: 3416
A249: =WORKDAY(A248,1,0) -> 44173 | B249: 75 | C249: 75 | D249: 106321 | E249: #N/A N/A | F249: #N/A N/A | G249: 302006 | H249: 120438 | I249: 3440
... A261: =WORKDAY(A260,1,0) -> 44189 | B261: 75 | C261: 75 | D261: 69500 | E261: #N/A N/A | F261: #N/A N/A | G261: 141716 | H261: 3200 | I261: 3379
A262: =WORKDAY(A261,1,0) -> 44190 | B262: #N/A N/A | C262: #N/A N/A | D262: #N/A N/A | E262: #N/A N/A | F262: #N/A N/A | G262: #N/A N/A | H262: #N/A N/A | I262: #N/A N/A
A263: =WORKDAY(A262,1,0) -> 44193 | B263: 75 | C263: 75 | D263: 68478 | E263: #N/A N/A | F263: #N/A N/A | G263: 142287 | H263: 3200 | I263: 3901
A264: =WORKDAY(A263,1,0) -> 44194 | B264: 75 | C264: 75 | D264: 68025 | E264: #N/A N/A | F264: #N/A N/A | G264: 142360 | H264: 3200 | I264: 4039
A265: =WORKDAY(A264,1,0) -> 44195 | B265: 75 | C265: 75 | D265: 61807 | E265: #N/A N/A | F265: #N/A N/A | G265: 142266 | H265: 3200 | I265: 4183
A266: =WORKDAY(A265,1,0) -> 44196 | B266: 75 | C266: 75 | D266: 132311 | E266: #N/A N/A | F266: #N/A N/A | G266: 142253 | H266: 3200 | I266: 4183
A267: =WORKDAY(A266,1,0) -> 44197 | B267: #N/A N/A | C267: #N/A N/A | D267: #N/A N/A | E267: #N/A N/A | F267: #N/A N/A | G267: #N/A N/A | H267: #N/A N/A | I267: #N/A N/A
A268: =WORKDAY(A267,1,0) -> 44200 | B268: 75 | C268: 75 | D268: 132014 | E268: #N/A N/A | F268: #N/A N/A | G268: 142341 | H268: 3225 | I268: 4180
A269: =WORKDAY(A268,1,0) -> 44201 | B269: 75 | C269: 75 | D269: 129065 | E269: #N/A N/A | F269: #N/A N/A | G269: 142332 | H269: 3225 | I269: 4203
A270: =WORKDAY(A269,1,0) -> 44202 | B270: 75 | C270: 75 | D270: 127963 | E270: #N/A N/A | F270: #N/A N/A | G270: 142348 | H270: 3225 | I270: 4171
A271: =WORKDAY(A270,1,0) -> 44203 | B271: 75 | C271: 75 | D271: 130819 | E271: #N/A N/A | F271: #N/A N/A | G271: 142387 | H271: 3225 | I271: 4190
A272: =WORKDAY(A271,1,0) -> 44204 | B272: 75 | C272: 75 | D272: 136460 | E272: #N/A N/A | F272: #N/A N/A | G272: 142669 | H272: 3225 | I272: 4140
A273: =WORKDAY(A272,1,0) -> 44207 | B273: 75 | C273: 75 | D273: 131716 | E273: #N/A N/A | F273: #N/A N/A | G273: 142713 | H273: 3225 | I273: 4107
A274: =WORKDAY(A273,1,0) -> 44208 | B274: 75 | C274: 75 | D274: 128786 | E274: #N/A N/A | F274: #N/A N/A | G274: 142793 | H274: 3225 | I274: 3935
A275: =WORKDAY(A274,1,0) -> 44209 | B275: 75 | C275: 75 | D275: 123904 | E275: #N/A N/A | F275: #N/A N/A | G275: 143138 | H275: 3225 | I275: 3914
A276: =WORKDAY(A275,1,0) -> 44210 | B276: 75 | C276: 75 | D276: 120478 | E276: #N/A N/A | F276: #N/A N/A | G276: 143199 | H276: 3225 | I276: 3922
A277: =WORKDAY(A276,1,0) -> 44211 | B277: 75 | C277: 75 | D277: 119207 | E277: #N/A N/A | F277: #N/A N/A | G277: 143310 | H277: 3225 | I277: 3888
A278: =WORKDAY(A277,1,0) -> 44214 | B278: 75 | C278: 75 | D278: 115998 | E278: #N/A N/A | F278: #N/A N/A | G278: 143340 | H278: 3225 | I278: 3836
A279: =WORKDAY(A278,1,0) -> 44215 | B279: 75 | C279: 75 | D279: 112916 | E279: #N/A N/A | F279: #N/A N/A | G279: 143846 | H279: 3225 | I279: 3842
... A331: =WORKDAY(A330,1,0) -> 44287 | B331: 105 | C331: 105 | D331: 114321 | E331: #N/A N/A | F331: #N/A N/A | G331: 22392 | H331: 1585 | I331: 2834
A332: =WORKDAY(A331,1,0) -> 44288 | B332: #N/A N/A | C332: #N/A N/A | D332: #N/A N/A | E332: #N/A N/A | F332: #N/A N/A | G332: #N/A N/A | H332: #N/A N/A | I332: #N/A N/A
A333: =WORKDAY(A332,1,0) -> 44291 | B333: 105 | C333: 105 | D333: 114321 | E333: #N/A N/A | F333: #N/A N/A | G333: 22392 | H333: 1585 | I333: 2834
A334: =WORKDAY(A333,1,0) -> 44292 | B334: 105 | C334: 105 | D334: 115107 | E334: #N/A N/A | F334: #N/A N/A | G334: 22243 | H334: 1585 | I334: 2828
A335: =WORKDAY(A334,1,0) -> 44293 | B335: 105 | C335: 105 | D335: 113617 | E335: #N/A N/A | F335: #N/A N/A | G335: 22442 | H335: 1585 | I335: 2835
A336: =WORKDAY(A335,1,0) -> 44294 | B336: 105 | C336: 105 | D336: 112737 | E336: #N/A N/A | F336: #N/A N/A | G336: 23092 | H336: 1585 | I336: 2813
A337: =WORKDAY(A336,1,0) -> 44295 | B337: 105 | C337: 105 | D337: 109376 | E337: #N/A N/A | F337: #N/A N/A | G337: 23292 | H337: 1585 | I337: 2843
A338: =WORKDAY(A337,1,0) -> 44298 | B338: 105 | C338: 105 | D338: 112578 | E338: #N/A N/A | F338: #N/A N/A | G338: 23519 | H338: 1585 | I338: 2847
A339: =WORKDAY(A338,1,0) -> 44299 | B339: 115 | C339: 115 | D339: 109462 | E339: #N/A N/A | F339: #N/A N/A | G339: 24561 | H339: 1585 | I339: 2806
A340: =WORKDAY(A339,1,0) -> 44300 | B340: 115 | C340: 115 | D340: 107838 | E340: #N/A N/A | F340: #N/A N/A | G340: 24510 | H340: 1585 | I340: 2791
A341: =WORKDAY(A340,1,0) -> 44301 | B341: 125 | C341: 125 | D341: 107146 | E341: #N/A N/A | F341: #N/A N/A | G341: 24510 | H341: 1585 | I341: 2784
A342: =WORKDAY(A341,1,0) -> 44302 | B342: 125 | C342: 125 | D342: 101306 | E342: #N/A N/A | F342: #N/A N/A | G342: 24478 | H342: 1585 | I342: 2772
A343: =WORKDAY(A342,1,0) -> 44305 | B343: 125 | C343: 125 | D343: 95054 | E343: #N/A N/A | F343: #N/A N/A | G343: 24463 | H343: 1585 | I343: 2774
A344: =WORKDAY(A343,1,0) -> 44306 | B344: 125 | C344: 125 | D344: 93931 | E344: #N/A N/A | F344: #N/A N/A | G344: 24455 | H344: 1585 | I344: 2774
... A380: =WORKDAY(A379,1,0) -> 44356 | B380: 275 | C380: 275 | D380: 116065 | E380: #N/A N/A | F380: #N/A N/A | G380: 20392 | H380: 6918 | I380: 3069
A381: =WORKDAY(A380,1,0) -> 44357 | B381: 275 | C381: 275 | D381: 114459 | E381: 5 | F381: 5 | G381: 20391 | H381: 6918 | I381: 3060
A382: =WORKDAY(A381,1,0) -> 44358 | B382: 275 | C382: 275 | D382: 111115 | E382: 5 | F382: 5 | G382: 20323 | H382: 7022 | I382: 3055
A383: =WORKDAY(A382,1,0) -> 44361 | B383: 275 | C383: 275 | D383: 110813 | E383: 5 | F383: 5 | G383: 20320 | H383: 7022 | I383: 3055
A384: =WORKDAY(A383,1,0) -> 44362 | B384: 275 | C384: 275 | D384: 110851 | E384: 5 | F384: 5 | G384: 20322 | H384: 7022 | I384: 3050
A385: =WORKDAY(A384,1,0) -> 44363 | B385: 275 | C385: 275 | D385: 110323 | E385: 5 | F385: 5 | G385: 20367 | H385: 7022 | I385: 2994
A386: =WORKDAY(A385,1,0) -> 44364 | B386: 275 | C386: 275 | D386: 108532 | E386: 5 | F386: 5 | G386: 20054 | H386: 7022 | I386: 2994
A387: =WORKDAY(A386,1,0) -> 44365 | B387: 275 | C387: 275 | D387: 109369 | E387: 5 | F387: 5 | G387: 20054 | H387: 7022 | I387: 2994
A388: =WORKDAY(A387,1,0) -> 44368 | B388: 275 | C388: 275 | D388: 110004 | E388: 5 | F388: 5 | G388: 20045 | H388: 9022 | I388: 2994
A389: =WORKDAY(A388,1,0) -> 44369 | B389: 275 | C389: 275 | D389: 107254 | E389: 10 | F389: 10 | G389: 19580 | H389: 9022 | I389: 2994
A390: =WORKDAY(A389,1,0) -> 44370 | B390: 275 | C390: 275 | D390: 96161 | E390: 10 | F390: 10 | G390: 19600 | H390: 9022 | I390: 2994
A391: =WORKDAY(A390,1,0) -> 44371 | B391: 275 | C391: 275 | D391: 98561 | E391: 10 | F391: 10 | G391: 18660 | H391: 9022 | I391: 2984
A392: =WORKDAY(A391,1,0) -> 44372 | B392: 275 | C392: 275 | D392: 77479 | E392: 10 | F392: 10 | G392: 18669 | H392: 9022 | I392: 2964
... A518: =WORKDAY(A517,1,0) -> 44550 | B518: 1300 | C518: 1300 | D518: 130403 | E518: 35 | F518: 35 | G518: 221592 | H518: 125710 | I518: 3749
A519: =WORKDAY(A518,1,0) -> 44551 | B519: 1315 | C519: 1315 | D519: 123183 | E519: 35 | F519: 35 | G519: 127554 | H519: #N/A N/A | I519: 3744
A520: =WORKDAY(A519,1,0) -> 44552 | B520: 1315 | C520: 1315 | D520: 120646 | E520: 35 | F520: 35 | G520: 129936 | H520: #N/A N/A | I520: 3742
A521: =WORKDAY(A520,1,0) -> 44553 | B521: 1350 | C521: 1350 | D521: 113327 | E521: 35 | F521: 35 | G521: 131861 | H521: #N/A N/A | I521: 3742
A522: =WORKDAY(A521,1,0) -> 44554 | B522: 1350 | C522: 1350 | D522: 103797 | E522: 35 | F522: 35 | G522: 132382 | H522: #N/A N/A | I522: 3742
A523: =WORKDAY(A522,1,0) -> 44557 | B523: 1350 | C523: 1350 | D523: 96967 | E523: 35 | F523: 35 | G523: 132332 | H523: #N/A N/A | I523: 3742
A524: =WORKDAY(A523,1,0) -> 44558 | B524: 1350 | C524: 1350 | D524: 96509 | E524: 35 | F524: 35 | G524: 132112 | H524: #N/A N/A | I524: 3742
A525: =WORKDAY(A524,1,0) -> 44559 | B525: 1350 | C525: 1350 | D525: 84133 | E525: 35 | F525: 35 | G525: 132045 | H525: #N/A N/A | I525: 3738
A526: =WORKDAY(A525,1,0) -> 44560 | B526: 1365 | C526: 1365 | D526: 75916 | E526: 35 | F526: 35 | G526: 131941 | H526: #N/A N/A | I526: 3738
A527: =WORKDAY(A526,1,0) -> 44561 | B527: 1365 | C527: 1365 | D527: 138366 | E527: 35 | F527: 35 | G527: 132084 | H527: #N/A N/A | I527: 3738
...

Sheet COT
A1: Instrument | C1: EUA
A2: Group | C2: M01 Comdty
A3: Start Date | C3: 43833
A4: End Date | C4: =TODAY() -> 46132
B5: IU34DXTZ Index | C5: IU34NIMQ Index | D5: IU34SOVM Index | E5: IU34TKAC Index | F5: IU34LTIS Index | G5: IU34JCIV Index | H5: IU34XWQO Index | I5: IU34JIHS Index | J5: IU34PACT Index | K5: IU34BDCL Index | L5: IU34YJER Index | M5: IU34PLIQ Index | N5: IU34SCVE Index | O5: IU34FCWY Index | P5: IU34OHYS Index | Q5: IU34FFWD Index | R5: IU34ELRX Index | S5: IU34YDTT Index | T5: IU34LUZX Index | U5: IU34MHZA Index | V5: IU34APAC Index | W5: IU34TTSU Index | X5: IU34YSRP Index | Y5: IU34LWBJ Index | Z5: IU34WVTK Index | AA5: IU34GKLQ Index | AB5: IU34QXFY Index | AC5: IU34DHGJ Index | AD5: IU34AVAK Index | AE5: IU34VSQW Index | AF5: IU34HKGO Index | AG5: IU34ALBA Index | AH5: IU34TITP Index | AI5: IU34SVVX Index | AJ5: IU34AEGX Index | AK5: IU34NFPU Index | AL5: IU34TIFI Index | AM5: IU34WQJC Index | AN5: IU34QUMY Index | AO5: IU34FYND Index | AP5: IU34SQPV Index | AQ5: IU34XSKZ Index | AR5: IU34EIVC Index | AS5: IU34LCXM Index | AT5: IU34LGHP Index | AU5: IU34EXRU Index | AV5: IU34TVHP Index | AW5: IU34XYDT Index | AX5: IU34FSWP Index | AY5: IU34VDQG Index | AZ5: IU34BTTU Index | BA5: IU34YKQK Index | BB5: IU34NLSL Index | BC5: IU34QDRX Index | BD5: IU34ZTIH Index | BE5: IU34FHAX Index | BF5: IU34BNCI Index | BG5: IU34AAJH Index | BH5: IU34LPLG Index | BI5: IU34WADG Index | BJ5: IU34QCTN Index | BK5: IU34WZPM Index | BL5: IU34HNWB Index | BM5: IU34URJU Index | BN5: IU34MXKT Index | BO5: IU34ZLIW Index | BP5: IU34SNEP Index | BQ5: IU34XAMA Index | BR5: IU34QAUR Index | BS5: IU34CMNN Index | BT5: IU34RKXO Index | BU5: IU34YOQM Index | BV5: IU34OOXC Index | BW5: IU34BWFD Index | BX5: IU34MHIR Index
A6: =C3 -> 43833 | B6: 29 | C6: 0 | D6: 73489.15 | E6: 8.96 | F6: 73518.15 | G6: 8.96 | H6: 946 | I6: 0.12 | J6: 654453.26 | K6: 81.33 | L6: 655399.26 | M6: 81.45 | N6: -917 | O6: -580964.13 | P6: -581881.13 | Q6: 68 | R6: 0.01 | S6: 56900.77 | T6: 6.94 | U6: 56968.77 | V6: 6.95 | W6: 0 | X6: 0 | Y6: 17715.01 | Z6: 2.2 | AA6: 17715.01 | AB6: 2.2 | AC6: 68 | AD6: 39185.76 | AE6: 39253.76 | AF6: 0 | AG6: 0 | AH6: 55 | AI6: 0.01 | AJ6: 55 | AK6: 0.01 | AL6: 0 | AM6: 0 | AN6: 0 | AO6: 0 | AP6: 0 | AQ6: 0 | AR6: 0 | AS6: 55 | AT6: 55 | AU6: 358996.87 | AV6: 43.76 | AW6: 173613.98 | AX6: 21.16 | AY6: 532610.85 | AZ6: 64.92 | BA6: 18067.45 | BB6: 2.25 | BC6: 108987.79 | BD6: 13.54 | BE6: 127055.24 | BF6: 15.79 | BG6: 340929.44 | BH6: 64626.2 | BI6: 405555.63 | BJ6: 107072 | BK6: 13.05 | BL6: 50157.86 | BM6: 6.11 | BN6: 157229.86 | BO6: 19.16 | BP6: 126 | BQ6: 0.02 | BR6: 4382.87 | BS6: 0.54 | BT6: 4508.87 | BU6: 0.56 | BV6: 106946 | BW6: 45774.99 | BX6: 152720.98
A7: =IF(A6="",,IF(A6+7<=$C$4,A6+7,"")) -> 43840 | B7: 53 | C7: 0 | D7: 78896.84 | E7: 9.48 | F7: 78949.84 | G7: 9.48 | H7: 955 | I7: 0.11 | J7: 657835.54 | K7: 80.59 | L7: 658790.54 | M7: 80.7 | N7: -902 | O7: -578938.75 | P7: -579840.75 | Q7: 67 | R7: 0.01 | S7: 56240.33 | T7: 6.76 | U7: 56307.33 | V7: 6.77 | W7: 0 | X7: 0 | Y7: 19146.15 | Z7: 2.35 | AA7: 19146.15 | AB7: 2.35 | AC7: 67 | AD7: 37094.18 | AE7: 37161.18 | AF7: 0 | AG7: 0 | AH7: 48 | AI7: 0.01 | AJ7: 48 | AK7: 0.01 | AL7: 0 | AM7: 0 | AN7: 217 | AO7: 0.03 | AP7: 217 | AQ7: 0.03 | AR7: 0 | AS7: -169 | AT7: -169 | AU7: 361751.02 | AV7: 43.47 | AW7: 178173.24 | AX7: 21.41 | AY7: 539924.26 | AZ7: 64.88 | BA7: 20073.64 | BB7: 2.46 | BC7: 112966.75 | BD7: 13.84 | BE7: 133040.39 | BF7: 16.3 | BG7: 341677.38 | BH7: 65206.48 | BI7: 406883.88 | BJ7: 107011.91 | BK7: 12.86 | BL7: 49887.65 | BM7: 6 | BN7: 156899.56 | BO7: 18.86 | BP7: 608 | BQ7: 0.07 | BR7: 4515.57 | BS7: 0.55 | BT7: 5123.57 | BU7: 0.62 | BV7: 106403.91 | BW7: 45372.08 | BX7: 151776
A8: =IF(A7="",,IF(A7+7<=$C$4,A7+7,"")) -> 43847 | B8: 77 | C8: 0 | D8: 81134.91 | E8: 9.82 | F8: 81211.91 | G8: 9.82 | H8: 981 | I8: 0.11 | J8: 651577 | K8: 80.77 | L8: 652558 | M8: 80.88 | N8: -904 | O8: -570442.13 | P8: -571346.13 | Q8: 66 | R8: 0.01 | S8: 57140.56 | T8: 6.92 | U8: 57206.56 | V8: 6.93 | W8: 2 | X8: 0 | Y8: 18214.09 | Z8: 2.26 | AA8: 18216.09 | AB8: 2.26 | AC8: 64 | AD8: 38926.47 | AE8: 38990.47 | AF8: 0 | AG8: 0 | AH8: 43 | AI8: 0.01 | AJ8: 43 | AK8: 0.01 | AL8: 0 | AM8: 0 | AN8: 217 | AO8: 0.03 | AP8: 217 | AQ8: 0.03 | AR8: 0 | AS8: -174 | AT8: -174 | AU8: 345195.71 | AV8: 41.8 | AW8: 179356.81 | AX8: 21.72 | AY8: 524552.52 | AZ8: 63.52 | BA8: 19565.95 | BB8: 2.43 | BC8: 110804.35 | BD8: 13.74 | BE8: 130370.3 | BF8: 16.17 | BG8: 325629.78 | BH8: 68552.46 | BI8: 394182.19 | BJ8: 110733.28 | BK8: 13.41 | BL8: 52095.13 | BM8: 6.31 | BN8: 162828.41 | BO8: 19.72 | BP8: 776 | BQ8: 0.1 | BR8: 4551.33 | BS8: 0.56 | BT8: 5327.33 | BU8: 0.66 | BV8: 109957.28 | BW8: 47543.8 | BX8: 157501.08
A9: =IF(A8="",,IF(A8+7<=$C$4,A8+7,"")) -> 43854 | B9: 117 | C9: 0.01 | D9: 82769.78 | E9: 9.9 | F9: 82886.78 | G9: 9.91 | H9: 997 | I9: 0.12 | J9: 658065.2 | K9: 80.4 | L9: 659062.2 | M9: 80.52 | N9: -880 | O9: -575295.38 | P9: -576175.38 | Q9: 66 | R9: 0.01 | S9: 58118.38 | T9: 6.95 | U9: 58184.38 | V9: 6.96 | W9: 0 | X9: 0 | Y9: 19138.99 | Z9: 2.34 | AA9: 19138.99 | AB9: 2.34 | AC9: 66 | AD9: 38979.39 | AE9: 39045.39 | AF9: 0 | AG9: 0 | AH9: 43 | AI9: 0.01 | AJ9: 43 | AK9: 0.01 | AL9: 0 | AM9: 0 | AN9: 217 | AO9: 0.03 | AP9: 217 | AQ9: 0.03 | AR9: 0 | AS9: -174 | AT9: -174 | AU9: 346748.09 | AV9: 41.47 | AW9: 187851.09 | AX9: 22.47 | AY9: 534599.18 | AZ9: 63.94 | BA9: 20602.12 | BB9: 2.52 | BC9: 114005.95 | BD9: 13.93 | BE9: 134608.07 | BF9: 16.45 | BG9: 326145.97 | BH9: 73845.14 | BI9: 399991.13 | BJ9: 107251.89 | BK9: 12.83 | BL9: 53111.37 | BM9: 6.35 | BN9: 160363.26 | BO9: 19.18 | BP9: 927 | BQ9: 0.11 | BR9: 4524.06 | BS9: 0.55 | BT9: 5451.06 | BU9: 0.66 | BV9: 106324.89 | BW9: 48587.31 | BX9: 154912.2
A10: =IF(A9="",,IF(A9+7<=$C$4,A9+7,"")) -> 43861 | B10: 0 | C10: 0 | D10: 68884.11 | E10: 8.37 | F10: 68884.11 | G10: 8.37 | H10: 284 | I10: 0.03 | J10: 391255.95 | K10: 48.02 | L10: 391539.95 | M10: 48.05 | N10: -284 | O10: -322371.81 | P10: -322655.81 | Q10: 66 | R10: 0.01 | S10: 38525.98 | T10: 4.69 | U10: 38591.98 | V10: 4.7 | W10: 6 | X10: 0 | Y10: 14133 | Z10: 1.73 | AA10: 14139 | AB10: 1.73 | AC10: 60 | AD10: 24392.98 | AE10: 24452.98 | AF10: 1553.97 | AG10: 0.19 | AH10: 16180 | AI10: 1.97 | AJ10: 17733.97 | AK10: 2.16 | AL10: 0 | AM10: 0 | AN10: 4969.93 | AO10: 0.61 | AP10: 4969.93 | AQ10: 0.61 | AR10: 1553.97 | AS10: 11210.07 | AT10: 12764.04 | AU10: 432869.13 | AV10: 52.67 | AW10: 263070.57 | AX10: 32.01 | AY10: 695939.7 | AZ10: 84.68 | BA10: 6574.23 | BB10: 0.81 | BC10: 392181.96 | BD10: 48.14 | BE10: 398756.19 | BF10: 48.95 | BG10: 426294.91 | BH10: -129111.41 | BI10: 297183.5 | BJ10: 754 | BK10: 0.09 | BL10: 0 | BM10: 0 | BN10: 754 | BO10: 0.09 | BP10: 0 | BQ10: 0 | BR10: 5342 | BS10: 0.66 | BT10: 5342 | BU10: 0.66 | BV10: 754 | BW10: -5342 | BX10: -4588
A11: =IF(A10="",,IF(A10+7<=$C$4,A10+7,"")) -> 43868 | B11: 148 | C11: 0.01 | D11: 86939.01 | E11: 10.22 | F11: 87087.01 | G11: 10.23 | H11: 833 | I11: 0.11 | J11: 661954.85 | K11: 79.41 | L11: 662787.85 | M11: 79.52 | N11: -685 | O11: -575015.88 | P11: -575700.88 | Q11: 66 | R11: 0.01 | S11: 61068.14 | T11: 7.18 | U11: 61134.14 | V11: 7.19 | W11: 15 | X11: 0 | Y11: 23850.18 | Z11: 2.86 | AA11: 23865.18 | AB11: 2.86 | AC11: 51 | AD11: 37217.96 | AE11: 37268.96 | AF11: 0 | AG11: 0 | AH11: 26 | AI11: 0 | AJ11: 26 | AK11: 0 | AL11: 0 | AM11: 0 | AN11: 217 | AO11: 0.03 | AP11: 217 | AQ11: 0.03 | AR11: 0 | AS11: -191 | AT11: -191 | AU11: 347792.16 | AV11: 40.87 | AW11: 193019.81 | AX11: 22.68 | AY11: 540811.97 | AZ11: 63.55 | BA11: 19780.16 | BB11: 2.37 | BC11: 121476.45 | BD11: 14.57 | BE11: 141256.61 | BF11: 16.94 | BG11: 328012 | BH11: 71543.36 | BI11: 399555.38 | BJ11: 105624.82 | BK11: 12.41 | BL11: 56370.84 | BM11: 6.62 | BN11: 161995.66 | BO11: 19.03 | BP11: 1527 | BQ11: 0.18 | BR11: 3926.31 | BS11: 0.47 | BT11: 5453.31 | BU11: 0.65 | BV11: 104097.82 | BW11: 52444.53 | BX11: 156542.34
A12: =IF(A11="",,IF(A11+7<=$C$4,A11+7,"")) -> 43875 | B12: 192 | C12: 0.03 | D12: 86970.12 | E12: 10.17 | F12: 87162.12 | G12: 10.2 | H12: 861 | I12: 0.11 | J12: 664913.77 | K12: 79.54 | L12: 665774.77 | M12: 79.65 | N12: -669 | O12: -577943.63 | P12: -578612.63 | Q12: 42 | R12: 0 | S12: 61177.66 | T12: 7.16 | U12: 61219.66 | V12: 7.16 | W12: 13 | X12: 0 | Y12: 23487.68 | Z12: 2.81 | AA12: 23500.68 | AB12: 2.81 | AC12: 29 | AD12: 37689.98 | AE12: 37718.98 | AF12: 0 | AG12: 0 | AH12: 20 | AI12: 0 | AJ12: 20 | AK12: 0 | AL12: 0 | AM12: 0 | AN12: 217 | AO12: 0.03 | AP12: 217 | AQ12: 0.03 | AR12: 0 | AS12: -197 | AT12: -197 | AU12: 347872.72 | AV12: 40.7 | AW12: 195473.08 | AX12: 22.87 | AY12: 543345.8 | AZ12: 63.57 | BA12: 19587.04 | BB12: 2.34 | BC12: 121304.88 | BD12: 14.51 | BE12: 140891.92 | BF12: 16.85 | BG12: 328285.69 | BH12: 74168.2 | BI12: 402453.88 | BJ12: 105088.06 | BK12: 12.29 | BL12: 57947.88 | BM12: 6.78 | BN12: 163035.94 | BO12: 19.07 | BP12: 1626 | BQ12: 0.19 | BR12: 3921.43 | BS12: 0.47 | BT12: 5547.43 | BU12: 0.66 | BV12: 103462.06 | BW12: 54026.45 | BX12: 157488.5
A13: =IF(A12="",,IF(A12+7<=$C$4,A12+7,"")) -> 43882 | B13: 215 | C13: 0.02 | D13: 85176.49 | E13: 9.98 | F13: 85391.49 | G13: 10 | H13: 896 | I13: 0.1 | J13: 667624.52 | K13: 80.16 | L13: 668520.52 | M13: 80.26 | N13: -681 | O13: -582448 | P13: -583129 | Q13: 45 | R13: 0.01 | S13: 63273.13 | T13: 7.41 | U13: 63318.13 | V13: 7.42 | W13: 0 | X13: 0 | Y13: 17593.67 | Z13: 2.11 | AA13: 17593.67 | AB13: 2.11 | AC13: 45 | AD13: 45679.46 | AE13: 45724.46 | AF13: 0 | AG13: 0 | AH13: 26 | AI13: 0 | AJ13: 26 | AK13: 0 | AL13: 0 | AM13: 0 | AN13: 0 | AO13: 0 | AP13: 0 | AQ13: 0 | AR13: 0 | AS13: 26 | AT13: 26 | AU13: 348584.8 | AV13: 40.85 | AW13: 194433.54 | AX13: 22.79 | AY13: 543018.34 | AZ13: 63.64 | BA13: 20035.56 | BB13: 2.41 | BC13: 120815.86 | BD13: 14.51 | BE13: 140851.42 | BF13: 16.92 | BG13: 328549.25 | BH13: 73617.69 | BI13: 402166.88 | BJ13: 102470.8 | BK13: 12.01 | BL13: 59102.8 | BM13: 6.93 | BN13: 161573.6 | BO13: 18.94 | BP13: 2121 | BQ13: 0.25 | BR13: 3803.63 | BS13: 0.46 | BT13: 5924.63 | BU13: 0.71 | BV13: 100349.8 | BW13: 55299.17 | BX13: 155648.97
A14: =IF(A13="",,IF(A13+7<=$C$4,A13+7,"")) -> 43889 | B14: 237.91 | C14: 0.03 | D14: 86244.82 | E14: 10.09 | F14: 86482.73 | G14: 10.12 | H14: 841 | I14: 0.11 | J14: 671903.98 | K14: 80.48 | L14: 672744.98 | M14: 80.59 | N14: -603.09 | O14: -585659.19 | P14: -586262.25 | Q14: 19 | R14: 0 | S14: 59569.08 | T14: 6.97 | U14: 59588.08 | V14: 6.97 | W14: 4 | X14: 0 | Y14: 18424.96 | Z14: 2.21 | AA14: 18428.96 | AB14: 2.21 | AC14: 15 | AD14: 41144.12 | AE14: 41159.12 | AF14: 0 | AG14: 0 | AH14: 23 | AI14: 0 | AJ14: 23 | AK14: 0 | AL14: 0 | AM14: 0 | AN14: 0 | AO14: 0 | AP14: 0 | AQ14: 0 | AR14: 0 | AS14: 23 | AT14: 23 | AU14: 352898.97 | AV14: 41.27 | AW14: 194419.62 | AX14: 22.73 | AY14: 547318.59 | AZ14: 64 | BA14: 19316.33 | BB14: 2.31 | BC14: 118815.19 | BD14: 14.23 | BE14: 138131.52 | BF14: 16.54 | BG14: 333582.63 | BH14: 75604.44 | BI14: 409187.06 | BJ14: 104797.84 | BK14: 12.25 | BL14: 56949.88 | BM14: 6.66 | BN14: 161747.72 | BO14: 18.91 | BP14: 2067 | BQ14: 0.25 | BR14: 3461.39 | BS14: 0.41 | BT14: 5528.39 | BU14: 0.66 | BV14: 102730.84 | BW14: 53488.49 | BX14: 156219.33
A15: =IF(A14="",,IF(A14+7<=$C$4,A14+7,"")) -> 43896 | B15: 338 | C15: 0.05 | D15: 98978.5 | E15: 11.47 | F15: 99316.5 | G15: 11.52 | H15: 474 | I15: 0.06 | J15: 681713.66 | K15: 80.78 | L15: 682187.66 | M15: 80.84 | N15: -136 | O15: -582735.19 | P15: -582871.19 | Q15: 30 | R15: 0 | S15: 55365.59 | T15: 6.42 | U15: 55395.59 | V15: 6.42 | W15: 6 | X15: 0 | Y15: 19845.93 | Z15: 2.35 | AA15: 19851.93 | AB15: 2.35 | AC15: 24 | AD15: 35519.66 | AE15: 35543.66 | AF15: 0 | AG15: 0 | AH15: 17 | AI15: 0 | AJ15: 17 | AK15: 0 | AL15: 0 | AM15: 0 | AN15: 0 | AO15: 0 | AP15: 0 | AQ15: 0 | AR15: 0 | AS15: 17 | AT15: 17 | AU15: 355940.94 | AV15: 41.26 | AW15: 190898.67 | AX15: 22.13 | AY15: 546839.61 | AZ15: 63.39 | BA15: 18663.08 | BB15: 2.21 | BC15: 118026.99 | BD15: 13.99 | BE15: 136690.07 | BF15: 16.2 | BG15: 337277.84 | BH15: 72871.68 | BI15: 410149.56 | BJ15: 106225.87 | BK15: 12.31 | BL15: 54823.26 | BM15: 6.36 | BN15: 161049.13 | BO15: 18.67 | BP15: 2150 | BQ15: 0.25 | BR15: 3069.31 | BS15: 0.36 | BT15: 5219.31 | BU15: 0.61 | BV15: 104075.87 | BW15: 51753.95 | BX15: 155829.81
A16: =IF(A15="",,IF(A15+7<=$C$4,A15+7,"")) -> 43903 | B16: 327 | C16: 0.04 | D16: 95282.22 | E16: 10.76 | F16: 95609.22 | G16: 10.8 | H16: 474 | I16: 0.05 | J16: 687023.33 | K16: 78.68 | L16: 687497.33 | M16: 78.73 | N16: -147 | O16: -591741.13 | P16: -591888.13 | Q16: 30 | R16: 0 | S16: 47283.99 | T16: 5.34 | U16: 47313.99 | V16: 5.34 | W16: 7 | X16: 0 | Y16: 27158.94 | Z16: 3.11 | AA16: 27165.94 | AB16: 3.11 | AC16: 23 | AD16: 20125.05 | AE16: 20148.05 | AF16: 0 | AG16: 0 | AH16: 9 | AI16: 0 | AJ16: 9 | AK16: 0 | AL16: 0 | AM16: 0 | AN16: 254 | AO16: 0.03 | AP16: 254 | AQ16: 0.03 | AR16: 0 | AS16: -245 | AT16: -245 | AU16: 366823.73 | AV16: 41.41 | AW16: 213599.41 | AX16: 24.11 | AY16: 580423.14 | AZ16: 65.52 | BA16: 19871.4 | BB16: 2.28 | BC16: 133718.59 | BD16: 15.31 | BE16: 153589.99 | BF16: 17.59 | BG16: 346952.31 | BH16: 79880.81 | BI16: 426833.13 | BJ16: 107533.83 | BK16: 12.14 | BL16: 54952.57 | BM16: 6.2 | BN16: 162486.4 | BO16: 18.34 | BP16: 2034 | BQ16: 0.23 | BR16: 2683.34 | BS16: 0.31 | BT16: 4717.34 | BU16: 0.54 | BV16: 105499.83 | BW16: 52269.23 | BX16: 157769.06
A17: =IF(A16="",,IF(A16+7<=$C$4,A16+7,"")) -> 43910 | B17: 331 | C17: 0.03 | D17: 101041.86 | E17: 11.17 | F17: 101372.86 | G17: 11.2 | H17: 480 | I17: 0.06 | J17: 683831.52 | K17: 76.83 | L17: 684311.52 | M17: 76.89 | N17: -149 | O17: -582789.63 | P17: -582938.63 | Q17: 0 | R17: 0 | S17: 42424.95 | T17: 4.69 | U17: 42424.95 | V17: 4.69 | W17: 61 | X17: 0.01 | Y17: 36084.36 | Z17: 4.05 | AA17: 36145.36 | AB17: 4.06 | AC17: -61 | AD17: 6340.59 | AE17: 6279.59 | AF17: 0 | AG17: 0 | AH17: 0 | AI17: 0 | AJ17: 0 | AK17: 0 | AL17: 0 | AM17: 0 | AN17: 281 | AO17: 0.03 | AP17: 281 | AQ17: 0.03 | AR17: 0 | AS17: -281 | AT17: -281 | AU17: 381182.29 | AV17: 42.13 | AW17: 224525.97 | AX17: 24.81 | AY17: 605708.26 | AZ17: 66.94 | BA17: 20970.11 | BB17: 2.36 | BC17: 144734.18 | BD17: 16.26 | BE17: 165704.29 | BF17: 18.62 | BG17: 360212.19 | BH17: 79791.78 | BI17: 440003.94 | BJ17: 99327.95 | BK17: 10.98 | BL17: 55978.33 | BM17: 6.19 | BN17: 155306.28 | BO17: 17.17 | BP17: 1986 | BQ17: 0.22 | BR17: 1621.78 | BS17: 0.18 | BT17: 3607.78 | BU17: 0.4 | BV17: 97341.95 | BW17: 54356.55 | BX17: 151698.5
A18: =IF(A17="",,IF(A17+7<=$C$4,A17+7,"")) -> 43917 | B18: 344 | C18: 0.04 | D18: 99189.86 | E18: 10.88 | F18: 99533.86 | G18: 10.92 | H18: 487 | I18: 0.04 | J18: 684025.61 | K18: 76.58 | L18: 684512.61 | M18: 76.62 | N18: -143 | O18: -584835.75 | P18: -584978.75 | Q18: 0 | R18: 0 | S18: 51606.36 | T18: 5.66 | U18: 51606.36 | V18: 5.66 | W18: 50 | X18: 0.01 | Y18: 46535.65 | Z18: 5.21 | AA18: 46585.65 | AB18: 5.22 | AC18: -50 | AD18: 5070.71 | AE18: 5020.71 | AF18: 0 | AG18: 0 | AH18: 0 | AI18: 0 | AJ18: 0 | AK18: 0 | AL18: 0 | AM18: 0 | AN18: 46 | AO18: 0.01 | AP18: 46 | AQ18: 0.01 | AR18: 0 | AS18: -46 | AT18: -46 | AU18: 380895.46 | AV18: 41.8 | AW18: 220499.88 | AX18: 24.2 | AY18: 601395.34 | AZ18: 66 | BA18: 17911.38 | BB18: 2.01 | BC18: 140539.58 | BD18: 15.73 | BE18: 158450.96 | BF18: 17.74 | BG18: 362984.09 | BH18: 79960.3 | BI18: 442944.38 | BJ18: 103834.14 | BK18: 11.39 | BL18: 54969.06 | BM18: 6.03 | BN18: 158803.2 | BO18: 17.42 | BP18: 2013 | BQ18: 0.23 | BR18: 1629.96 | BS18: 0.18 | BT18: 3642.96 | BU18: 0.41 | BV18: 101821.14 | BW18: 53339.1 | BX18: 155160.25
... A124: =IF(A123="",,IF(A123+7<=$C$4,A123+7,"")) -> 44659 | B124: 0 | C124: 0 | D124: 129488.9 | E124: 20.67 | F124: 129488.9 | G124: 20.67 | H124: 0 | I124: 0 | J124: 568530.78 | K124: 89.02 | L124: 568530.78 | M124: 89.02 | N124: 0 | O124: -439041.84 | P124: -439041.84 | Q124: 1 | R124: 0 | S124: 34956.1 | T124: 5.58 | U124: 34957.1 | V124: 5.58 | W124: 0 | X124: 0 | Y124: 17469.32 | Z124: 2.74 | AA124: 17469.32 | AB124: 2.74 | AC124: 1 | AD124: 17486.78 | AE124: 17487.78 | AF124: 0 | AG124: 0 | AH124: 1218 | AI124: 0.19 | AJ124: 1218 | AK124: 0.19 | AL124: 0 | AM124: 0 | AN124: 0 | AO124: 0 | AP124: 0 | AQ124: 0 | AR124: 0 | AS124: 1218 | AT124: 1218 | AU124: 226822.27 | AV124: 36.19 | AW124: 138939.03 | AX124: 22.17 | AY124: 365761.3 | AZ124: 58.36 | BA124: 5949.01 | BB124: 0.93 | BC124: 42590.86 | BD124: 6.67 | BE124: 48539.87 | BF124: 7.6 | BG124: 220873.25 | BH124: 96348.17 | BI124: 317221.44 | BJ124: 50595.25 | BK124: 8.07 | BL124: 44712.24 | BM124: 7.13 | BN124: 95307.49 | BO124: 15.2 | BP124: 1734 | BQ124: 0.27 | BR124: 2377 | BS124: 0.37 | BT124: 4111 | BU124: 0.64 | BV124: 48861.25 | BW124: 42335.24 | BX124: 91196.49
A125: =IF(A124="",,IF(A124+7<=$C$4,A124+7,"")) -> 44666 | B125: #N/A N/A | C125: #N/A N/A | D125: #N/A N/A | E125: #N/A N/A | F125: #N/A N/A | G125: #N/A N/A | H125: #N/A N/A | I125: #N/A N/A | J125: #N/A N/A | K125: #N/A N/A | L125: #N/A N/A | M125: #N/A N/A | N125: #N/A N/A | O125: #N/A N/A | P125: #N/A N/A | Q125: #N/A N/A | R125: #N/A N/A | S125: #N/A N/A | T125: #N/A N/A | U125: #N/A N/A | V125: #N/A N/A | W125: #N/A N/A | X125: #N/A N/A | Y125: #N/A N/A | Z125: #N/A N/A | AA125: #N/A N/A | AB125: #N/A N/A | AC125: #N/A N/A | AD125: #N/A N/A | AE125: #N/A N/A | AF125: #N/A N/A | AG125: #N/A N/A | AH125: #N/A N/A | AI125: #N/A N/A | AJ125: #N/A N/A | AK125: #N/A N/A | AL125: #N/A N/A | AM125: #N/A N/A | AN125: #N/A N/A | AO125: #N/A N/A | AP125: #N/A N/A | AQ125: #N/A N/A | AR125: #N/A N/A | AS125: #N/A N/A | AT125: #N/A N/A | AU125: #N/A N/A | AV125: #N/A N/A | AW125: #N/A N/A | AX125: #N/A N/A | AY125: #N/A N/A | AZ125: #N/A N/A | BA125: #N/A N/A | BB125: #N/A N/A | BC125: #N/A N/A | BD125: #N/A N/A | BE125: #N/A N/A | BF125: #N/A N/A | BG125: #N/A N/A | BH125: #N/A N/A | BI125: #N/A N/A | BJ125: #N/A N/A | BK125: #N/A N/A | BL125: #N/A N/A | BM125: #N/A N/A | BN125: #N/A N/A | BO125: #N/A N/A | BP125: #N/A N/A | BQ125: #N/A N/A | BR125: #N/A N/A | BS125: #N/A N/A | BT125: #N/A N/A | BU125: #N/A N/A | BV125: #N/A N/A | BW125: #N/A N/A | BX125: #N/A N/A
A126: =IF(A125="",,IF(A125+7<=$C$4,A125+7,"")) -> 44673 | B126: 0 | C126: 0 | D126: 130940.01 | E126: 20.73 | F126: 130940.01 | G126: 20.73 | H126: 0 | I126: 0 | J126: 572578.37 | K126: 89.05 | L126: 572578.37 | M126: 89.05 | N126: 0 | O126: -441638.38 | P126: -441638.38 | Q126: 134.38 | R126: 0.02 | S126: 39837.74 | T126: 6.31 | U126: 39972.12 | V126: 6.33 | W126: 95 | X126: 0.01 | Y126: 17299.51 | Z126: 2.69 | AA126: 17394.51 | AB126: 2.7 | AC126: 39.38 | AD126: 22538.23 | AE126: 22577.61 | AF126: 0 | AG126: 0 | AH126: 1223 | AI126: 0.19 | AJ126: 1223 | AK126: 0.19 | AL126: 0 | AM126: 0 | AN126: 0 | AO126: 0 | AP126: 0 | AQ126: 0 | AR126: 0 | AS126: 1223 | AT126: 1223 | AU126: 228832.21 | AV126: 36.24 | AW126: 138537.14 | AX126: 21.94 | AY126: 367369.35 | AZ126: 58.18 | BA126: 6450.91 | BB126: 1 | BC126: 42208.92 | BD126: 6.56 | BE126: 48659.83 | BF126: 7.56 | BG126: 222381.3 | BH126: 96328.22 | BI126: 318709.5 | BJ126: 47462.95 | BK126: 7.52 | BL126: 44551.01 | BM126: 7.05 | BN126: 92013.96 | BO126: 14.57 | BP126: 2028 | BQ126: 0.32 | BR126: 2377 | BS126: 0.37 | BT126: 4405 | BU126: 0.69 | BV126: 45434.95 | BW126: 42174.01 | BX126: 87608.96
A127: =IF(A126="",,IF(A126+7<=$C$4,A126+7,"")) -> 44680 | B127: 0 | C127: 0 | D127: 129974.01 | E127: 20.82 | F127: 129974.01 | G127: 20.82 | H127: 0 | I127: 0 | J127: 569397.48 | K127: 89.55 | L127: 569397.48 | M127: 89.55 | N127: 0 | O127: -439423.5 | P127: -439423.5 | Q127: 152.38 | R127: 0.02 | S127: 37411.46 | T127: 5.99 | U127: 37563.84 | V127: 6.01 | W127: 95 | X127: 0.01 | Y127: 15494.34 | Z127: 2.44 | AA127: 15589.34 | AB127: 2.45 | AC127: 57.38 | AD127: 21917.12 | AE127: 21974.5 | AF127: 0 | AG127: 0 | AH127: 1225 | AI127: 0.2 | AJ127: 1225 | AK127: 0.2 | AL127: 0 | AM127: 0 | AN127: 0 | AO127: 0 | AP127: 0 | AQ127: 0 | AR127: 0 | AS127: 1225 | AT127: 1225 | AU127: 232776.99 | AV127: 37.29 | AW127: 135354.38 | AX127: 21.68 | AY127: 368131.37 | AZ127: 58.97 | BA127: 6648.51 | BB127: 1.05 | BC127: 39580.7 | BD127: 6.22 | BE127: 46229.21 | BF127: 7.27 | BG127: 226128.47 | BH127: 95773.67 | BI127: 321902.16 | BJ127: 44222.84 | BK127: 7.08 | BL127: 43172.34 | BM127: 6.92 | BN127: 87395.18 | BO127: 14 | BP127: 2081 | BQ127: 0.33 | BR127: 2546.9 | BS127: 0.4 | BT127: 4627.9 | BU127: 0.73 | BV127: 42141.84 | BW127: 40625.44 | BX127: 82767.28
A128: =IF(A127="",,IF(A127+7<=$C$4,A127+7,"")) -> 44687 | B128: 0 | C128: 0 | D128: 131015.23 | E128: 20.42 | F128: 131015.23 | G128: 20.42 | H128: 0 | I128: 0 | J128: 579999.61 | K128: 88.95 | L128: 579999.61 | M128: 88.95 | N128: 0 | O128: -448984.41 | P128: -448984.41 | Q128: 183.24 | R128: 0.03 | S128: 40384.26 | T128: 6.29 | U128: 40567.5 | V128: 6.32 | W128: 115 | X128: 0.02 | Y128: 16302 | Z128: 2.5 | AA128: 16417 | AB128: 2.52 | AC128: 68.24 | AD128: 24082.26 | AE128: 24150.5 | AF128: 0 | AG128: 0 | AH128: 1239 | AI128: 0.19 | AJ128: 1239 | AK128: 0.19 | AL128: 0 | AM128: 0 | AN128: 0 | AO128: 0 | AP128: 0 | AQ128: 0 | AR128: 0 | AS128: 1239 | AT128: 1239 | AU128: 235013.89 | AV128: 36.63 | AW128: 141264.42 | AX128: 22.02 | AY128: 376278.31 | AZ128: 58.65 | BA128: 6613.75 | BB128: 1.01 | BC128: 44341.48 | BD128: 6.8 | BE128: 50955.23 | BF128: 7.81 | BG128: 228400.14 | BH128: 96922.94 | BI128: 325323.09 | BJ128: 49373.36 | BK128: 7.69 | BL128: 43187.35 | BM128: 6.73 | BN128: 92560.71 | BO128: 14.42 | BP128: 2243 | BQ128: 0.34 | BR128: 2486.77 | BS128: 0.38 | BT128: 4729.77 | BU128: 0.72 | BV128: 47130.36 | BW128: 40700.58 | BX128: 87830.94
A129: =IF(A128="",,IF(A128+7<=$C$4,A128+7,"")) -> 44694 | B129: 0 | C129: 0 | D129: 125448.87 | E129: 19.56 | F129: 125448.87 | G129: 19.56 | H129: 0 | I129: 0 | J129: 581760.47 | K129: 88.83 | L129: 581760.47 | M129: 88.83 | N129: 0 | O129: -456311.63 | P129: -456311.63 | Q129: 192.47 | R129: 0.03 | S129: 38397.92 | T129: 5.99 | U129: 38590.39 | V129: 6.02 | W129: 140 | X129: 0.02 | Y129: 15661.4 | Z129: 2.39 | AA129: 15801.4 | AB129: 2.41 | AC129: 52.47 | AD129: 22736.52 | AE129: 22788.99 | AF129: 0 | AG129: 0 | AH129: 1262 | AI129: 0.2 | AJ129: 1262 | AK129: 0.2 | AL129: 0 | AM129: 0 | AN129: 0 | AO129: 0 | AP129: 0 | AQ129: 0 | AR129: 0 | AS129: 1262 | AT129: 1262 | AU129: 237079.17 | AV129: 36.97 | AW129: 139097.88 | AX129: 21.69 | AY129: 376177.05 | AZ129: 58.66 | BA129: 6591.68 | BB129: 1.01 | BC129: 44119.68 | BD129: 6.74 | BE129: 50711.36 | BF129: 7.75 | BG129: 230487.48 | BH129: 94978.2 | BI129: 325465.69 | BJ129: 55646 | BK129: 8.68 | BL129: 44101.22 | BM129: 6.88 | BN129: 99747.22 | BO129: 15.56 | BP129: 3628 | BQ129: 0.55 | BR129: 3018.56 | BS129: 0.46 | BT129: 6646.56 | BU129: 1.01 | BV129: 52018 | BW129: 41082.66 | BX129: 93100.66
A130: =IF(A129="",,IF(A129+7<=$C$4,A129+7,"")) -> 44701 | B130: 0 | C130: 0 | D130: 122709.49 | E130: 18.79 | F130: 122709.49 | G130: 18.79 | H130: 0 | I130: 0 | J130: 588797.3 | K130: 88.5 | L130: 588797.3 | M130: 88.5 | N130: 0 | O130: -466087.81 | P130: -466087.81 | Q130: 190.87 | R130: 0.03 | S130: 33749.4 | T130: 5.17 | U130: 33940.27 | V130: 5.2 | W130: 175 | X130: 0.03 | Y130: 17069.98 | Z130: 2.57 | AA130: 17244.98 | AB130: 2.6 | AC130: 15.87 | AD130: 16679.42 | AE130: 16695.29 | AF130: 0 | AG130: 0 | AH130: 1160 | AI130: 0.18 | AJ130: 1160 | AK130: 0.18 | AL130: 0 | AM130: 0 | AN130: 0 | AO130: 0 | AP130: 0 | AQ130: 0 | AR130: 0 | AS130: 1160 | AT130: 1160 | AU130: 242998.9 | AV130: 37.22 | AW130: 147415.38 | AX130: 22.58 | AY130: 390414.28 | AZ130: 59.8 | BA130: 6499.77 | BB130: 0.98 | BC130: 45867.95 | BD130: 6.9 | BE130: 52367.72 | BF130: 7.88 | BG130: 236499.14 | BH130: 101547.42 | BI130: 338046.56 | BJ130: 59955 | BK130: 9.18 | BL130: 44707.91 | BM130: 6.85 | BN130: 104662.91 | BO130: 16.03 | BP130: 3804 | BQ130: 0.57 | BR130: 2994.55 | BS130: 0.45 | BT130: 6798.55 | BU130: 1.02 | BV130: 56151 | BW130: 41713.36 | BX130: 97864.36
A131: =IF(A130="",,IF(A130+7<=$C$4,A130+7,"")) -> 44708 | B131: 0 | C131: 0 | D131: 110501.19 | E131: 17.26 | F131: 110501.19 | G131: 17.26 | H131: 0 | I131: 0 | J131: 578610.81 | K131: 88.53 | L131: 578610.81 | M131: 88.53 | N131: 0 | O131: -468109.63 | P131: -468109.63 | Q131: 190.6 | R131: 0.03 | S131: 33466.38 | T131: 5.23 | U131: 33656.98 | V131: 5.26 | W131: 170 | X131: 0.03 | Y131: 17635.7 | Z131: 2.7 | AA131: 17805.7 | AB131: 2.73 | AC131: 20.6 | AD131: 15830.68 | AE131: 15851.28 | AF131: 0 | AG131: 0 | AH131: 1372 | AI131: 0.21 | AJ131: 1372 | AK131: 0.21 | AL131: 0 | AM131: 0 | AN131: 197 | AO131: 0.03 | AP131: 197 | AQ131: 0.03 | AR131: 0 | AS131: 1175 | AT131: 1175 | AU131: 243310.81 | AV131: 38 | AW131: 146919.08 | AX131: 22.94 | AY131: 390229.89 | AZ131: 60.94 | BA131: 6332.91 | BB131: 0.97 | BC131: 43157.17 | BD131: 6.6 | BE131: 49490.08 | BF131: 7.57 | BG131: 236977.91 | BH131: 103761.91 | BI131: 340739.81 | BJ131: 60010 | BK131: 9.37 | BL131: 44572.91 | BM131: 6.96 | BN131: 104582.91 | BO131: 16.33 | BP131: 4489 | BQ131: 0.69 | BR131: 2970.55 | BS131: 0.45 | BT131: 7459.55 | BU131: 1.14 | BV131: 55521 | BW131: 41602.36 | BX131: 97123.36
A132: =IF(A131="",,IF(A131+7<=$C$4,A131+7,"")) -> 44715 | B132: 0 | C132: 0 | D132: 111061.73 | E132: 17.26 | F132: 111061.73 | G132: 17.26 | H132: 0 | I132: 0 | J132: 581800.39 | K132: 88.59 | L132: 581800.39 | M132: 88.59 | N132: 0 | O132: -470738.66 | P132: -470738.66 | Q132: 192.87 | R132: 0.03 | S132: 35279.04 | T132: 5.49 | U132: 35471.91 | V132: 5.52 | W132: 170 | X132: 0.03 | Y132: 16950.31 | Z132: 2.58 | AA132: 17120.31 | AB132: 2.61 | AC132: 22.87 | AD132: 18328.73 | AE132: 18351.6 | AF132: 0 | AG132: 0 | AH132: 1334 | AI132: 0.21 | AJ132: 1334 | AK132: 0.21 | AL132: 0 | AM132: 0 | AN132: 201 | AO132: 0.03 | AP132: 201 | AQ132: 0.03 | AR132: 0 | AS132: 1133 | AT132: 1133 | AU132: 242844.86 | AV132: 37.77 | AW132: 148249.7 | AX132: 23.06 | AY132: 391094.56 | AZ132: 60.83 | BA132: 6214.93 | BB132: 0.95 | BC132: 42006.24 | BD132: 6.4 | BE132: 48221.17 | BF132: 7.35 | BG132: 236629.92 | BH132: 106243.47 | BI132: 342873.38 | BJ132: 59157 | BK132: 9.2 | BL132: 44903.76 | BM132: 6.98 | BN132: 104060.76 | BO132: 16.18 | BP132: 6516 | BQ132: 0.99 | BR132: 2826.02 | BS132: 0.43 | BT132: 9342.02 | BU132: 1.42 | BV132: 52641 | BW132: 42077.74 | BX132: 94718.73
A133: =IF(A132="",,IF(A132+7<=$C$4,A132+7,"")) -> 44722 | B133: 0 | C133: 0 | D133: 107358.17 | E133: 16.73 | F133: 107358.17 | G133: 16.73 | H133: 0 | I133: 0 | J133: 579336.87 | K133: 88.1 | L133: 579336.87 | M133: 88.1 | N133: 0 | O133: -471978.69 | P133: -471978.69 | Q133: 182.33 | R133: 0.03 | S133: 31531.81 | T133: 4.91 | U133: 31714.14 | V133: 4.94 | W133: 170 | X133: 0.03 | Y133: 17130.73 | Z133: 2.61 | AA133: 17300.73 | AB133: 2.64 | AC133: 12.33 | AD133: 14401.08 | AE133: 14413.41 | AF133: 0 | AG133: 0 | AH133: 1166 | AI133: 0.18 | AJ133: 1166 | AK133: 0.18 | AL133: 0 | AM133: 0 | AN133: 201 | AO133: 0.03 | AP133: 201 | AQ133: 0.03 | AR133: 0 | AS133: 965 | AT133: 965 | AU133: 246005.56 | AV133: 38.34 | AW133: 149700.94 | AX133: 23.33 | AY133: 395706.5 | AZ133: 61.67 | BA133: 6560.64 | BB133: 1 | BC133: 39922.12 | BD133: 6.07 | BE133: 46482.76 | BF133: 7.07 | BG133: 239444.92 | BH133: 109778.81 | BI133: 349223.75 | BJ133: 59647 | BK133: 9.3 | BL133: 46078.67 | BM133: 7.18 | BN133: 105725.67 | BO133: 16.48 | BP133: 11276 | BQ133: 1.71 | BR133: 2950.86 | BS133: 0.45 | BT133: 14226.86 | BU133: 2.16 | BV133: 48371 | BW133: 43127.81 | BX133: 91498.81
A134: =IF(A133="",,IF(A133+7<=$C$4,A133+7,"")) -> 44729 | B134: 0 | C134: 0 | D134: 108833.7 | E134: 16.79 | F134: 108833.7 | G134: 16.79 | H134: 0 | I134: 0 | J134: 586064.17 | K134: 88.24 | L134: 586064.17 | M134: 88.24 | N134: 0 | O134: -477230.5 | P134: -477230.5 | Q134: 181 | R134: 0.03 | S134: 33194.52 | T134: 5.12 | U134: 33375.52 | V134: 5.15 | W134: 170.75 | X134: 0.03 | Y134: 17440.28 | Z134: 2.63 | AA134: 17611.03 | AB134: 2.66 | AC134: 10.25 | AD134: 15754.24 | AE134: 15764.49 | AF134: 0 | AG134: 0 | AH134: 1125 | AI134: 0.17 | AJ134: 1125 | AK134: 0.17 | AL134: 0 | AM134: 0 | AN134: 201 | AO134: 0.03 | AP134: 201 | AQ134: 0.03 | AR134: 0 | AS134: 924 | AT134: 924 | AU134: 248567.56 | AV134: 38.33 | AW134: 149565.08 | AX134: 23.06 | AY134: 398132.64 | AZ134: 61.39 | BA134: 7878.49 | BB134: 1.19 | BC134: 39349.12 | BD134: 5.93 | BE134: 47227.61 | BF134: 7.12 | BG134: 240689.08 | BH134: 110215.95 | BI134: 350905 | BJ134: 60167 | BK134: 9.28 | BL134: 46851.11 | BM134: 7.22 | BN134: 107018.11 | BO134: 16.5 | BP134: 9904 | BQ134: 1.49 | BR134: 3057.11 | BS134: 0.46 | BT134: 12961.11 | BU134: 1.95 | BV134: 50263 | BW134: 43794 | BX134: 94057
A135: =IF(A134="",,IF(A134+7<=$C$4,A134+7,"")) -> 44736 | B135: 0 | C135: 0 | D135: 108262.21 | E135: 16.98 | F135: 108262.21 | G135: 16.98 | H135: 0 | I135: 0 | J135: 595082.48 | K135: 88.18 | L135: 595082.48 | M135: 88.18 | N135: 0 | O135: -486820.28 | P135: -486820.28 | Q135: 181 | R135: 0.03 | S135: 34331.22 | T135: 5.38 | U135: 34512.22 | V135: 5.41 | W135: 170 | X135: 0.03 | Y135: 17044.99 | Z135: 2.53 | AA135: 17214.99 | AB135: 2.56 | AC135: 11 | AD135: 17286.23 | AE135: 17297.23 | AF135: 0 | AG135: 0 | AH135: 982 | AI135: 0.15 | AJ135: 982 | AK135: 0.15 | AL135: 0 | AM135: 0 | AN135: 201 | AO135: 0.03 | AP135: 201 | AQ135: 0.03 | AR135: 0 | AS135: 781 | AT135: 781 | AU135: 254497.48 | AV135: 39.9 | AW135: 151527.92 | AX135: 23.75 | AY135: 406025.4 | AZ135: 63.65 | BA135: 13386.82 | BB135: 1.98 | BC135: 36046.04 | BD135: 5.34 | BE135: 49432.86 | BF135: 7.32 | BG135: 241110.66 | BH135: 115481.88 | BI135: 356592.56 | BJ135: 60749 | BK135: 9.52 | BL135: 27369.31 | BM135: 4.29 | BN135: 88118.31 | BO135: 13.81 | BP135: 9763 | BQ135: 1.45 | BR135: 3135.97 | BS135: 0.46 | BT135: 12898.97 | BU135: 1.91 | BV135: 50986 | BW135: 24233.34 | BX135: 75219.34
A136: =IF(A135="",,IF(A135+7<=$C$4,A135+7,"")) -> 44743 | B136: 0 | C136: 0 | D136: 102120.39 | E136: 15.63 | F136: 102120.39 | G136: 15.63 | H136: 0 | I136: 0 | J136: 588051.23 | K136: 87.79 | L136: 588051.23 | M136: 87.79 | N136: 0 | O136: -485930.88 | P136: -485930.88 | Q136: 181 | R136: 0.03 | S136: 37418.3 | T136: 5.73 | U136: 37599.3 | V136: 5.76 | W136: 170 | X136: 0.03 | Y136: 15668.79 | Z136: 2.34 | AA136: 15838.79 | AB136: 2.37 | AC136: 11 | AD136: 21749.51 | AE136: 21760.51 | AF136: 0 | AG136: 0 | AH136: 947 | AI136: 0.14 | AJ136: 947 | AK136: 0.14 | AL136: 0 | AM136: 0 | AN136: 201 | AO136: 0.03 | AP136: 201 | AQ136: 0.03 | AR136: 0 | AS136: 746 | AT136: 746 | AU136: 255657.21 | AV136: 39.12 | AW136: 147964.47 | AX136: 22.64 | AY136: 403621.68 | AZ136: 61.76 | BA136: 16258.95 | BB136: 2.43 | BC136: 35927.45 | BD136: 5.36 | BE136: 52186.4 | BF136: 7.79 | BG136: 239398.25 | BH136: 112037.02 | BI136: 351435.28 | BJ136: 60120 | BK136: 9.2 | BL136: 49111.56 | BM136: 7.51 | BN136: 109231.56 | BO136: 16.71 | BP136: 10448 | BQ136: 1.56 | BR136: 3104.37 | BS136: 0.46 | BT136: 13552.37 | BU136: 2.02 | BV136: 49672 | BW136: 46007.19 | BX136: 95679.2
A137: =IF(A136="",,IF(A136+7<=$C$4,A136+7,"")) -> 44750 | B137: 0 | C137: 0 | D137: 103762.72 | E137: 15.75 | F137: 103762.72 | G137: 15.75 | H137: 0 | I137: 0 | J137: 597469.36 | K137: 88.38 | L137: 597469.36 | M137: 88.38 | N137: 0 | O137: -493706.66 | P137: -493706.66 | Q137: 181 | R137: 0.03 | S137: 35733.6 | T137: 5.42 | U137: 35914.6 | V137: 5.45 | W137: 163 | X137: 0.02 | Y137: 15777.4 | Z137: 2.33 | AA137: 15940.4 | AB137: 2.35 | AC137: 18 | AD137: 19956.2 | AE137: 19974.2 | AF137: 0 | AG137: 0 | AH137: 939 | AI137: 0.14 | AJ137: 939 | AK137: 0.14 | AL137: 0 | AM137: 0 | AN137: 201 | AO137: 0.03 | AP137: 201 | AQ137: 0.03 | AR137: 0 | AS137: 738 | AT137: 738 | AU137: 259182.88 | AV137: 39.34 | AW137: 147156.54 | AX137: 22.33 | AY137: 406339.42 | AZ137: 61.67 | BA137: 12739.7 | BB137: 1.88 | BC137: 36860.88 | BD137: 5.45 | BE137: 49600.58 | BF137: 7.33 | BG137: 246443.17 | BH137: 110295.67 | BI137: 356738.81 | BJ137: 61952 | BK137: 9.4 | BL137: 49994.87 | BM137: 7.59 | BN137: 111946.87 | BO137: 16.99 | BP137: 9783 | BQ137: 1.45 | BR137: 3100.56 | BS137: 0.46 | BT137: 12883.56 | BU137: 1.91 | BV137: 52169 | BW137: 46894.31 | BX137: 99063.3
... A175: =IF(A174="",,IF(A174+7<=$C$4,A174+7,"")) -> 45016 | B175: 0 | C175: 0 | D175: 135269.7 | E175: 27.79 | F175: 135269.7 | G175: 27.79 | H175: 0 | I175: 0 | J175: 403260.68 | K175: 82.73 | L175: 403260.68 | M175: 82.73 | N175: 0 | O175: -267991 | P175: -267991 | Q175: 0 | R175: 0 | S175: 32543.59 | T175: 6.69 | U175: 32543.59 | V175: 6.69 | W175: 0 | X175: 0 | Y175: 24701.91 | Z175: 5.07 | AA175: 24701.91 | AB175: 5.07 | AC175: 0 | AD175: 7841.68 | AE175: 7841.68 | AF175: 0 | AG175: 0 | AH175: 386 | AI175: 0.08 | AJ175: 386 | AK175: 0.08 | AL175: 0 | AM175: 0 | AN175: 194 | AO175: 0.04 | AP175: 194 | AQ175: 0.04 | AR175: 0 | AS175: 192 | AT175: 192 | AU175: 154061.85 | AV175: 31.67 | AW175: 99291.65 | AX175: 20.41 | AY175: 253353.5 | AZ175: 52.08 | BA175: 12453.87 | BB175: 2.56 | BC175: 27071.47 | BD175: 5.55 | BE175: 39525.34 | BF175: 8.11 | BG175: 141607.97 | BH175: 72220.18 | BI175: 213828.16 | BJ175: 35690 | BK175: 7.34 | BL175: 29270.57 | BM175: 6.02 | BN175: 64960.57 | BO175: 13.36 | BP175: 17994 | BQ175: 3.69 | BR175: 1732.66 | BS175: 0.36 | BT175: 19726.66 | BU175: 4.05 | BV175: 17696 | BW175: 27537.91 | BX175: 45233.91
A176: =IF(A175="",,IF(A175+7<=$C$4,A175+7,"")) -> 45023 | B176: #N/A N/A | C176: #N/A N/A | D176: #N/A N/A | E176: #N/A N/A | F176: #N/A N/A | G176: #N/A N/A | H176: #N/A N/A | I176: #N/A N/A | J176: #N/A N/A | K176: #N/A N/A | L176: #N/A N/A | M176: #N/A N/A | N176: #N/A N/A | O176: #N/A N/A | P176: #N/A N/A | Q176: #N/A N/A | R176: #N/A N/A | S176: #N/A N/A | T176: #N/A N/A | U176: #N/A N/A | V176: #N/A N/A | W176: #N/A N/A | X176: #N/A N/A | Y176: #N/A N/A | Z176: #N/A N/A | AA176: #N/A N/A | AB176: #N/A N/A | AC176: #N/A N/A | AD176: #N/A N/A | AE176: #N/A N/A | AF176: #N/A N/A | AG176: #N/A N/A | AH176: #N/A N/A | AI176: #N/A N/A | AJ176: #N/A N/A | AK176: #N/A N/A | AL176: #N/A N/A | AM176: #N/A N/A | AN176: #N/A N/A | AO176: #N/A N/A | AP176: #N/A N/A | AQ176: #N/A N/A | AR176: #N/A N/A | AS176: #N/A N/A | AT176: #N/A N/A | AU176: #N/A N/A | AV176: #N/A N/A | AW176: #N/A N/A | AX176: #N/A N/A | AY176: #N/A N/A | AZ176: #N/A N/A | BA176: #N/A N/A | BB176: #N/A N/A | BC176: #N/A N/A | BD176: #N/A N/A | BE176: #N/A N/A | BF176: #N/A N/A | BG176: #N/A N/A | BH176: #N/A N/A | BI176: #N/A N/A | BJ176: #N/A N/A | BK176: #N/A N/A | BL176: #N/A N/A | BM176: #N/A N/A | BN176: #N/A N/A | BO176: #N/A N/A | BP176: #N/A N/A | BQ176: #N/A N/A | BR176: #N/A N/A | BS176: #N/A N/A | BT176: #N/A N/A | BU176: #N/A N/A | BV176: #N/A N/A | BW176: #N/A N/A | BX176: #N/A N/A
A177: =IF(A176="",,IF(A176+7<=$C$4,A176+7,"")) -> 45030 | B177: 0 | C177: 0 | D177: 137439.57 | E177: 28.3 | F177: 137439.57 | G177: 28.3 | H177: 0 | I177: 0 | J177: 407627.25 | K177: 80.52 | L177: 407627.25 | M177: 80.52 | N177: 0 | O177: -270187.69 | P177: -270187.69 | Q177: 0 | R177: 0 | S177: 36623.78 | T177: 7.54 | U177: 36623.78 | V177: 7.54 | W177: 0 | X177: 0 | Y177: 24070.05 | Z177: 4.75 | AA177: 24070.05 | AB177: 4.75 | AC177: 0 | AD177: 12553.73 | AE177: 12553.73 | AF177: 0 | AG177: 0 | AH177: 299 | AI177: 0.06 | AJ177: 299 | AK177: 0.06 | AL177: 0 | AM177: 0 | AN177: 388 | AO177: 0.08 | AP177: 388 | AQ177: 0.08 | AR177: 0 | AS177: -89 | AT177: -89 | AU177: 157670.61 | AV177: 32.47 | AW177: 92064.29 | AX177: 18.96 | AY177: 249734.9 | AZ177: 51.43 | BA177: 23029.18 | BB177: 4.55 | BC177: 32738.76 | BD177: 6.47 | BE177: 55767.94 | BF177: 11.02 | BG177: 134641.44 | BH177: 59325.53 | BI177: 193966.97 | BJ177: 32299 | BK177: 6.65 | BL177: 29226.54 | BM177: 6.02 | BN177: 61525.54 | BO177: 12.67 | BP177: 17290 | BQ177: 3.42 | BR177: 1082 | BS177: 0.21 | BT177: 18372 | BU177: 3.63 | BV177: 15009 | BW177: 28144.54 | BX177: 43153.54
A178: =IF(A177="",,IF(A177+7<=$C$4,A177+7,"")) -> 45037 | B178: 0 | C178: 0 | D178: 144048.44 | E178: 29.02 | F178: 144048.44 | G178: 29.02 | H178: 0 | I178: 0 | J178: 401520.76 | K178: 78.62 | L178: 401520.76 | M178: 78.62 | N178: 0 | O178: -257472.33 | P178: -257472.33 | Q178: 0 | R178: 0 | S178: 33292.75 | T178: 6.7 | U178: 33292.75 | V178: 6.7 | W178: 0 | X178: 0 | Y178: 25552.66 | Z178: 5 | AA178: 25552.66 | AB178: 5 | AC178: 0 | AD178: 7740.09 | AE178: 7740.09 | AF178: 0 | AG178: 0 | AH178: 302 | AI178: 0.06 | AJ178: 302 | AK178: 0.06 | AL178: 0 | AM178: 0 | AN178: 0 | AO178: 0 | AP178: 0 | AQ178: 0 | AR178: 0 | AS178: 302 | AT178: 302 | AU178: 160082.62 | AV178: 32.23 | AW178: 96545.47 | AX178: 19.44 | AY178: 256628.09 | AZ178: 51.67 | BA178: 31117.15 | BB178: 6.09 | BC178: 34120.38 | BD178: 6.68 | BE178: 65237.53 | BF178: 12.77 | BG178: 128965.48 | BH178: 62425.09 | BI178: 191390.56 | BJ178: 32551 | BK178: 6.55 | BL178: 29818.29 | BM178: 6 | BN178: 62369.29 | BO178: 12.55 | BP178: 17410 | BQ178: 3.41 | BR178: 1027 | BS178: 0.2 | BT178: 18437 | BU178: 3.61 | BV178: 15141 | BW178: 28791.29 | BX178: 43932.29
A179: =IF(A178="",,IF(A178+7<=$C$4,A178+7,"")) -> 45044 | B179: 0 | C179: 0 | D179: 119940.24 | E179: 25.71 | F179: 119940.24 | G179: 25.71 | H179: 0 | I179: 0 | J179: 360882.16 | K179: 76.87 | L179: 360882.16 | M179: 76.87 | N179: 0 | O179: -240941.91 | P179: -240941.91 | Q179: 0 | R179: 0 | S179: 23121.06 | T179: 4.96 | U179: 23121.06 | V179: 4.96 | W179: 0 | X179: 0 | Y179: 27860.8 | Z179: 5.94 | AA179: 27860.8 | AB179: 5.94 | AC179: 0 | AD179: -4739.74 | AE179: -4739.74 | AF179: 0 | AG179: 0 | AH179: 172 | AI179: 0.04 | AJ179: 172 | AK179: 0.04 | AL179: 0 | AM179: 0 | AN179: 222 | AO179: 0.05 | AP179: 222 | AQ179: 0.05 | AR179: 0 | AS179: -50 | AT179: -50 | AU179: 164669.89 | AV179: 35.31 | AW179: 94580.64 | AX179: 20.28 | AY179: 259250.53 | AZ179: 55.59 | BA179: 30675.52 | BB179: 6.54 | BC179: 30495.1 | BD179: 6.5 | BE179: 61170.62 | BF179: 13.04 | BG179: 133994.38 | BH179: 64085.54 | BI179: 198079.91 | BJ179: 33012 | BK179: 7.08 | BL179: 30883.58 | BM179: 6.62 | BN179: 63895.58 | BO179: 13.7 | BP179: 18161 | BQ179: 3.87 | BR179: 1096.12 | BS179: 0.23 | BT179: 19257.12 | BU179: 4.1 | BV179: 14851 | BW179: 29787.46 | BX179: 44638.46
A180: =IF(A179="",,IF(A179+7<=$C$4,A179+7,"")) -> 45051 | B180: 0 | C180: 0 | D180: 122681.42 | E180: 26.13 | F180: 122681.42 | G180: 26.13 | H180: 0 | I180: 0 | J180: 357989.99 | K180: 76 | L180: 357989.99 | M180: 76 | N180: 0 | O180: -235308.58 | P180: -235308.58 | Q180: 0 | R180: 0 | S180: 20165.75 | T180: 4.3 | U180: 20165.75 | V180: 4.3 | W180: 0 | X180: 0 | Y180: 30450.94 | Z180: 6.46 | AA180: 30450.94 | AB180: 6.46 | AC180: 0 | AD180: -10285.19 | AE180: -10285.19 | AF180: 0 | AG180: 0 | AH180: 172 | AI180: 0.04 | AJ180: 172 | AK180: 0.04 | AL180: 0 | AM180: 0 | AN180: 227 | AO180: 0.05 | AP180: 227 | AQ180: 0.05 | AR180: 0 | AS180: -55 | AT180: -55 | AU180: 167960.11 | AV180: 35.79 | AW180: 92069.11 | AX180: 19.62 | AY180: 260029.22 | AZ180: 55.41 | BA180: 30673.97 | BB180: 6.51 | BC180: 33710.09 | BD180: 7.16 | BE180: 64384.06 | BF180: 13.67 | BG180: 137286.14 | BH180: 58359.02 | BI180: 195645.16 | BJ180: 35174 | BK180: 7.49 | BL180: 31104.83 | BM180: 6.63 | BN180: 66278.83 | BO180: 14.12 | BP180: 16595 | BQ180: 3.52 | BR180: 1430.66 | BS180: 0.3 | BT180: 18025.66 | BU180: 3.82 | BV180: 18579 | BW180: 29674.17 | BX180: 48253.17
A181: =IF(A180="",,IF(A180+7<=$C$4,A180+7,"")) -> 45058 | B181: 0 | C181: 0 | D181: 129328.29 | E181: 27.03 | F181: 129328.29 | G181: 27.03 | H181: 0 | I181: 0 | J181: 364992.45 | K181: 75.85 | L181: 364992.45 | M181: 75.85 | N181: 0 | O181: -235664.16 | P181: -235664.16 | Q181: 0 | R181: 0 | S181: 20363.19 | T181: 4.26 | U181: 20363.19 | V181: 4.26 | W181: 0 | X181: 0 | Y181: 28356.33 | Z181: 5.89 | AA181: 28356.33 | AB181: 5.89 | AC181: 0 | AD181: -7993.14 | AE181: -7993.14 | AF181: 0 | AG181: 0 | AH181: 171 | AI181: 0.04 | AJ181: 171 | AK181: 0.04 | AL181: 0 | AM181: 0 | AN181: 227 | AO181: 0.05 | AP181: 227 | AQ181: 0.05 | AR181: 0 | AS181: -56 | AT181: -56 | AU181: 168786.25 | AV181: 35.28 | AW181: 91716.2 | AX181: 19.17 | AY181: 260502.45 | AZ181: 54.45 | BA181: 30630.29 | BB181: 6.37 | BC181: 38255.56 | BD181: 7.95 | BE181: 68885.85 | BF181: 14.32 | BG181: 138155.97 | BH181: 53460.64 | BI181: 191616.59 | BJ181: 36683 | BK181: 7.67 | BL181: 31346.75 | BM181: 6.55 | BN181: 68029.75 | BO181: 14.22 | BP181: 17445 | BQ181: 3.63 | BR181: 1271.21 | BS181: 0.26 | BT181: 18716.21 | BU181: 3.89 | BV181: 19238 | BW181: 30075.54 | BX181: 49313.54
A182: =IF(A181="",,IF(A181+7<=$C$4,A181+7,"")) -> 45065 | B182: 0 | C182: 0 | D182: 130331.38 | E182: 26.9 | F182: 130331.38 | G182: 26.9 | H182: 0 | I182: 0 | J182: 368535.78 | K182: 75.71 | L182: 368535.78 | M182: 75.71 | N182: 0 | O182: -238204.41 | P182: -238204.41 | Q182: 0 | R182: 0 | S182: 22181.67 | T182: 4.58 | U182: 22181.67 | V182: 4.58 | W182: 0 | X182: 0 | Y182: 26320.6 | Z182: 5.41 | AA182: 26320.6 | AB182: 5.41 | AC182: 0 | AD182: -4138.93 | AE182: -4138.93 | AF182: 0 | AG182: 0 | AH182: 331 | AI182: 0.07 | AJ182: 331 | AK182: 0.07 | AL182: 0 | AM182: 0 | AN182: 227 | AO182: 0.05 | AP182: 227 | AQ182: 0.05 | AR182: 0 | AS182: 104 | AT182: 104 | AU182: 165798.12 | AV182: 34.23 | AW182: 91646.44 | AX182: 18.92 | AY182: 257444.56 | AZ182: 53.15 | BA182: 31369.93 | BB182: 6.44 | BC182: 40601.99 | BD182: 8.34 | BE182: 71971.92 | BF182: 14.78 | BG182: 134428.19 | BH182: 51044.45 | BI182: 185472.64 | BJ182: 41099 | BK182: 8.49 | BL182: 32970.88 | BM182: 6.81 | BN182: 74069.88 | BO182: 15.3 | BP182: 18249 | BQ182: 3.75 | BR182: 1471.26 | BS182: 0.3 | BT182: 19720.26 | BU182: 4.05 | BV182: 22850 | BW182: 31499.62 | BX182: 54349.63
A183: =IF(A182="",,IF(A182+7<=$C$4,A182+7,"")) -> 45072 | B183: 0 | C183: 0 | D183: 116477.52 | E183: 24.01 | F183: 116477.52 | G183: 24.01 | H183: 0 | I183: 0 | J183: 366671.97 | K183: 75.38 | L183: 366671.97 | M183: 75.38 | N183: 0 | O183: -250194.44 | P183: -250194.44 | Q183: 0 | R183: 0 | S183: 19958.14 | T183: 4.12 | U183: 19958.14 | V183: 4.12 | W183: 0 | X183: 0 | Y183: 32768.24 | Z183: 6.74 | AA183: 32768.24 | AB183: 6.74 | AC183: 0 | AD183: -12810.1 | AE183: -12810.1 | AF183: 0 | AG183: 0 | AH183: 330 | AI183: 0.07 | AJ183: 330 | AK183: 0.07 | AL183: 0 | AM183: 0 | AN183: 227 | AO183: 0.05 | AP183: 227 | AQ183: 0.05 | AR183: 0 | AS183: 103 | AT183: 103 | AU183: 171464.94 | AV183: 35.36 | AW183: 100042.95 | AX183: 20.63 | AY183: 271507.89 | AZ183: 55.99 | BA183: 29908.63 | BB183: 6.15 | BC183: 36213.53 | BD183: 7.45 | BE183: 66122.16 | BF183: 13.6 | BG183: 141556.31 | BH183: 63829.42 | BI183: 205385.72 | BJ183: 42689 | BK183: 8.8 | BL183: 33972.01 | BM183: 7.01 | BN183: 76661.01 | BO183: 15.81 | BP183: 18360 | BQ183: 3.77 | BR183: 2253.57 | BS183: 0.46 | BT183: 20613.57 | BU183: 4.23 | BV183: 24329 | BW183: 31718.44 | BX183: 56047.44
A184: =IF(A183="",,IF(A183+7<=$C$4,A183+7,"")) -> 45079 | B184: 0 | C184: 0 | D184: 129674.06 | E184: 25.63 | F184: 129674.06 | G184: 25.63 | H184: 0 | I184: 0 | J184: 375865.15 | K184: 74.08 | L184: 375865.15 | M184: 74.08 | N184: 0 | O184: -246191.09 | P184: -246191.09 | Q184: 0 | R184: 0 | S184: 19749.59 | T184: 3.9 | U184: 19749.59 | V184: 3.9 | W184: 0 | X184: 0 | Y184: 43862.29 | Z184: 8.64 | AA184: 43862.29 | AB184: 8.64 | AC184: 0 | AD184: -24112.7 | AE184: -24112.7 | AF184: 0 | AG184: 0 | AH184: 209 | AI184: 0.04 | AJ184: 209 | AK184: 0.04 | AL184: 0 | AM184: 0 | AN184: 400 | AO184: 0.08 | AP184: 400 | AQ184: 0.08 | AR184: 0 | AS184: -191 | AT184: -191 | AU184: 176280.55 | AV184: 34.85 | AW184: 100124.76 | AX184: 19.79 | AY184: 276405.31 | AZ184: 54.64 | BA184: 30355.7 | BB184: 5.98 | BC184: 36282.8 | BD184: 7.15 | BE184: 66638.5 | BF184: 13.13 | BG184: 145924.84 | BH184: 63841.96 | BI184: 209766.81 | BJ184: 45263 | BK184: 8.95 | BL184: 34577.73 | BM184: 6.84 | BN184: 79840.73 | BO184: 15.79 | BP184: 18520 | BQ184: 3.65 | BR184: 2141.56 | BS184: 0.42 | BT184: 20661.56 | BU184: 4.07 | BV184: 26743 | BW184: 32436.17 | BX184: 59179.16
A185: =IF(A184="",,IF(A184+7<=$C$4,A184+7,"")) -> 45086 | B185: 0 | C185: 0 | D185: 132712.44 | E185: 26.28 | F185: 132712.44 | G185: 26.28 | H185: 0 | I185: 0 | J185: 381217.78 | K185: 75.03 | L185: 381217.78 | M185: 75.03 | N185: 0 | O185: -248505.34 | P185: -248505.34 | Q185: 0 | R185: 0 | S185: 20932.98 | T185: 4.14 | U185: 20932.98 | V185: 4.14 | W185: 0 | X185: 0 | Y185: 39757.06 | Z185: 7.83 | AA185: 39757.06 | AB185: 7.83 | AC185: 0 | AD185: -18824.08 | AE185: -18824.08 | AF185: 0 | AG185: 0 | AH185: 252 | AI185: 0.05 | AJ185: 252 | AK185: 0.05 | AL185: 0 | AM185: 0 | AN185: 400 | AO185: 0.08 | AP185: 400 | AQ185: 0.08 | AR185: 0 | AS185: -148 | AT185: -148 | AU185: 173546.77 | AV185: 34.36 | AW185: 97314.53 | AX185: 19.27 | AY185: 270861.3 | AZ185: 53.63 | BA185: 29040.26 | BB185: 5.72 | BC185: 36604.07 | BD185: 7.21 | BE185: 65644.33 | BF185: 12.93 | BG185: 144506.5 | BH185: 60710.46 | BI185: 205216.98 | BJ185: 45917 | BK185: 9.09 | BL185: 34385.31 | BM185: 6.81 | BN185: 80302.31 | BO185: 15.9 | BP185: 19256 | BQ185: 3.79 | BR185: 1710.99 | BS185: 0.34 | BT185: 20966.99 | BU185: 4.13 | BV185: 26661 | BW185: 32674.32 | BX185: 59335.32
A186: =IF(A185="",,IF(A185+7<=$C$4,A185+7,"")) -> 45093 | B186: 0 | C186: 0 | D186: 137866.06 | E186: 27.04 | F186: 137866.06 | G186: 27.04 | H186: 0 | I186: 0 | J186: 391141.78 | K186: 76.64 | L186: 391141.78 | M186: 76.64 | N186: 0 | O186: -253275.72 | P186: -253275.72 | Q186: 0 | R186: 0 | S186: 27076.8 | T186: 5.31 | U186: 27076.8 | V186: 5.31 | W186: 0 | X186: 0 | Y186: 27800.59 | Z186: 5.45 | AA186: 27800.59 | AB186: 5.45 | AC186: 0 | AD186: -723.79 | AE186: -723.79 | AF186: 6 | AG186: 0 | AH186: 34 | AI186: 0.01 | AJ186: 40 | AK186: 0.01 | AL186: 0 | AM186: 0 | AN186: 227 | AO186: 0.04 | AP186: 227 | AQ186: 0.04 | AR186: 6 | AS186: -193 | AT186: -187 | AU186: 168325.46 | AV186: 33.01 | AW186: 95954.32 | AX186: 18.82 | AY186: 264279.78 | AZ186: 51.83 | BA186: 39979.08 | BB186: 7.83 | BC186: 28674.04 | BD186: 5.62 | BE186: 68653.12 | BF186: 13.45 | BG186: 128346.38 | BH186: 67280.28 | BI186: 195626.66 | BJ186: 46439 | BK186: 9.11 | BL186: 34182.81 | BM186: 6.7 | BN186: 80621.81 | BO186: 15.81 | BP186: 21125 | BQ186: 4.14 | BR186: 1427.67 | BS186: 0.28 | BT186: 22552.67 | BU186: 4.42 | BV186: 25314 | BW186: 32755.14 | BX186: 58069.14
A187: =IF(A186="",,IF(A186+7<=$C$4,A186+7,"")) -> 45100 | B187: 0 | C187: 0 | D187: 144520.16 | E187: 27.73 | F187: 144520.16 | G187: 27.73 | H187: 0 | I187: 0 | J187: 407065.61 | K187: 78.01 | L187: 407065.61 | M187: 78.01 | N187: 0 | O187: -262545.47 | P187: -262545.47 | Q187: 0 | R187: 0 | S187: 28172.91 | T187: 5.4 | U187: 28172.91 | V187: 5.4 | W187: 0 | X187: 0 | Y187: 26458.67 | Z187: 5.07 | AA187: 26458.67 | AB187: 5.07 | AC187: 0 | AD187: 1714.24 | AE187: 1714.24 | AF187: 5 | AG187: 0 | AH187: 26 | AI187: 0 | AJ187: 31 | AK187: 0 | AL187: 0 | AM187: 0 | AN187: 227 | AO187: 0.04 | AP187: 227 | AQ187: 0.04 | AR187: 5 | AS187: -201 | AT187: -196 | AU187: 170120.14 | AV187: 32.62 | AW187: 98213.98 | AX187: 18.83 | AY187: 268334.12 | AZ187: 51.45 | BA187: 39187.43 | BB187: 7.51 | BC187: 25735.12 | BD187: 4.93 | BE187: 64922.55 | BF187: 12.44 | BG187: 130932.71 | BH187: 72478.86 | BI187: 203411.58 | BJ187: 46040 | BK187: 8.83 | BL187: 34379.66 | BM187: 6.59 | BN187: 80419.66 | BO187: 15.42 | BP187: 21566 | BQ187: 4.13 | BR187: 1611.62 | BS187: 0.31 | BT187: 23177.62 | BU187: 4.44 | BV187: 24474 | BW187: 32768.04 | BX187: 57242.04
A188: =IF(A187="",,IF(A187+7<=$C$4,A187+7,"")) -> 45107 | B188: 0 | C188: 0 | D188: 125742.14 | E188: 25.11 | F188: 125742.14 | G188: 25.11 | H188: 0 | I188: 0 | J188: 411723.42 | K188: 82.14 | L188: 411723.42 | M188: 82.14 | N188: 0 | O188: -285981.25 | P188: -285981.25 | Q188: 0 | R188: 0 | S188: 26396.37 | T188: 5.27 | U188: 26396.37 | V188: 5.27 | W188: 0 | X188: 0 | Y188: 25184.77 | Z188: 5.02 | AA188: 25184.77 | AB188: 5.02 | AC188: 0 | AD188: 1211.6 | AE188: 1211.6 | AF188: 5 | AG188: 0 | AH188: 39 | AI188: 0.01 | AJ188: 44 | AK188: 0.01 | AL188: 0 | AM188: 0 | AN188: 225 | AO188: 0.04 | AP188: 225 | AQ188: 0.04 | AR188: 5 | AS188: -186 | AT188: -181 | AU188: 160337.93 | AV188: 32.02 | AW188: 107477.84 | AX188: 21.46 | AY188: 267815.77 | AZ188: 53.48 | BA188: 16534.8 | BB188: 3.3 | BC188: 25373.91 | BD188: 5.06 | BE188: 41908.71 | BF188: 8.36 | BG188: 143803.14 | BH188: 82103.94 | BI188: 225907.06 | BJ188: 45980 | BK188: 9.18 | BL188: 34815.99 | BM188: 6.95 | BN188: 80795.99 | BO188: 16.13 | BP188: 20604 | BQ188: 4.11 | BR188: 1660.29 | BS188: 0.33 | BT188: 22264.29 | BU188: 4.44 | BV188: 25376 | BW188: 33155.7 | BX188: 58531.7
... A226: =IF(A225="",,IF(A225+7<=$C$4,A225+7,"")) -> 45373 | B226: 0 | C226: 0 | D226: 144604.39 | E226: 28.82 | F226: 144604.39 | G226: 28.82 | H226: 0 | I226: 0 | J226: 381496.54 | K226: 75.58 | L226: 381496.54 | M226: 75.58 | N226: 0 | O226: -236892.14 | P226: -236892.14 | Q226: 0 | R226: 0 | S226: 37344.13 | T226: 7.44 | U226: 37344.13 | V226: 7.44 | W226: 0 | X226: 0 | Y226: 61357.73 | Z226: 12.16 | AA226: 61357.73 | AB226: 12.16 | AC226: 0 | AD226: -24013.6 | AE226: -24013.6 | AF226: 0 | AG226: 0 | AH226: 2548 | AI226: 0.51 | AJ226: 2548 | AK226: 0.51 | AL226: 0 | AM226: 0 | AN226: 0 | AO226: 0 | AP226: 0 | AQ226: 0 | AR226: 0 | AS226: 2548 | AT226: 2548 | AU226: 165666.85 | AV226: 33.01 | AW226: 85244.38 | AX226: 16.99 | AY226: 250911.23 | AZ226: 50 | BA226: 27743.96 | BB226: 5.5 | BC226: 20563.21 | BD226: 4.07 | BE226: 48307.17 | BF226: 9.57 | BG226: 137922.88 | BH226: 64681.17 | BI226: 202604.06 | BJ226: 33490.9 | BK226: 6.67 | BL226: 32927.85 | BM226: 6.56 | BN226: 66418.75 | BO226: 13.23 | BP226: 11122.33 | BQ226: 2.2 | BR226: 2486.88 | BS226: 0.49 | BT226: 13609.21 | BU226: 2.69 | BV226: 22368.57 | BW226: 30440.97 | BX226: 52809.54
A227: =IF(A226="",,IF(A226+7<=$C$4,A226+7,"")) -> 45380 | B227: #N/A N/A | C227: #N/A N/A | D227: #N/A N/A | E227: #N/A N/A | F227: #N/A N/A | G227: #N/A N/A | H227: #N/A N/A | I227: #N/A N/A | J227: #N/A N/A | K227: #N/A N/A | L227: #N/A N/A | M227: #N/A N/A | N227: #N/A N/A | O227: #N/A N/A | P227: #N/A N/A | Q227: #N/A N/A | R227: #N/A N/A | S227: #N/A N/A | T227: #N/A N/A | U227: #N/A N/A | V227: #N/A N/A | W227: #N/A N/A | X227: #N/A N/A | Y227: #N/A N/A | Z227: #N/A N/A | AA227: #N/A N/A | AB227: #N/A N/A | AC227: #N/A N/A | AD227: #N/A N/A | AE227: #N/A N/A | AF227: #N/A N/A | AG227: #N/A N/A | AH227: #N/A N/A | AI227: #N/A N/A | AJ227: #N/A N/A | AK227: #N/A N/A | AL227: #N/A N/A | AM227: #N/A N/A | AN227: #N/A N/A | AO227: #N/A N/A | AP227: #N/A N/A | AQ227: #N/A N/A | AR227: #N/A N/A | AS227: #N/A N/A | AT227: #N/A N/A | AU227: #N/A N/A | AV227: #N/A N/A | AW227: #N/A N/A | AX227: #N/A N/A | AY227: #N/A N/A | AZ227: #N/A N/A | BA227: #N/A N/A | BB227: #N/A N/A | BC227: #N/A N/A | BD227: #N/A N/A | BE227: #N/A N/A | BF227: #N/A N/A | BG227: #N/A N/A | BH227: #N/A N/A | BI227: #N/A N/A | BJ227: #N/A N/A | BK227: #N/A N/A | BL227: #N/A N/A | BM227: #N/A N/A | BN227: #N/A N/A | BO227: #N/A N/A | BP227: #N/A N/A | BQ227: #N/A N/A | BR227: #N/A N/A | BS227: #N/A N/A | BT227: #N/A N/A | BU227: #N/A N/A | BV227: #N/A N/A | BW227: #N/A N/A | BX227: #N/A N/A
A228: =IF(A227="",,IF(A227+7<=$C$4,A227+7,"")) -> 45387 | B228: 0 | C228: 0 | D228: 157675.59 | E228: 29.85 | F228: 157675.59 | G228: 29.85 | H228: 0 | I228: 0 | J228: 396438.25 | K228: 74.66 | L228: 396438.25 | M228: 74.66 | N228: 0 | O228: -238762.66 | P228: -238762.66 | Q228: 0 | R228: 0 | S228: 38436.84 | T228: 7.27 | U228: 38436.84 | V228: 7.27 | W228: 0 | X228: 0 | Y228: 63801.54 | Z228: 12.02 | AA228: 63801.54 | AB228: 12.02 | AC228: 0 | AD228: -25364.7 | AE228: -25364.7 | AF228: 0 | AG228: 0 | AH228: 2779 | AI228: 0.53 | AJ228: 2779 | AK228: 0.53 | AL228: 0 | AM228: 0 | AN228: 0 | AO228: 0 | AP228: 0 | AQ228: 0 | AR228: 0 | AS228: 2779 | AT228: 2779 | AU228: 174695.02 | AV228: 33.06 | AW228: 87412.26 | AX228: 16.54 | AY228: 262107.28 | AZ228: 49.6 | BA228: 33634.97 | BB228: 6.34 | BC228: 23483.13 | BD228: 4.42 | BE228: 57118.1 | BF228: 10.76 | BG228: 141060.05 | BH228: 63929.13 | BI228: 204989.19 | BJ228: 34030.56 | BK228: 6.44 | BL228: 33355.65 | BM228: 6.31 | BN228: 67386.21 | BO228: 12.75 | BP228: 10965.41 | BQ228: 2.07 | BR228: 2614.69 | BS228: 0.49 | BT228: 13580.1 | BU228: 2.56 | BV228: 23065.15 | BW228: 30740.96 | BX228: 53806.11
A229: =IF(A228="",,IF(A228+7<=$C$4,A228+7,"")) -> 45394 | B229: 0 | C229: 0 | D229: 164827.89 | E229: 30.67 | F229: 164827.89 | G229: 30.67 | H229: 0 | I229: 0 | J229: 396431.52 | K229: 73.29 | L229: 396431.52 | M229: 73.29 | N229: 0 | O229: -231603.64 | P229: -231603.64 | Q229: 0 | R229: 0 | S229: 37285.92 | T229: 6.93 | U229: 37285.92 | V229: 6.93 | W229: 0 | X229: 0 | Y229: 62400.66 | Z229: 11.54 | AA229: 62400.66 | AB229: 11.54 | AC229: 0 | AD229: -25114.74 | AE229: -25114.74 | AF229: 0 | AG229: 0 | AH229: 2436 | AI229: 0.45 | AJ229: 2436 | AK229: 0.45 | AL229: 0 | AM229: 0 | AN229: 0 | AO229: 0 | AP229: 0 | AQ229: 0 | AR229: 0 | AS229: 2436 | AT229: 2436 | AU229: 178747.55 | AV229: 33.24 | AW229: 86046.19 | AX229: 16 | AY229: 264793.74 | AZ229: 49.24 | BA229: 43307.71 | BB229: 8.01 | BC229: 23029.93 | BD229: 4.26 | BE229: 66337.64 | BF229: 12.27 | BG229: 135439.84 | BH229: 63016.26 | BI229: 198456.11 | BJ229: 33983.49 | BK229: 6.32 | BL229: 34371.34 | BM229: 6.39 | BN229: 68354.83 | BO229: 12.71 | BP229: 10435.16 | BQ229: 1.93 | BR229: 5228.38 | BS229: 0.97 | BT229: 15663.54 | BU229: 2.9 | BV229: 23548.33 | BW229: 29142.96 | BX229: 52691.29
A230: =IF(A229="",,IF(A229+7<=$C$4,A229+7,"")) -> 45401 | B230: 0 | C230: 0 | D230: 187249.03 | E230: 33.27 | F230: 187249.03 | G230: 33.27 | H230: 0 | I230: 0 | J230: 399566.95 | K230: 71.46 | L230: 399566.95 | M230: 71.46 | N230: 0 | O230: -212317.91 | P230: -212317.91 | Q230: 0 | R230: 0 | S230: 29698.93 | T230: 5.28 | U230: 29698.93 | V230: 5.28 | W230: 0 | X230: 0 | Y230: 49606.63 | Z230: 8.87 | AA230: 49606.63 | AB230: 8.87 | AC230: 0 | AD230: -19907.7 | AE230: -19907.7 | AF230: 0 | AG230: 0 | AH230: 1828 | AI230: 0.32 | AJ230: 1828 | AK230: 0.32 | AL230: 0 | AM230: 0 | AN230: 87 | AO230: 0.02 | AP230: 87 | AQ230: 0.02 | AR230: 0 | AS230: 1741 | AT230: 1741 | AU230: 182892.35 | AV230: 32.49 | AW230: 92165.28 | AX230: 16.37 | AY230: 275057.63 | AZ230: 48.86 | BA230: 73152.6 | BB230: 13.08 | BC230: 23429.84 | BD230: 4.19 | BE230: 96582.44 | BF230: 17.27 | BG230: 109739.74 | BH230: 68735.44 | BI230: 178475.19 | BJ230: 34458.29 | BK230: 6.12 | BL230: 34605.41 | BM230: 6.15 | BN230: 69063.7 | BO230: 12.27 | BP230: 8015.85 | BQ230: 1.43 | BR230: 5334.43 | BS230: 0.95 | BT230: 13350.28 | BU230: 2.38 | BV230: 26442.44 | BW230: 29270.98 | BX230: 55713.42
A231: =IF(A230="",,IF(A230+7<=$C$4,A230+7,"")) -> 45408 | B231: 0 | C231: 0 | D231: 214452.03 | E231: 35.37 | F231: 214452.03 | G231: 35.37 | H231: 0 | I231: 0 | J231: 439544.34 | K231: 71.92 | L231: 439544.34 | M231: 71.92 | N231: 0 | O231: -225092.31 | P231: -225092.31 | Q231: 0 | R231: 0 | S231: 32876.25 | T231: 5.42 | U231: 32876.25 | V231: 5.42 | W231: 0 | X231: 0 | Y231: 51627.42 | Z231: 8.45 | AA231: 51627.42 | AB231: 8.45 | AC231: 0 | AD231: -18751.17 | AE231: -18751.17 | AF231: 0 | AG231: 0 | AH231: 1912 | AI231: 0.32 | AJ231: 1912 | AK231: 0.32 | AL231: 0 | AM231: 0 | AN231: 0 | AO231: 0 | AP231: 0 | AQ231: 0 | AR231: 0 | AS231: 1912 | AT231: 1912 | AU231: 183259.88 | AV231: 30.23 | AW231: 103389.64 | AX231: 17.06 | AY231: 286649.52 | AZ231: 47.29 | BA231: 72464.7 | BB231: 11.86 | BC231: 26474.91 | BD231: 4.33 | BE231: 98939.61 | BF231: 16.19 | BG231: 110795.17 | BH231: 76914.73 | BI231: 187709.92 | BJ231: 34947.96 | BK231: 5.77 | BL231: 35369.31 | BM231: 5.83 | BN231: 70317.27 | BO231: 11.6 | BP231: 8097.04 | BQ231: 1.32 | BR231: 12973.65 | BS231: 2.12 | BT231: 21070.69 | BU231: 3.44 | BV231: 26850.92 | BW231: 22395.66 | BX231: 49246.59
A232: =IF(A231="",,IF(A231+7<=$C$4,A231+7,"")) -> 45415 | B232: 0 | C232: 0 | D232: 238679.52 | E232: 37.53 | F232: 238679.52 | G232: 37.53 | H232: 0 | I232: 0 | J232: 468255.79 | K232: 73.34 | L232: 468255.79 | M232: 73.34 | N232: 0 | O232: -229576.27 | P232: -229576.27 | Q232: 0 | R232: 0 | S232: 38165.45 | T232: 6 | U232: 38165.45 | V232: 6 | W232: 0 | X232: 0 | Y232: 51113.06 | Z232: 8.01 | AA232: 51113.06 | AB232: 8.01 | AC232: 0 | AD232: -12947.61 | AE232: -12947.61 | AF232: 0 | AG232: 0 | AH232: 1886 | AI232: 0.3 | AJ232: 1886 | AK232: 0.3 | AL232: 0 | AM232: 0 | AN232: 133 | AO232: 0.02 | AP232: 133 | AQ232: 0.02 | AR232: 0 | AS232: 1753 | AT232: 1753 | AU232: 182785.96 | AV232: 28.74 | AW232: 103908.71 | AX232: 16.34 | AY232: 286694.67 | AZ232: 45.08 | BA232: 72101.9 | BB232: 11.29 | BC232: 24790.08 | BD232: 3.88 | BE232: 96891.98 | BF232: 15.17 | BG232: 110684.05 | BH232: 79118.63 | BI232: 189802.69 | BJ232: 34832.05 | BK232: 5.48 | BL232: 35682.17 | BM232: 5.61 | BN232: 70514.22 | BO232: 11.09 | BP232: 9224.04 | BQ232: 1.44 | BR232: 12883.53 | BS232: 2.02 | BT232: 22107.57 | BU232: 3.46 | BV232: 25608.01 | BW232: 22798.64 | BX232: 48406.65
A233: =IF(A232="",,IF(A232+7<=$C$4,A232+7,"")) -> 45422 | B233: 0 | C233: 0 | D233: 245004.03 | E233: 37.99 | F233: 245004.03 | G233: 37.99 | H233: 0 | I233: 0 | J233: 477344.82 | K233: 73.4 | L233: 477344.82 | M233: 73.4 | N233: 0 | O233: -232340.78 | P233: -232340.78 | Q233: 0 | R233: 0 | S233: 39242.62 | T233: 6.09 | U233: 39242.62 | V233: 6.09 | W233: 0 | X233: 0 | Y233: 50934.45 | Z233: 7.83 | AA233: 50934.45 | AB233: 7.83 | AC233: 0 | AD233: -11691.83 | AE233: -11691.83 | AF233: 0 | AG233: 0 | AH233: 1862 | AI233: 0.29 | AJ233: 1862 | AK233: 0.29 | AL233: 0 | AM233: 0 | AN233: 245 | AO233: 0.04 | AP233: 245 | AQ233: 0.04 | AR233: 0 | AS233: 1617 | AT233: 1617 | AU233: 184180.97 | AV233: 28.56 | AW233: 102501.81 | AX233: 15.9 | AY233: 286682.78 | AZ233: 44.46 | BA233: 71632.65 | BB233: 11.02 | BC233: 28040.23 | BD233: 4.31 | BE233: 99672.88 | BF233: 15.33 | BG233: 112548.32 | BH233: 74461.58 | BI233: 187009.91 | BJ233: 35853.77 | BK233: 5.56 | BL233: 36189.29 | BM233: 5.61 | BN233: 72043.06 | BO233: 11.17 | BP233: 9294.67 | BQ233: 1.43 | BR233: 12803.79 | BS233: 1.97 | BT233: 22098.46 | BU233: 3.4 | BV233: 26559.1 | BW233: 23385.5 | BX233: 49944.6
A234: =IF(A233="",,IF(A233+7<=$C$4,A233+7,"")) -> 45429 | B234: 0 | C234: 0 | D234: 251630.58 | E234: 38.11 | F234: 251630.58 | G234: 38.11 | H234: 0 | I234: 0 | J234: 488445.81 | K234: 73.43 | L234: 488445.81 | M234: 73.43 | N234: 0 | O234: -236815.23 | P234: -236815.23 | Q234: 0 | R234: 0 | S234: 39713.02 | T234: 6.01 | U234: 39713.02 | V234: 6.01 | W234: 0 | X234: 0 | Y234: 53833.61 | Z234: 8.09 | AA234: 53833.61 | AB234: 8.09 | AC234: 0 | AD234: -14120.59 | AE234: -14120.59 | AF234: 0 | AG234: 0 | AH234: 1952 | AI234: 0.3 | AJ234: 1952 | AK234: 0.3 | AL234: 0 | AM234: 0 | AN234: 316 | AO234: 0.05 | AP234: 316 | AQ234: 0.05 | AR234: 0 | AS234: 1636 | AT234: 1636 | AU234: 188398.74 | AV234: 28.53 | AW234: 104301.15 | AX234: 15.79 | AY234: 292699.89 | AZ234: 44.32 | BA234: 74663.39 | BB234: 11.22 | BC234: 26124.91 | BD234: 3.93 | BE234: 100788.3 | BF234: 15.15 | BG234: 113735.34 | BH234: 78176.23 | BI234: 191911.58 | BJ234: 37001.24 | BK234: 5.6 | BL234: 37400.92 | BM234: 5.66 | BN234: 74402.16 | BO234: 11.26 | BP234: 8813.79 | BQ234: 1.33 | BR234: 12964.37 | BS234: 1.95 | BT234: 21778.16 | BU234: 3.28 | BV234: 28187.45 | BW234: 24436.55 | BX234: 52624
A235: =IF(A234="",,IF(A234+7<=$C$4,A234+7,"")) -> 45436 | B235: 0 | C235: 0 | D235: 236574.4 | E235: 36.29 | F235: 236574.4 | G235: 36.29 | H235: 0 | I235: 0 | J235: 491684.95 | K235: 74.8 | L235: 491684.95 | M235: 74.8 | N235: 0 | O235: -255110.53 | P235: -255110.53 | Q235: 0 | R235: 0 | S235: 43733.03 | T235: 6.71 | U235: 43733.03 | V235: 6.71 | W235: 0 | X235: 0 | Y235: 50523.63 | Z235: 7.69 | AA235: 50523.63 | AB235: 7.69 | AC235: 0 | AD235: -6790.6 | AE235: -6790.6 | AF235: 0 | AG235: 0 | AH235: 2035 | AI235: 0.31 | AJ235: 2035 | AK235: 0.31 | AL235: 0 | AM235: 0 | AN235: 243 | AO235: 0.04 | AP235: 243 | AQ235: 0.04 | AR235: 0 | AS235: 1792 | AT235: 1792 | AU235: 189643.26 | AV235: 29.08 | AW235: 106236.27 | AX235: 16.29 | AY235: 295879.53 | AZ235: 45.37 | BA235: 72400.59 | BB235: 11.01 | BC235: 27921.81 | BD235: 4.25 | BE235: 100322.4 | BF235: 15.26 | BG235: 117242.67 | BH235: 78314.46 | BI235: 195557.13 | BJ235: 36150.99 | BK235: 5.54 | BL235: 37674.73 | BM235: 5.78 | BN235: 73825.72 | BO235: 11.32 | BP235: 9258.03 | BQ235: 1.41 | BR235: 5286.95 | BS235: 0.8 | BT235: 14544.98 | BU235: 2.21 | BV235: 26892.96 | BW235: 32387.78 | BX235: 59280.74
A236: =IF(A235="",,IF(A235+7<=$C$4,A235+7,"")) -> 45443 | B236: 0 | C236: 0 | D236: 237453.7 | E236: 35.93 | F236: 237453.7 | G236: 35.93 | H236: 0 | I236: 0 | J236: 497075.44 | K236: 74.59 | L236: 497075.44 | M236: 74.59 | N236: 0 | O236: -259621.73 | P236: -259621.73 | Q236: 0 | R236: 0 | S236: 43588.3 | T236: 6.59 | U236: 43588.3 | V236: 6.59 | W236: 0 | X236: 0 | Y236: 51706.57 | Z236: 7.76 | AA236: 51706.57 | AB236: 7.76 | AC236: 0 | AD236: -8118.27 | AE236: -8118.27 | AF236: 0 | AG236: 0 | AH236: 2061 | AI236: 0.31 | AJ236: 2061 | AK236: 0.31 | AL236: 0 | AM236: 0 | AN236: 76 | AO236: 0.01 | AP236: 76 | AQ236: 0.01 | AR236: 0 | AS236: 1985 | AT236: 1985 | AU236: 191031.88 | AV236: 28.9 | AW236: 109310.22 | AX236: 16.54 | AY236: 300342.1 | AZ236: 45.44 | BA236: 72404.95 | BB236: 10.86 | BC236: 30526.06 | BD236: 4.58 | BE236: 102931.01 | BF236: 15.44 | BG236: 118626.92 | BH236: 78784.16 | BI236: 197411.09 | BJ236: 39232.14 | BK236: 5.94 | BL236: 38296.08 | BM236: 5.79 | BN236: 77528.22 | BO236: 11.73 | BP236: 9328.73 | BQ236: 1.4 | BR236: 5339.59 | BS236: 0.8 | BT236: 14668.32 | BU236: 2.2 | BV236: 29903.41 | BW236: 32956.49 | BX236: 62859.9
A237: =IF(A236="",,IF(A236+7<=$C$4,A236+7,"")) -> 45450 | B237: 0 | C237: 0 | D237: 242197.62 | E237: 36.2 | F237: 242197.62 | G237: 36.2 | H237: 0 | I237: 0 | J237: 505971.99 | K237: 75.12 | L237: 505971.99 | M237: 75.12 | N237: 0 | O237: -263774.38 | P237: -263774.38 | Q237: 0 | R237: 0 | S237: 41458.69 | T237: 6.2 | U237: 41458.69 | V237: 6.2 | W237: 0 | X237: 0 | Y237: 51348.73 | Z237: 7.62 | AA237: 51348.73 | AB237: 7.62 | AC237: 0 | AD237: -9890.04 | AE237: -9890.04 | AF237: 0 | AG237: 0 | AH237: 2202 | AI237: 0.33 | AJ237: 2202 | AK237: 0.33 | AL237: 0 | AM237: 0 | AN237: 76 | AO237: 0.01 | AP237: 76 | AQ237: 0.01 | AR237: 0 | AS237: 2126 | AT237: 2126 | AU237: 194412.91 | AV237: 29.06 | AW237: 108552.02 | AX237: 16.22 | AY237: 302964.93 | AZ237: 45.28 | BA237: 73486 | BB237: 10.91 | BC237: 29892.9 | BD237: 4.44 | BE237: 103378.9 | BF237: 15.35 | BG237: 120926.91 | BH237: 78659.13 | BI237: 199586.03 | BJ237: 41552.47 | BK237: 6.21 | BL237: 38695.68 | BM237: 5.78 | BN237: 80248.15 | BO237: 11.99 | BP237: 7313.66 | BQ237: 1.09 | BR237: 5425.28 | BS237: 0.81 | BT237: 12738.94 | BU237: 1.9 | BV237: 34238.81 | BW237: 33270.4 | BX237: 67509.21
A238: =IF(A237="",,IF(A237+7<=$C$4,A237+7,"")) -> 45457 | B238: 0 | C238: 0 | D238: 259407.15 | E238: 37.43 | F238: 259407.15 | G238: 37.43 | H238: 0 | I238: 0 | J238: 522208.36 | K238: 75.4 | L238: 522208.36 | M238: 75.4 | N238: 0 | O238: -262801.22 | P238: -262801.22 | Q238: 0 | R238: 0 | S238: 38103.79 | T238: 5.5 | U238: 38103.79 | V238: 5.5 | W238: 0 | X238: 0 | Y238: 51721.25 | Z238: 7.47 | AA238: 51721.25 | AB238: 7.47 | AC238: 0 | AD238: -13617.46 | AE238: -13617.46 | AF238: 0 | AG238: 0 | AH238: 2252 | AI238: 0.32 | AJ238: 2252 | AK238: 0.32 | AL238: 0 | AM238: 0 | AN238: 76 | AO238: 0.01 | AP238: 76 | AQ238: 0.01 | AR238: 0 | AS238: 2176 | AT238: 2176 | AU238: 200393.67 | AV238: 28.91 | AW238: 112313.55 | AX238: 16.2 | AY238: 312707.22 | AZ238: 45.11 | BA238: 74008.11 | BB238: 10.69 | BC238: 32233.23 | BD238: 4.65 | BE238: 106241.34 | BF238: 15.34 | BG238: 126385.56 | BH238: 80080.31 | BI238: 206465.88 | BJ238: 42008.75 | BK238: 6.06 | BL238: 38647.12 | BM238: 5.58 | BN238: 80655.87 | BO238: 11.64 | BP238: 7269.91 | BQ238: 1.05 | BR238: 5044.37 | BS238: 0.73 | BT238: 12314.28 | BU238: 1.78 | BV238: 34738.84 | BW238: 33602.75 | BX238: 68341.59
A239: =IF(A238="",,IF(A238+7<=$C$4,A238+7,"")) -> 45464 | B239: 0 | C239: 0 | D239: 273714.93 | E239: 38.96 | F239: 273714.93 | G239: 38.96 | H239: 0 | I239: 0 | J239: 545160.56 | K239: 77.08 | L239: 545160.56 | M239: 77.08 | N239: 0 | O239: -271445.63 | P239: -271445.63 | Q239: 0 | R239: 0 | S239: 31730.79 | T239: 4.52 | U239: 31730.79 | V239: 4.52 | W239: 0 | X239: 0 | Y239: 49830.55 | Z239: 7.05 | AA239: 49830.55 | AB239: 7.05 | AC239: 0 | AD239: -18099.76 | AE239: -18099.76 | AF239: 0 | AG239: 0 | AH239: 2247 | AI239: 0.32 | AJ239: 2247 | AK239: 0.32 | AL239: 0 | AM239: 0 | AN239: 0 | AO239: 0 | AP239: 0 | AQ239: 0 | AR239: 0 | AS239: 2247 | AT239: 2247 | AU239: 199556.63 | AV239: 28.41 | AW239: 115063.2 | AX239: 16.38 | AY239: 314619.83 | AZ239: 44.79 | BA239: 70995.96 | BB239: 10.04 | BC239: 31346.07 | BD239: 4.43 | BE239: 102342.03 | BF239: 14.47 | BG239: 128560.66 | BH239: 83717.13 | BI239: 212277.81 | BJ239: 42859.57 | BK239: 6.1 | BL239: 37323.77 | BM239: 5.31 | BN239: 80183.34 | BO239: 11.41 | BP239: 6611.88 | BQ239: 0.93 | BR239: 3343.79 | BS239: 0.47 | BT239: 9955.67 | BU239: 1.4 | BV239: 36247.69 | BW239: 33979.98 | BX239: 70227.67
... A281: =IF(A280="",,IF(A280+7<=$C$4,A280+7,"")) -> 45758 | B281: 0 | C281: 0 | D281: 200380.31 | E281: 31.61 | F281: 200380.31 | G281: 31.61 | H281: 0 | I281: 0 | J281: 529468.28 | K281: 83.51 | L281: 529468.28 | M281: 83.51 | N281: 0 | O281: -329087.94 | P281: -329087.94 | Q281: 0 | R281: 0 | S281: 53161.41 | T281: 8.38 | U281: 53161.41 | V281: 8.38 | W281: 0 | X281: 0 | Y281: 51557.55 | Z281: 8.13 | AA281: 51557.55 | AB281: 8.13 | AC281: 0 | AD281: 1603.86 | AE281: 1603.86 | AF281: 0 | AG281: 0 | AH281: 2297 | AI281: 0.36 | AJ281: 2297 | AK281: 0.36 | AL281: 0 | AM281: 0 | AN281: 535 | AO281: 0.08 | AP281: 535 | AQ281: 0.08 | AR281: 0 | AS281: 1762 | AT281: 1762 | AU281: 197711.01 | AV281: 31.18 | AW281: 98989.72 | AX281: 15.61 | AY281: 296700.73 | AZ281: 46.79 | BA281: 34373.83 | BB281: 5.42 | BC281: 16188.1 | BD281: 2.55 | BE281: 50561.93 | BF281: 7.97 | BG281: 163337.19 | BH281: 82801.62 | BI281: 246138.78 | BJ281: 46856.63 | BK281: 7.39 | BL281: 34704.59 | BM281: 5.47 | BN281: 81561.22 | BO281: 12.86 | BP281: 408 | BQ281: 0.06 | BR281: 1565.39 | BS281: 0.25 | BT281: 1973.39 | BU281: 0.31 | BV281: 46448.63 | BW281: 33139.2 | BX281: 79587.83
A282: =IF(A281="",,IF(A281+7<=$C$4,A281+7,"")) -> 45765 | B282: #N/A N/A | C282: #N/A N/A | D282: #N/A N/A | E282: #N/A N/A | F282: #N/A N/A | G282: #N/A N/A | H282: #N/A N/A | I282: #N/A N/A | J282: #N/A N/A | K282: #N/A N/A | L282: #N/A N/A | M282: #N/A N/A | N282: #N/A N/A | O282: #N/A N/A | P282: #N/A N/A | Q282: #N/A N/A | R282: #N/A N/A | S282: #N/A N/A | T282: #N/A N/A | U282: #N/A N/A | V282: #N/A N/A | W282: #N/A N/A | X282: #N/A N/A | Y282: #N/A N/A | Z282: #N/A N/A | AA282: #N/A N/A | AB282: #N/A N/A | AC282: #N/A N/A | AD282: #N/A N/A | AE282: #N/A N/A | AF282: #N/A N/A | AG282: #N/A N/A | AH282: #N/A N/A | AI282: #N/A N/A | AJ282: #N/A N/A | AK282: #N/A N/A | AL282: #N/A N/A | AM282: #N/A N/A | AN282: #N/A N/A | AO282: #N/A N/A | AP282: #N/A N/A | AQ282: #N/A N/A | AR282: #N/A N/A | AS282: #N/A N/A | AT282: #N/A N/A | AU282: #N/A N/A | AV282: #N/A N/A | AW282: #N/A N/A | AX282: #N/A N/A | AY282: #N/A N/A | AZ282: #N/A N/A | BA282: #N/A N/A | BB282: #N/A N/A | BC282: #N/A N/A | BD282: #N/A N/A | BE282: #N/A N/A | BF282: #N/A N/A | BG282: #N/A N/A | BH282: #N/A N/A | BI282: #N/A N/A | BJ282: #N/A N/A | BK282: #N/A N/A | BL282: #N/A N/A | BM282: #N/A N/A | BN282: #N/A N/A | BO282: #N/A N/A | BP282: #N/A N/A | BQ282: #N/A N/A | BR282: #N/A N/A | BS282: #N/A N/A | BT282: #N/A N/A | BU282: #N/A N/A | BV282: #N/A N/A | BW282: #N/A N/A | BX282: #N/A N/A
A283: =IF(A282="",,IF(A282+7<=$C$4,A282+7,"")) -> 45772 | B283: 0 | C283: 0 | D283: 206431.52 | E283: 31.58 | F283: 206431.52 | G283: 31.58 | H283: 0 | I283: 0 | J283: 549457.23 | K283: 84.06 | L283: 549457.23 | M283: 84.06 | N283: 0 | O283: -343025.75 | P283: -343025.75 | Q283: 0 | R283: 0 | S283: 53661.31 | T283: 8.21 | U283: 53661.31 | V283: 8.21 | W283: 0 | X283: 0 | Y283: 51042.13 | Z283: 7.81 | AA283: 51042.13 | AB283: 7.81 | AC283: 0 | AD283: 2619.18 | AE283: 2619.18 | AF283: 0 | AG283: 0 | AH283: 2278 | AI283: 0.35 | AJ283: 2278 | AK283: 0.35 | AL283: 0 | AM283: 0 | AN283: 410 | AO283: 0.06 | AP283: 410 | AQ283: 0.06 | AR283: 0 | AS283: 1868 | AT283: 1868 | AU283: 206203.72 | AV283: 31.55 | AW283: 102311.75 | AX283: 15.65 | AY283: 308515.47 | AZ283: 47.2 | BA283: 34877.6 | BB283: 5.34 | BC283: 16402.33 | BD283: 2.51 | BE283: 51279.93 | BF283: 7.85 | BG283: 171326.13 | BH283: 85909.42 | BI283: 257235.53 | BJ283: 46763.61 | BK283: 7.15 | BL283: 36031.21 | BM283: 5.51 | BN283: 82794.82 | BO283: 12.66 | BP283: 401 | BQ283: 0.06 | BR283: 1067.82 | BS283: 0.16 | BT283: 1468.82 | BU283: 0.22 | BV283: 46362.61 | BW283: 34963.39 | BX283: 81326
A284: =IF(A283="",,IF(A283+7<=$C$4,A283+7,"")) -> 45779 | B284: 0 | C284: 0 | D284: 205874.3 | E284: 31.8 | F284: 205874.3 | G284: 31.8 | H284: 0 | I284: 0 | J284: 546020.23 | K284: 84.33 | L284: 546020.23 | M284: 84.33 | N284: 0 | O284: -340145.94 | P284: -340145.94 | Q284: 0 | R284: 0 | S284: 59278.02 | T284: 9.15 | U284: 59278.02 | V284: 9.15 | W284: 0 | X284: 0 | Y284: 51797.9 | Z284: 8 | AA284: 51797.9 | AB284: 8 | AC284: 0 | AD284: 7480.12 | AE284: 7480.12 | AF284: 0 | AG284: 0 | AH284: 2287 | AI284: 0.35 | AJ284: 2287 | AK284: 0.35 | AL284: 0 | AM284: 0 | AN284: 275 | AO284: 0.04 | AP284: 275 | AQ284: 0.04 | AR284: 0 | AS284: 2012 | AT284: 2012 | AU284: 205650.12 | AV284: 31.76 | AW284: 92344.57 | AX284: 14.26 | AY284: 297994.69 | AZ284: 46.02 | BA284: 33247.16 | BB284: 5.13 | BC284: 14695.66 | BD284: 2.27 | BE284: 47942.82 | BF284: 7.4 | BG284: 172402.97 | BH284: 77648.91 | BI284: 250051.88 | BJ284: 45824.71 | BK284: 7.08 | BL284: 36291.2 | BM284: 5.6 | BN284: 82115.91 | BO284: 12.68 | BP284: 395 | BQ284: 0.06 | BR284: 1082.95 | BS284: 0.17 | BT284: 1477.95 | BU284: 0.23 | BV284: 45429.71 | BW284: 35208.25 | BX284: 80637.95
A285: =IF(A284="",,IF(A284+7<=$C$4,A284+7,"")) -> 45786 | B285: 0 | C285: 0 | D285: 207595.77 | E285: 31.69 | F285: 207595.77 | G285: 31.69 | H285: 0 | I285: 0 | J285: 554502.12 | K285: 84.67 | L285: 554502.12 | M285: 84.67 | N285: 0 | O285: -346906.38 | P285: -346906.38 | Q285: 0 | R285: 0 | S285: 57297.39 | T285: 8.75 | U285: 57297.39 | V285: 8.75 | W285: 0 | X285: 0 | Y285: 48205.38 | Z285: 7.36 | AA285: 48205.38 | AB285: 7.36 | AC285: 0 | AD285: 9092.01 | AE285: 9092.01 | AF285: 0 | AG285: 0 | AH285: 2217 | AI285: 0.34 | AJ285: 2217 | AK285: 0.34 | AL285: 0 | AM285: 0 | AN285: 253 | AO285: 0.04 | AP285: 253 | AQ285: 0.04 | AR285: 0 | AS285: 1964 | AT285: 1964 | AU285: 208084.19 | AV285: 31.77 | AW285: 96828.44 | AX285: 14.78 | AY285: 304912.63 | AZ285: 46.55 | BA285: 34509.79 | BB285: 5.27 | BC285: 15879.81 | BD285: 2.42 | BE285: 50389.6 | BF285: 7.69 | BG285: 173574.41 | BH285: 80948.63 | BI285: 254523.03 | BJ285: 45684.23 | BK285: 6.98 | BL285: 37249.66 | BM285: 5.69 | BN285: 82933.89 | BO285: 12.67 | BP285: 458 | BQ285: 0.07 | BR285: 1091.58 | BS285: 0.17 | BT285: 1549.58 | BU285: 0.24 | BV285: 45226.23 | BW285: 36158.08 | BX285: 81384.31
A286: =IF(A285="",,IF(A285+7<=$C$4,A285+7,"")) -> 45793 | B286: 0 | C286: 0 | D286: 205361.88 | E286: 31.23 | F286: 205361.88 | G286: 31.23 | H286: 0 | I286: 0 | J286: 564522.49 | K286: 85.81 | L286: 564522.49 | M286: 85.81 | N286: 0 | O286: -359160.63 | P286: -359160.63 | Q286: 0 | R286: 0 | S286: 57658.3 | T286: 8.76 | U286: 57658.3 | V286: 8.76 | W286: 0 | X286: 0 | Y286: 40827.56 | Z286: 6.21 | AA286: 40827.56 | AB286: 6.21 | AC286: 0 | AD286: 16830.74 | AE286: 16830.74 | AF286: 0 | AG286: 0 | AH286: 2248 | AI286: 0.34 | AJ286: 2248 | AK286: 0.34 | AL286: 0 | AM286: 0 | AN286: 331 | AO286: 0.05 | AP286: 331 | AQ286: 0.05 | AR286: 0 | AS286: 1917 | AT286: 1917 | AU286: 208886.75 | AV286: 31.75 | AW286: 101652.66 | AX286: 15.45 | AY286: 310539.41 | AZ286: 47.2 | BA286: 33797.57 | BB286: 5.14 | BC286: 16779.46 | BD286: 2.55 | BE286: 50577.03 | BF286: 7.69 | BG286: 175089.19 | BH286: 84873.2 | BI286: 259962.38 | BJ286: 44652.51 | BK286: 6.79 | BL286: 37393.36 | BM286: 5.68 | BN286: 82045.87 | BO286: 12.47 | BP286: 452 | BQ286: 0.07 | BR286: 1145.38 | BS286: 0.17 | BT286: 1597.38 | BU286: 0.24 | BV286: 44200.51 | BW286: 36247.98 | BX286: 80448.48
A287: =IF(A286="",,IF(A286+7<=$C$4,A286+7,"")) -> 45800 | B287: 0 | C287: 0 | D287: 195543.35 | E287: 29.86 | F287: 195543.35 | G287: 29.86 | H287: 0 | I287: 0 | J287: 564966.57 | K287: 86.29 | L287: 564966.57 | M287: 86.29 | N287: 0 | O287: -369423.22 | P287: -369423.22 | Q287: 0 | R287: 0 | S287: 58018.44 | T287: 8.86 | U287: 58018.44 | V287: 8.86 | W287: 0 | X287: 0 | Y287: 40158.68 | Z287: 6.13 | AA287: 40158.68 | AB287: 6.13 | AC287: 0 | AD287: 17859.76 | AE287: 17859.76 | AF287: 0 | AG287: 0 | AH287: 2294 | AI287: 0.35 | AJ287: 2294 | AK287: 0.35 | AL287: 0 | AM287: 0 | AN287: 493 | AO287: 0.08 | AP287: 493 | AQ287: 0.08 | AR287: 0 | AS287: 1801 | AT287: 1801 | AU287: 212429.78 | AV287: 32.45 | AW287: 103329.9 | AX287: 15.78 | AY287: 315759.68 | AZ287: 48.23 | BA287: 32144.8 | BB287: 4.91 | BC287: 15371.79 | BD287: 2.35 | BE287: 47516.59 | BF287: 7.26 | BG287: 180284.98 | BH287: 87958.11 | BI287: 268243.09 | BJ287: 44619.57 | BK287: 6.82 | BL287: 38490.78 | BM287: 5.88 | BN287: 83110.35 | BO287: 12.7 | BP287: 472 | BQ287: 0.07 | BR287: 1118.98 | BS287: 0.17 | BT287: 1590.98 | BU287: 0.24 | BV287: 44147.57 | BW287: 37371.8 | BX287: 81519.38
A288: =IF(A287="",,IF(A287+7<=$C$4,A287+7,"")) -> 45807 | B288: 0 | C288: 0 | D288: 202156.4 | E288: 30.39 | F288: 202156.4 | G288: 30.39 | H288: 0 | I288: 0 | J288: 576804.2 | K288: 86.75 | L288: 576804.2 | M288: 86.75 | N288: 0 | O288: -374647.78 | P288: -374647.78 | Q288: 0 | R288: 0 | S288: 57820.12 | T288: 8.7 | U288: 57820.12 | V288: 8.7 | W288: 0 | X288: 0 | Y288: 40900.27 | Z288: 6.15 | AA288: 40900.27 | AB288: 6.15 | AC288: 0 | AD288: 16919.85 | AE288: 16919.85 | AF288: 0 | AG288: 0 | AH288: 2317 | AI288: 0.35 | AJ288: 2317 | AK288: 0.35 | AL288: 0 | AM288: 0 | AN288: 505 | AO288: 0.08 | AP288: 505 | AQ288: 0.08 | AR288: 0 | AS288: 1812 | AT288: 1812 | AU288: 212929.92 | AV288: 32.03 | AW288: 106221.84 | AX288: 15.98 | AY288: 319151.76 | AZ288: 48.01 | BA288: 29650.64 | BB288: 4.46 | BC288: 15293.78 | BD288: 2.3 | BE288: 44944.42 | BF288: 6.76 | BG288: 183279.28 | BH288: 90928.06 | BI288: 274207.31 | BJ288: 44849.22 | BK288: 6.75 | BL288: 38572 | BM288: 5.8 | BN288: 83421.22 | BO288: 12.55 | BP288: 589.82 | BQ288: 0.09 | BR288: 1128.77 | BS288: 0.17 | BT288: 1718.59 | BU288: 0.26 | BV288: 44259.4 | BW288: 37443.23 | BX288: 81702.63
A289: =IF(A288="",,IF(A288+7<=$C$4,A288+7,"")) -> 45814 | B289: 0 | C289: 0 | D289: 202979.28 | E289: 30.19 | F289: 202979.28 | G289: 30.19 | H289: 0 | I289: 0 | J289: 583209.54 | K289: 86.77 | L289: 583209.54 | M289: 86.77 | N289: 0 | O289: -380230.28 | P289: -380230.28 | Q289: 0 | R289: 0 | S289: 60792.91 | T289: 9.04 | U289: 60792.91 | V289: 9.04 | W289: 0 | X289: 0 | Y289: 38133.99 | Z289: 5.67 | AA289: 38133.99 | AB289: 5.67 | AC289: 0 | AD289: 22658.92 | AE289: 22658.92 | AF289: 0 | AG289: 0 | AH289: 2340 | AI289: 0.35 | AJ289: 2340 | AK289: 0.35 | AL289: 0 | AM289: 0 | AN289: 512 | AO289: 0.08 | AP289: 512 | AQ289: 0.08 | AR289: 0 | AS289: 1828 | AT289: 1828 | AU289: 213988.19 | AV289: 31.84 | AW289: 107460.89 | AX289: 15.99 | AY289: 321449.08 | AZ289: 47.83 | BA289: 31460.24 | BB289: 4.68 | BC289: 16421.65 | BD289: 2.44 | BE289: 47881.89 | BF289: 7.12 | BG289: 182527.95 | BH289: 91039.24 | BI289: 273567.19 | BJ289: 45152.33 | BK289: 6.72 | BL289: 39441.61 | BM289: 5.87 | BN289: 84593.94 | BO289: 12.59 | BP289: 1370.55 | BQ289: 0.2 | BR289: 1079.24 | BS289: 0.16 | BT289: 2449.79 | BU289: 0.36 | BV289: 43781.78 | BW289: 38362.37 | BX289: 82144.15
A290: =IF(A289="",,IF(A289+7<=$C$4,A289+7,"")) -> 45821 | B290: 0 | C290: 0 | D290: 202637.64 | E290: 29.76 | F290: 202637.64 | G290: 29.76 | H290: 0 | I290: 0 | J290: 589072.14 | K290: 86.49 | L290: 589072.14 | M290: 86.49 | N290: 0 | O290: -386434.5 | P290: -386434.5 | Q290: 0 | R290: 0 | S290: 66671.77 | T290: 9.79 | U290: 66671.77 | V290: 9.79 | W290: 0 | X290: 0 | Y290: 38586.86 | Z290: 5.67 | AA290: 38586.86 | AB290: 5.67 | AC290: 0 | AD290: 28084.91 | AE290: 28084.91 | AF290: 0 | AG290: 0 | AH290: 2358 | AI290: 0.35 | AJ290: 2358 | AK290: 0.35 | AL290: 0 | AM290: 0 | AN290: 465 | AO290: 0.07 | AP290: 465 | AQ290: 0.07 | AR290: 0 | AS290: 1893 | AT290: 1893 | AU290: 221168.73 | AV290: 32.48 | AW290: 100336.46 | AX290: 14.74 | AY290: 321505.19 | AZ290: 47.22 | BA290: 30867.67 | BB290: 4.53 | BC290: 16902.78 | BD290: 2.48 | BE290: 47770.45 | BF290: 7.01 | BG290: 190301.06 | BH290: 83433.68 | BI290: 273734.75 | BJ290: 45304.11 | BK290: 6.65 | BL290: 42440.59 | BM290: 6.23 | BN290: 87744.7 | BO290: 12.88 | BP290: 1379.99 | BQ290: 0.2 | BR290: 3792.86 | BS290: 0.56 | BT290: 5172.85 | BU290: 0.76 | BV290: 43924.12 | BW290: 38647.73 | BX290: 82571.85
A291: =IF(A290="",,IF(A290+7<=$C$4,A290+7,"")) -> 45828 | B291: 0 | C291: 0 | D291: 208803.33 | E291: 30.28 | F291: 208803.33 | G291: 30.28 | H291: 0 | I291: 0 | J291: 602689.77 | K291: 87.43 | L291: 602689.77 | M291: 87.43 | N291: 0 | O291: -393886.44 | P291: -393886.44 | Q291: 0 | R291: 0 | S291: 60294.89 | T291: 8.75 | U291: 60294.89 | V291: 8.75 | W291: 0 | X291: 0 | Y291: 37256.69 | Z291: 5.4 | AA291: 37256.69 | AB291: 5.4 | AC291: 0 | AD291: 23038.2 | AE291: 23038.2 | AF291: 0 | AG291: 0 | AH291: 2392 | AI291: 0.35 | AJ291: 2392 | AK291: 0.35 | AL291: 0 | AM291: 0 | AN291: 317 | AO291: 0.05 | AP291: 317 | AQ291: 0.05 | AR291: 0 | AS291: 2075 | AT291: 2075 | AU291: 230020.37 | AV291: 33.37 | AW291: 104787.64 | AX291: 15.2 | AY291: 334808.01 | AZ291: 48.57 | BA291: 30572.55 | BB291: 4.43 | BC291: 14561.84 | BD291: 2.11 | BE291: 45134.39 | BF291: 6.54 | BG291: 199447.83 | BH291: 90225.8 | BI291: 289673.63 | BJ291: 46703.05 | BK291: 6.77 | BL291: 36385.3 | BM291: 5.28 | BN291: 83088.35 | BO291: 12.05 | BP291: 1502.35 | BQ291: 0.22 | BR291: 2478.38 | BS291: 0.36 | BT291: 3980.73 | BU291: 0.58 | BV291: 45200.7 | BW291: 33906.92 | BX291: 79107.63
A292: =IF(A291="",,IF(A291+7<=$C$4,A291+7,"")) -> 45835 | B292: 0 | C292: 0 | D292: 212367.37 | E292: 30.44 | F292: 212367.37 | G292: 30.44 | H292: 0 | I292: 0 | J292: 616081.93 | K292: 88.31 | L292: 616081.93 | M292: 88.31 | N292: 0 | O292: -403714.56 | P292: -403714.56 | Q292: 0 | R292: 0 | S292: 50780.62 | T292: 7.28 | U292: 50780.62 | V292: 7.28 | W292: 0 | X292: 0 | Y292: 35133.81 | Z292: 5.04 | AA292: 35133.81 | AB292: 5.04 | AC292: 0 | AD292: 15646.81 | AE292: 15646.81 | AF292: 0 | AG292: 0 | AH292: 2483 | AI292: 0.36 | AJ292: 2483 | AK292: 0.36 | AL292: 0 | AM292: 0 | AN292: 338 | AO292: 0.05 | AP292: 338 | AQ292: 0.05 | AR292: 0 | AS292: 2145 | AT292: 2145 | AU292: 236091.52 | AV292: 33.85 | AW292: 110562.36 | AX292: 15.85 | AY292: 346653.88 | AZ292: 49.7 | BA292: 31497.32 | BB292: 4.52 | BC292: 11873.09 | BD292: 1.7 | BE292: 43370.41 | BF292: 6.22 | BG292: 204594.19 | BH292: 98689.27 | BI292: 303283.47 | BJ292: 47031.53 | BK292: 6.74 | BL292: 38217.18 | BM292: 5.48 | BN292: 85248.71 | BO292: 12.22 | BP292: 1444 | BQ292: 0.21 | BR292: 1156.43 | BS292: 0.17 | BT292: 2600.43 | BU292: 0.38 | BV292: 45587.53 | BW292: 37060.75 | BX292: 82648.28
A293: =IF(A292="",,IF(A292+7<=$C$4,A292+7,"")) -> 45842 | B293: 0 | C293: 0 | D293: 199274.03 | E293: 29.25 | F293: 199274.03 | G293: 29.25 | H293: 0 | I293: 0 | J293: 601290.81 | K293: 88.15 | L293: 601290.81 | M293: 88.15 | N293: 0 | O293: -402016.78 | P293: -402016.78 | Q293: 0 | R293: 0 | S293: 52809.3 | T293: 7.75 | U293: 52809.3 | V293: 7.75 | W293: 0 | X293: 0 | Y293: 33853.22 | Z293: 4.96 | AA293: 33853.22 | AB293: 4.96 | AC293: 0 | AD293: 18956.08 | AE293: 18956.08 | AF293: 0 | AG293: 0 | AH293: 2464 | AI293: 0.36 | AJ293: 2464 | AK293: 0.36 | AL293: 0 | AM293: 0 | AN293: 351 | AO293: 0.05 | AP293: 351 | AQ293: 0.05 | AR293: 0 | AS293: 2113 | AT293: 2113 | AU293: 232232.18 | AV293: 34.08 | AW293: 108675.32 | AX293: 15.95 | AY293: 340907.5 | AZ293: 50.03 | BA293: 30413.43 | BB293: 4.46 | BC293: 14564.29 | BD293: 2.13 | BE293: 44977.72 | BF293: 6.59 | BG293: 201818.75 | BH293: 94111.03 | BI293: 295929.78 | BJ293: 47531.44 | BK293: 6.98 | BL293: 38372.07 | BM293: 5.63 | BN293: 85903.51 | BO293: 12.61 | BP293: 523 | BQ293: 0.08 | BR293: 1179.59 | BS293: 0.17 | BT293: 1702.59 | BU293: 0.25 | BV293: 47008.44 | BW293: 37192.48 | BX293: 84200.91
A294: =IF(A293="",,IF(A293+7<=$C$4,A293+7,"")) -> 45849 | B294: 0 | C294: 0 | D294: 201049.11 | E294: 29.08 | F294: 201049.11 | G294: 29.08 | H294: 0 | I294: 0 | J294: 609001.08 | K294: 87.95 | L294: 609001.08 | M294: 87.95 | N294: 0 | O294: -407951.94 | P294: -407951.94 | Q294: 0 | R294: 0 | S294: 51136.06 | T294: 7.4 | U294: 51136.06 | V294: 7.4 | W294: 0 | X294: 0 | Y294: 36073.77 | Z294: 5.21 | AA294: 36073.77 | AB294: 5.21 | AC294: 0 | AD294: 15062.29 | AE294: 15062.29 | AF294: 0 | AG294: 0 | AH294: 2499 | AI294: 0.36 | AJ294: 2499 | AK294: 0.36 | AL294: 0 | AM294: 0 | AN294: 221 | AO294: 0.03 | AP294: 221 | AQ294: 0.03 | AR294: 0 | AS294: 2278 | AT294: 2278 | AU294: 238062.44 | AV294: 34.44 | AW294: 110095.64 | AX294: 15.93 | AY294: 348158.08 | AZ294: 50.37 | BA294: 31197.98 | BB294: 4.5 | BC294: 14226.75 | BD294: 2.05 | BE294: 45424.73 | BF294: 6.55 | BG294: 206864.45 | BH294: 95868.89 | BI294: 302733.38 | BJ294: 48324.53 | BK294: 6.99 | BL294: 40081.2 | BM294: 5.8 | BN294: 88405.73 | BO294: 12.79 | BP294: 517 | BQ294: 0.07 | BR294: 1350.4 | BS294: 0.19 | BT294: 1867.4 | BU294: 0.26 | BV294: 47807.53 | BW294: 38730.8 | BX294: 86538.33
... A317: =IF(A316="",,IF(A316+7<=$C$4,A316+7,"")) -> 46010 | B317: 0 | C317: 0 | D317: 165899.39 | E317: 24.96 | F317: 165899.39 | G317: 24.96 | H317: 0 | I317: 0 | J317: 557338.56 | K317: 83.87 | L317: 557338.56 | M317: 83.87 | N317: 0 | O317: -391439.19 | P317: -391439.19 | Q317: 0 | R317: 0 | S317: 144820.45 | T317: 21.79 | U317: 144820.45 | V317: 21.79 | W317: 0 | X317: 0 | Y317: 27033.31 | Z317: 4.07 | AA317: 27033.31 | AB317: 4.07 | AC317: 0 | AD317: 117787.14 | AE317: 117787.14 | AF317: 0 | AG317: 0 | AH317: 2956 | AI317: 0.44 | AJ317: 2956 | AK317: 0.44 | AL317: 0 | AM317: 0 | AN317: 260 | AO317: 0.04 | AP317: 260 | AQ317: 0.04 | AR317: 0 | AS317: 2696 | AT317: 2696 | AU317: 193687.46 | AV317: 29.15 | AW317: 86824.51 | AX317: 13.07 | AY317: 280511.97 | AZ317: 42.22 | BA317: 34135.76 | BB317: 5.14 | BC317: 38433.34 | BD317: 5.78 | BE317: 72569.1 | BF317: 10.92 | BG317: 159551.69 | BH317: 48391.17 | BI317: 207942.88 | BJ317: 34159.04 | BK317: 5.14 | BL317: 36190.27 | BM317: 5.45 | BN317: 70349.31 | BO317: 10.59 | BP317: 6121 | BQ317: 0.92 | BR317: 1217.01 | BS317: 0.18 | BT317: 7338.01 | BU317: 1.1 | BV317: 28038.04 | BW317: 34973.26 | BX317: 63011.3
A318: =IF(A317="",,IF(A317+7<=$C$4,A317+7,"")) -> 46017 | B318: #N/A N/A | C318: #N/A N/A | D318: #N/A N/A | E318: #N/A N/A | F318: #N/A N/A | G318: #N/A N/A | H318: #N/A N/A | I318: #N/A N/A | J318: #N/A N/A | K318: #N/A N/A | L318: #N/A N/A | M318: #N/A N/A | N318: #N/A N/A | O318: #N/A N/A | P318: #N/A N/A | Q318: #N/A N/A | R318: #N/A N/A | S318: #N/A N/A | T318: #N/A N/A | U318: #N/A N/A | V318: #N/A N/A | W318: #N/A N/A | X318: #N/A N/A | Y318: #N/A N/A | Z318: #N/A N/A | AA318: #N/A N/A | AB318: #N/A N/A | AC318: #N/A N/A | AD318: #N/A N/A | AE318: #N/A N/A | AF318: #N/A N/A | AG318: #N/A N/A | AH318: #N/A N/A | AI318: #N/A N/A | AJ318: #N/A N/A | AK318: #N/A N/A | AL318: #N/A N/A | AM318: #N/A N/A | AN318: #N/A N/A | AO318: #N/A N/A | AP318: #N/A N/A | AQ318: #N/A N/A | AR318: #N/A N/A | AS318: #N/A N/A | AT318: #N/A N/A | AU318: #N/A N/A | AV318: #N/A N/A | AW318: #N/A N/A | AX318: #N/A N/A | AY318: #N/A N/A | AZ318: #N/A N/A | BA318: #N/A N/A | BB318: #N/A N/A | BC318: #N/A N/A | BD318: #N/A N/A | BE318: #N/A N/A | BF318: #N/A N/A | BG318: #N/A N/A | BH318: #N/A N/A | BI318: #N/A N/A | BJ318: #N/A N/A | BK318: #N/A N/A | BL318: #N/A N/A | BM318: #N/A N/A | BN318: #N/A N/A | BO318: #N/A N/A | BP318: #N/A N/A | BQ318: #N/A N/A | BR318: #N/A N/A | BS318: #N/A N/A | BT318: #N/A N/A | BU318: #N/A N/A | BV318: #N/A N/A | BW318: #N/A N/A | BX318: #N/A N/A
A319: =IF(A318="",,IF(A318+7<=$C$4,A318+7,"")) -> 46024 | B319: 0 | C319: 0 | D319: 164024.09 | E319: 24.63 | F319: 164024.09 | G319: 24.63 | H319: 0 | I319: 0 | J319: 553500.44 | K319: 83.07 | L319: 553500.44 | M319: 83.07 | N319: 0 | O319: -389476.34 | P319: -389476.34 | Q319: 0 | R319: 0 | S319: 143697.4 | T319: 21.57 | U319: 143697.4 | V319: 21.57 | W319: 0 | X319: 0 | Y319: 28716.83 | Z319: 4.31 | AA319: 28716.83 | AB319: 4.31 | AC319: 0 | AD319: 114980.58 | AE319: 114980.58 | AF319: 0 | AG319: 0 | AH319: 2825 | AI319: 0.42 | AJ319: 2825 | AK319: 0.42 | AL319: 0 | AM319: 0 | AN319: 255 | AO319: 0.04 | AP319: 255 | AQ319: 0.04 | AR319: 0 | AS319: 2570 | AT319: 2570 | AU319: 203370.14 | AV319: 30.53 | AW319: 90481.01 | AX319: 13.58 | AY319: 293851.15 | AZ319: 44.11 | BA319: 37279.34 | BB319: 5.59 | BC319: 39797.3 | BD319: 5.97 | BE319: 77076.64 | BF319: 11.56 | BG319: 166090.8 | BH319: 50683.71 | BI319: 216774.52 | BJ319: 27591.87 | BK319: 4.14 | BL319: 34193.24 | BM319: 5.13 | BN319: 61785.11 | BO319: 9.27 | BP319: 6117 | BQ319: 0.92 | BR319: 634.81 | BS319: 0.1 | BT319: 6751.81 | BU319: 1.02 | BV319: 21474.87 | BW319: 33558.43 | BX319: 55033.3
A320: =IF(A319="",,IF(A319+7<=$C$4,A319+7,"")) -> 46031 | B320: 0 | C320: 0 | D320: 162085.65 | E320: 24.18 | F320: 162085.65 | G320: 24.18 | H320: 0 | I320: 0 | J320: 551821.3 | K320: 82.41 | L320: 551821.3 | M320: 82.41 | N320: 0 | O320: -389735.66 | P320: -389735.66 | Q320: 0 | R320: 0 | S320: 153080.74 | T320: 22.85 | U320: 153080.74 | V320: 22.85 | W320: 0 | X320: 0 | Y320: 27497.62 | Z320: 4.11 | AA320: 27497.62 | AB320: 4.11 | AC320: 0 | AD320: 125583.12 | AE320: 125583.12 | AF320: 0 | AG320: 0 | AH320: 2861 | AI320: 0.43 | AJ320: 2861 | AK320: 0.43 | AL320: 0 | AM320: 0 | AN320: 234 | AO320: 0.03 | AP320: 234 | AQ320: 0.03 | AR320: 0 | AS320: 2627 | AT320: 2627 | AU320: 202700.8 | AV320: 30.25 | AW320: 86336.8 | AX320: 12.89 | AY320: 289037.6 | AZ320: 43.14 | BA320: 40773.23 | BB320: 6.09 | BC320: 42944.44 | BD320: 6.41 | BE320: 83717.67 | BF320: 12.5 | BG320: 161927.56 | BH320: 43392.36 | BI320: 205319.92 | BJ320: 27183.02 | BK320: 4.06 | BL320: 35777.72 | BM320: 5.34 | BN320: 62960.74 | BO320: 9.4 | BP320: 5904 | BQ320: 0.88 | BR320: 472.85 | BS320: 0.07 | BT320: 6376.85 | BU320: 0.95 | BV320: 21279.02 | BW320: 35304.87 | BX320: 56583.89
A321: =IF(A320="",,IF(A320+7<=$C$4,A320+7,"")) -> 46038 | B321: 0 | C321: 0 | D321: 171136.98 | E321: 24.91 | F321: 171136.98 | G321: 24.91 | H321: 0 | I321: 0 | J321: 567644.45 | K321: 82.65 | L321: 567644.45 | M321: 82.65 | N321: 0 | O321: -396507.44 | P321: -396507.44 | Q321: 0 | R321: 0 | S321: 152346.3 | T321: 22.17 | U321: 152346.3 | V321: 22.17 | W321: 0 | X321: 0 | Y321: 26324.45 | Z321: 3.83 | AA321: 26324.45 | AB321: 3.83 | AC321: 0 | AD321: 126021.84 | AE321: 126021.84 | AF321: 0 | AG321: 0 | AH321: 2864 | AI321: 0.42 | AJ321: 2864 | AK321: 0.42 | AL321: 0 | AM321: 0 | AN321: 207 | AO321: 0.03 | AP321: 207 | AQ321: 0.03 | AR321: 0 | AS321: 2657 | AT321: 2657 | AU321: 209582.99 | AV321: 30.5 | AW321: 88850.33 | AX321: 12.93 | AY321: 298433.32 | AZ321: 43.43 | BA321: 38633.79 | BB321: 5.62 | BC321: 47942.03 | BD321: 6.98 | BE321: 86575.82 | BF321: 12.6 | BG321: 170949.19 | BH321: 40908.3 | BI321: 211857.5 | BJ321: 27914.83 | BK321: 4.06 | BL321: 34436.16 | BM321: 5.01 | BN321: 62350.99 | BO321: 9.07 | BP321: 5474 | BQ321: 0.8 | BR321: 650.31 | BS321: 0.09 | BT321: 6124.31 | BU321: 0.89 | BV321: 22440.83 | BW321: 33785.85 | BX321: 56226.68
A322: =IF(A321="",,IF(A321+7<=$C$4,A321+7,"")) -> 46045 | B322: 0 | C322: 0 | D322: 174772.99 | E322: 25.67 | F322: 174772.99 | G322: 25.67 | H322: 0 | I322: 0 | J322: 564628.32 | K322: 82.96 | L322: 564628.32 | M322: 82.96 | N322: 0 | O322: -389855.31 | P322: -389855.31 | Q322: 0 | R322: 0 | S322: 134843.24 | T322: 19.81 | U322: 134843.24 | V322: 19.81 | W322: 0 | X322: 0 | Y322: 22323.26 | Z322: 3.28 | AA322: 22323.26 | AB322: 3.28 | AC322: 0 | AD322: 112519.98 | AE322: 112519.98 | AF322: 0 | AG322: 0 | AH322: 2659 | AI322: 0.39 | AJ322: 2659 | AK322: 0.39 | AL322: 0 | AM322: 0 | AN322: 291 | AO322: 0.04 | AP322: 291 | AQ322: 0.04 | AR322: 0 | AS322: 2368 | AT322: 2368 | AU322: 216573.75 | AV322: 31.81 | AW322: 90238.14 | AX322: 13.25 | AY322: 306811.89 | AZ322: 45.06 | BA322: 39926.79 | BB322: 5.87 | BC322: 47216.43 | BD322: 6.94 | BE322: 87143.22 | BF322: 12.81 | BG322: 176646.97 | BH322: 43021.71 | BI322: 219668.66 | BJ322: 30132.1 | BK322: 4.43 | BL322: 31620.53 | BM322: 4.64 | BN322: 61752.63 | BO322: 9.07 | BP322: 5334 | BQ322: 0.78 | BR322: 853.35 | BS322: 0.13 | BT322: 6187.35 | BU322: 0.91 | BV322: 24798.1 | BW322: 30767.18 | BX322: 55565.28
A323: =IF(A322="",,IF(A322+7<=$C$4,A322+7,"")) -> 46052 | B323: 0 | C323: 0 | D323: 162583.2 | E323: 24.49 | F323: 162583.2 | G323: 24.49 | H323: 0 | I323: 0 | J323: 546833.41 | K323: 82.39 | L323: 546833.41 | M323: 82.39 | N323: 0 | O323: -384250.25 | P323: -384250.25 | Q323: 0 | R323: 0 | S323: 124376.26 | T323: 18.74 | U323: 124376.26 | V323: 18.74 | W323: 0 | X323: 0 | Y323: 23760.24 | Z323: 3.58 | AA323: 23760.24 | AB323: 3.58 | AC323: 0 | AD323: 100616.02 | AE323: 100616.02 | AF323: 0 | AG323: 0 | AH323: 2750 | AI323: 0.41 | AJ323: 2750 | AK323: 0.41 | AL323: 0 | AM323: 0 | AN323: 602 | AO323: 0.09 | AP323: 602 | AQ323: 0.09 | AR323: 0 | AS323: 2148 | AT323: 2148 | AU323: 226524.86 | AV323: 34.13 | AW323: 88603.11 | AX323: 13.35 | AY323: 315127.97 | AZ323: 47.48 | BA323: 40790.71 | BB323: 6.15 | BC323: 45651.77 | BD323: 6.88 | BE323: 86442.48 | BF323: 13.03 | BG323: 185734.16 | BH323: 42951.34 | BI323: 228685.5 | BJ323: 30523 | BK323: 4.6 | BL323: 28394.02 | BM323: 4.28 | BN323: 58917.02 | BO323: 8.88 | BP323: 5004 | BQ323: 0.75 | BR323: 1075.67 | BS323: 0.16 | BT323: 6079.67 | BU323: 0.91 | BV323: 25519 | BW323: 27318.35 | BX323: 52837.35
A324: =IF(A323="",,IF(A323+7<=$C$4,A323+7,"")) -> 46059 | B324: 0 | C324: 0 | D324: 181259.63 | E324: 26.47 | F324: 181259.63 | G324: 26.47 | H324: 0 | I324: 0 | J324: 557867.66 | K324: 81.52 | L324: 557867.66 | M324: 81.52 | N324: 0 | O324: -376608.06 | P324: -376608.06 | Q324: 0 | R324: 0 | S324: 118295.03 | T324: 17.28 | U324: 118295.03 | V324: 17.28 | W324: 0 | X324: 0 | Y324: 24296.64 | Z324: 3.55 | AA324: 24296.64 | AB324: 3.55 | AC324: 0 | AD324: 93998.39 | AE324: 93998.39 | AF324: 0 | AG324: 0 | AH324: 2867 | AI324: 0.42 | AJ324: 2867 | AK324: 0.42 | AL324: 0 | AM324: 0 | AN324: 619 | AO324: 0.09 | AP324: 619 | AQ324: 0.09 | AR324: 0 | AS324: 2248 | AT324: 2248 | AU324: 231517.65 | AV324: 33.82 | AW324: 88349.08 | AX324: 12.91 | AY324: 319866.73 | AZ324: 46.73 | BA324: 47667.35 | BB324: 6.97 | BC324: 45952.71 | BD324: 6.72 | BE324: 93620.06 | BF324: 13.69 | BG324: 183850.31 | BH324: 42396.37 | BI324: 226246.66 | BJ324: 32625 | BK324: 4.77 | BL324: 29642.27 | BM324: 4.33 | BN324: 62267.27 | BO324: 9.1 | BP324: 5178 | BQ324: 0.76 | BR324: 2679.22 | BS324: 0.39 | BT324: 7857.22 | BU324: 1.15 | BV324: 27447 | BW324: 26963.05 | BX324: 54410.05
A325: =IF(A324="",,IF(A324+7<=$C$4,A324+7,"")) -> 46066 | B325: 0 | C325: 0 | D325: 189578.74 | E325: 27.72 | F325: 189578.74 | G325: 27.72 | H325: 0 | I325: 0 | J325: 548297.33 | K325: 80.52 | L325: 548297.33 | M325: 80.52 | N325: 0 | O325: -358718.56 | P325: -358718.56 | Q325: 0 | R325: 0 | S325: 108915.92 | T325: 15.92 | U325: 108915.92 | V325: 15.92 | W325: 0 | X325: 0 | Y325: 26506.49 | Z325: 3.89 | AA325: 26506.49 | AB325: 3.89 | AC325: 0 | AD325: 82409.43 | AE325: 82409.43 | AF325: 0 | AG325: 0 | AH325: 3112 | AI325: 0.45 | AJ325: 3112 | AK325: 0.45 | AL325: 0 | AM325: 0 | AN325: 97 | AO325: 0.01 | AP325: 97 | AQ325: 0.01 | AR325: 0 | AS325: 3015 | AT325: 3015 | AU325: 224291.18 | AV325: 32.79 | AW325: 86167.7 | AX325: 12.6 | AY325: 310458.88 | AZ325: 45.39 | BA325: 46423.85 | BB325: 6.82 | BC325: 43960.77 | BD325: 6.46 | BE325: 90384.62 | BF325: 13.28 | BG325: 177867.34 | BH325: 42206.93 | BI325: 220074.25 | BJ325: 45866.44 | BK325: 6.7 | BL325: 26152.27 | BM325: 3.82 | BN325: 72018.71 | BO325: 10.52 | BP325: 8279 | BQ325: 1.22 | BR325: 7325.36 | BS325: 1.08 | BT325: 15604.36 | BU325: 2.3 | BV325: 37587.44 | BW325: 18826.91 | BX325: 56414.35
A326: =IF(A325="",,IF(A325+7<=$C$4,A325+7,"")) -> 46073 | B326: 0 | C326: 0 | D326: 203358.76 | E326: 29.81 | F326: 203358.76 | G326: 29.81 | H326: 0 | I326: 0 | J326: 539848.97 | K326: 79.16 | L326: 539848.97 | M326: 79.16 | N326: 0 | O326: -336490.25 | P326: -336490.25 | Q326: 0 | R326: 0 | S326: 102188.56 | T326: 14.98 | U326: 102188.56 | V326: 14.98 | W326: 0 | X326: 0 | Y326: 33362.37 | Z326: 4.89 | AA326: 33362.37 | AB326: 4.89 | AC326: 0 | AD326: 68826.19 | AE326: 68826.19 | AF326: 0 | AG326: 0 | AH326: 3178 | AI326: 0.47 | AJ326: 3178 | AK326: 0.47 | AL326: 0 | AM326: 0 | AN326: 580 | AO326: 0.09 | AP326: 580 | AQ326: 0.09 | AR326: 0 | AS326: 2598 | AT326: 2598 | AU326: 219931.49 | AV326: 32.25 | AW326: 85490.86 | AX326: 12.54 | AY326: 305422.35 | AZ326: 44.79 | BA326: 42933.8 | BB326: 6.3 | BC326: 50288.3 | BD326: 7.37 | BE326: 93222.1 | BF326: 13.67 | BG326: 176997.69 | BH326: 35202.56 | BI326: 212200.25 | BJ326: 40552.83 | BK326: 5.95 | BL326: 27296.04 | BM326: 4 | BN326: 67848.87 | BO326: 9.95 | BP326: 8421 | BQ326: 1.23 | BR326: 6524.91 | BS326: 0.96 | BT326: 14945.91 | BU326: 2.19 | BV326: 32131.83 | BW326: 20771.13 | BX326: 52902.96
A327: =IF(A326="",,IF(A326+7<=$C$4,A326+7,"")) -> 46080 | B327: 0 | C327: 0 | D327: 190489.97 | E327: 28.39 | F327: 190489.97 | G327: 28.39 | H327: 0 | I327: 0 | J327: 523475.81 | K327: 78 | L327: 523475.81 | M327: 78 | N327: 0 | O327: -332985.84 | P327: -332985.84 | Q327: 0 | R327: 0 | S327: 99854.28 | T327: 14.88 | U327: 99854.28 | V327: 14.88 | W327: 0 | X327: 0 | Y327: 36659.93 | Z327: 5.46 | AA327: 36659.93 | AB327: 5.46 | AC327: 0 | AD327: 63194.35 | AE327: 63194.35 | AF327: 0 | AG327: 0 | AH327: 3247 | AI327: 0.48 | AJ327: 3247 | AK327: 0.48 | AL327: 0 | AM327: 0 | AN327: 559 | AO327: 0.08 | AP327: 559 | AQ327: 0.08 | AR327: 0 | AS327: 2688 | AT327: 2688 | AU327: 224885.66 | AV327: 33.51 | AW327: 84453.91 | AX327: 12.58 | AY327: 309339.57 | AZ327: 46.09 | BA327: 40014.78 | BB327: 5.96 | BC327: 55109.12 | BD327: 8.21 | BE327: 95123.9 | BF327: 14.17 | BG327: 184870.88 | BH327: 29344.79 | BI327: 214215.66 | BJ327: 40702.46 | BK327: 6.06 | BL327: 27548.39 | BM327: 4.1 | BN327: 68250.85 | BO327: 10.16 | BP327: 8496 | BQ327: 1.27 | BR327: 6869.02 | BS327: 1.02 | BT327: 15365.02 | BU327: 2.29 | BV327: 32206.46 | BW327: 20679.37 | BX327: 52885.83
A328: =IF(A327="",,IF(A327+7<=$C$4,A327+7,"")) -> 46087 | B328: 0 | C328: 0 | D328: 206968.05 | E328: 30.47 | F328: 206968.05 | G328: 30.47 | H328: 0 | I328: 0 | J328: 523327.61 | K328: 76.46 | L328: 523327.61 | M328: 76.46 | N328: 0 | O328: -316359.56 | P328: -316359.56 | Q328: 0 | R328: 0 | S328: 93760.32 | T328: 13.81 | U328: 93760.32 | V328: 13.81 | W328: 0 | X328: 0 | Y328: 41455.66 | Z328: 6.06 | AA328: 41455.66 | AB328: 6.06 | AC328: 0 | AD328: 52304.66 | AE328: 52304.66 | AF328: 0 | AG328: 0 | AH328: 3209 | AI328: 0.47 | AJ328: 3209 | AK328: 0.47 | AL328: 0 | AM328: 0 | AN328: 632 | AO328: 0.09 | AP328: 632 | AQ328: 0.09 | AR328: 0 | AS328: 2577 | AT328: 2577 | AU328: 217383.79 | AV328: 32.01 | AW328: 82948.38 | AX328: 12.21 | AY328: 300332.17 | AZ328: 44.22 | BA328: 42412.52 | BB328: 6.2 | BC328: 60243.7 | BD328: 8.8 | BE328: 102656.22 | BF328: 15 | BG328: 174971.28 | BH328: 22704.68 | BI328: 197675.94 | BJ328: 46503.54 | BK328: 6.85 | BL328: 28366.42 | BM328: 4.18 | BN328: 74869.96 | BO328: 11.03 | BP328: 7916 | BQ328: 1.16 | BR328: 8414.01 | BS328: 1.23 | BT328: 16330.01 | BU328: 2.39 | BV328: 38587.54 | BW328: 19952.41 | BX328: 58539.95
A329: =IF(A328="",,IF(A328+7<=$C$4,A328+7,"")) -> 46094 | B329: 0 | C329: 0 | D329: 222301.96 | E329: 31.75 | F329: 222301.96 | G329: 31.75 | H329: 0 | I329: 0 | J329: 529601.36 | K329: 75.68 | L329: 529601.36 | M329: 75.68 | N329: 0 | O329: -307299.44 | P329: -307299.44 | Q329: 0 | R329: 0 | S329: 86841 | T329: 12.41 | U329: 86841 | V329: 12.41 | W329: 0 | X329: 0 | Y329: 47835.85 | Z329: 6.83 | AA329: 47835.85 | AB329: 6.83 | AC329: 0 | AD329: 39005.15 | AE329: 39005.15 | AF329: 0 | AG329: 0 | AH329: 3199 | AI329: 0.46 | AJ329: 3199 | AK329: 0.46 | AL329: 0 | AM329: 0 | AN329: 629 | AO329: 0.09 | AP329: 629 | AQ329: 0.09 | AR329: 0 | AS329: 2570 | AT329: 2570 | AU329: 224938.04 | AV329: 32.14 | AW329: 90464.83 | AX329: 12.92 | AY329: 315402.87 | AZ329: 45.06 | BA329: 42092.42 | BB329: 6.01 | BC329: 63373.17 | BD329: 9.05 | BE329: 105465.59 | BF329: 15.06 | BG329: 182845.63 | BH329: 27091.66 | BI329: 209937.28 | BJ329: 41162.03 | BK329: 5.88 | BL329: 31060.92 | BM329: 4.44 | BN329: 72222.95 | BO329: 10.32 | BP329: 7796 | BQ329: 1.11 | BR329: 8615.97 | BS329: 1.23 | BT329: 16411.97 | BU329: 2.34 | BV329: 33366.03 | BW329: 22444.95 | BX329: 55810.98
A330: =IF(A329="",,IF(A329+7<=$C$4,A329+7,"")) -> 46101 | B330: 0 | C330: 0 | D330: 225643.99 | E330: 34.45 | F330: 225643.99 | G330: 34.45 | H330: 0 | I330: 0 | J330: 490248.65 | K330: 74.86 | L330: 490248.65 | M330: 74.86 | N330: 0 | O330: -264604.69 | P330: -264604.69 | Q330: 0 | R330: 0 | S330: 81440.86 | T330: 12.44 | U330: 81440.86 | V330: 12.44 | W330: 0 | X330: 0 | Y330: 48674.11 | Z330: 7.43 | AA330: 48674.11 | AB330: 7.43 | AC330: 0 | AD330: 32766.75 | AE330: 32766.75 | AF330: 0 | AG330: 0 | AH330: 3152 | AI330: 0.48 | AJ330: 3152 | AK330: 0.48 | AL330: 0 | AM330: 0 | AN330: 836 | AO330: 0.13 | AP330: 836 | AQ330: 0.13 | AR330: 0 | AS330: 2316 | AT330: 2316 | AU330: 189314 | AV330: 28.91 | AW330: 81265.18 | AX330: 12.41 | AY330: 270579.18 | AZ330: 41.32 | BA330: 42261.47 | BB330: 6.45 | BC330: 54414.71 | BD330: 8.31 | BE330: 96676.18 | BF330: 14.76 | BG330: 147052.53 | BH330: 26850.47 | BI330: 173903 | BJ330: 40942.21 | BK330: 6.25 | BL330: 33167.77 | BM330: 5.06 | BN330: 74109.98 | BO330: 11.31 | BP330: 9907 | BQ330: 1.51 | BR330: 8585.07 | BS330: 1.31 | BT330: 18492.07 | BU330: 2.82 | BV330: 31035.21 | BW330: 24582.7 | BX330: 55617.91
A331: =IF(A330="",,IF(A330+7<=$C$4,A330+7,"")) -> 46108 | B331: 0 | C331: 0 | D331: 178284.81 | E331: 30.52 | F331: 178284.81 | G331: 30.52 | H331: 0 | I331: 0 | J331: 446796.95 | K331: 76.51 | L331: 446796.95 | M331: 76.51 | N331: 0 | O331: -268512.13 | P331: -268512.13 | Q331: 0 | R331: 0 | S331: 74249.29 | T331: 12.72 | U331: 74249.29 | V331: 12.72 | W331: 0 | X331: 0 | Y331: 41893.39 | Z331: 7.17 | AA331: 41893.39 | AB331: 7.17 | AC331: 0 | AD331: 32355.9 | AE331: 32355.9 | AF331: 0 | AG331: 0 | AH331: 2847 | AI331: 0.49 | AJ331: 2847 | AK331: 0.49 | AL331: 0 | AM331: 0 | AN331: 724 | AO331: 0.12 | AP331: 724 | AQ331: 0.12 | AR331: 0 | AS331: 2123 | AT331: 2123 | AU331: 184919.33 | AV331: 31.67 | AW331: 77315.42 | AX331: 13.24 | AY331: 262234.75 | AZ331: 44.91 | BA331: 32166.66 | BB331: 5.51 | BC331: 44672.75 | BD331: 7.65 | BE331: 76839.41 | BF331: 13.16 | BG331: 152752.67 | BH331: 32642.67 | BI331: 185395.34 | BJ331: 31167.72 | BK331: 5.34 | BL331: 35138.07 | BM331: 6.02 | BN331: 66305.79 | BO331: 11.36 | BP331: 10248 | BQ331: 1.75 | BR331: 7525.91 | BS331: 1.29 | BT331: 17773.91 | BU331: 3.04 | BV331: 20919.72 | BW331: 27612.16 | BX331: 48531.88
A332: =IF(A331="",,IF(A331+7<=$C$4,A331+7,"")) -> 46115 | B332: #N/A N/A | C332: #N/A N/A | D332: #N/A N/A | E332: #N/A N/A | F332: #N/A N/A | G332: #N/A N/A | H332: #N/A N/A | I332: #N/A N/A | J332: #N/A N/A | K332: #N/A N/A | L332: #N/A N/A | M332: #N/A N/A | N332: #N/A N/A | O332: #N/A N/A | P332: #N/A N/A | Q332: #N/A N/A | R332: #N/A N/A | S332: #N/A N/A | T332: #N/A N/A | U332: #N/A N/A | V332: #N/A N/A | W332: #N/A N/A | X332: #N/A N/A | Y332: #N/A N/A | Z332: #N/A N/A | AA332: #N/A N/A | AB332: #N/A N/A | AC332: #N/A N/A | AD332: #N/A N/A | AE332: #N/A N/A | AF332: #N/A N/A | AG332: #N/A N/A | AH332: #N/A N/A | AI332: #N/A N/A | AJ332: #N/A N/A | AK332: #N/A N/A | AL332: #N/A N/A | AM332: #N/A N/A | AN332: #N/A N/A | AO332: #N/A N/A | AP332: #N/A N/A | AQ332: #N/A N/A | AR332: #N/A N/A | AS332: #N/A N/A | AT332: #N/A N/A | AU332: #N/A N/A | AV332: #N/A N/A | AW332: #N/A N/A | AX332: #N/A N/A | AY332: #N/A N/A | AZ332: #N/A N/A | BA332: #N/A N/A | BB332: #N/A N/A | BC332: #N/A N/A | BD332: #N/A N/A | BE332: #N/A N/A | BF332: #N/A N/A | BG332: #N/A N/A | BH332: #N/A N/A | BI332: #N/A N/A | BJ332: #N/A N/A | BK332: #N/A N/A | BL332: #N/A N/A | BM332: #N/A N/A | BN332: #N/A N/A | BO332: #N/A N/A | BP332: #N/A N/A | BQ332: #N/A N/A | BR332: #N/A N/A | BS332: #N/A N/A | BT332: #N/A N/A | BU332: #N/A N/A | BV332: #N/A N/A | BW332: #N/A N/A | BX332: #N/A N/A
A333: =IF(A332="",,IF(A332+7<=$C$4,A332+7,"")) -> 46122 | B333: 0 | C333: 0 | D333: 189679.06 | E333: 31.86 | F333: 189679.06 | G333: 31.86 | H333: 0 | I333: 0 | J333: 462821.99 | K333: 77.74 | L333: 462821.99 | M333: 77.74 | N333: 0 | O333: -273142.94 | P333: -273142.94 | Q333: 0 | R333: 0 | S333: 70885.17 | T333: 11.9 | U333: 70885.17 | V333: 11.9 | W333: 0 | X333: 0 | Y333: 36167.01 | Z333: 6.07 | AA333: 36167.01 | AB333: 6.07 | AC333: 0 | AD333: 34718.16 | AE333: 34718.16 | AF333: 0 | AG333: 0 | AH333: 2886 | AI333: 0.48 | AJ333: 2886 | AK333: 0.48 | AL333: 0 | AM333: 0 | AN333: 825 | AO333: 0.14 | AP333: 825 | AQ333: 0.14 | AR333: 0 | AS333: 2061 | AT333: 2061 | AU333: 188137.09 | AV333: 31.6 | AW333: 80441.2 | AX333: 13.51 | AY333: 268578.29 | AZ333: 45.11 | BA333: 31733.72 | BB333: 5.33 | BC333: 45805.41 | BD333: 7.69 | BE333: 77539.13 | BF333: 13.02 | BG333: 156403.38 | BH333: 34635.79 | BI333: 191039.16 | BJ333: 31205.87 | BK333: 5.24 | BL333: 32191.97 | BM333: 5.41 | BN333: 63397.84 | BO333: 10.65 | BP333: 10919 | BQ333: 1.83 | BR333: 7129.86 | BS333: 1.2 | BT333: 18048.86 | BU333: 3.03 | BV333: 20286.87 | BW333: 25062.11 | BX333: 45348.98
A334: =IF(A333="",,IF(A333+7<=$C$4,A333+7,"")) -> 46129
A335: =IF(A334="",,IF(A334+7<=$C$4,A334+7,""))
A336: =IF(A335="",,IF(A335+7<=$C$4,A335+7,"")) -> 0
A337: =IF(A336="",,IF(A336+7<=$C$4,A336+7,"")) -> 7
A338: =IF(A337="",,IF(A337+7<=$C$4,A337+7,"")) -> 14
A339: =IF(A338="",,IF(A338+7<=$C$4,A338+7,"")) -> 21
A340: =IF(A339="",,IF(A339+7<=$C$4,A339+7,"")) -> 28
A341: =IF(A340="",,IF(A340+7<=$C$4,A340+7,"")) -> 35
A342: =IF(A341="",,IF(A341+7<=$C$4,A341+7,"")) -> 42
...

Sheet Option
B2: =B3&B4 -> RK910MOA Comdty | C2: =C3&C4 -> RK903MOA Comdty | D2: =D3&D4 -> RK908MOA Comdty | E2: =E3&E4 -> RK901MOA Comdty | F2: =F3&F4 -> RK910TMR1 Comdty | G2: =G3&G4 -> RK903TMR1 Comdty | H2: =H3&H4 -> RK908TMR1 Comdty | I2: =I3&I4 -> RK901TMR1 Comdty | ... AO2: =AO3&AO4 -> RK901MO1 Comdty
B3: RK910 | C3: RK903 | D3: RK908 | E3: RK901 | F3: RK910 | G3: RK903 | H3: RK908 | I3: RK901 | J3: RK910 | K3: RK903 | L3: RK908 | M3: RK901 | N3: RK910 | O3: RK903 | P3: RK908 | Q3: RK901 | R3: RK910 | S3: RK903 | T3: RK908 | U3: RK901 | V3: RK910 | W3: RK903 | X3: RK908 | Y3: RK901 | Z3: RK910 | AA3: RK903 | AB3: RK908 | AC3: RK901 | AD3: RK910 | AE3: RK903 | AF3: RK908 | AG3: RK901 | AH3: RK910 | AI3: RK903 | AJ3: RK908 | AK3: RK901 | AL3: RK910 | AM3: RK903 | AN3: RK908 | AO3: RK901
